Workbook

Sheet DOMESTIC DEBIT
A2: Domestic Air Travel Statement for the period 16-08-2026 to 31-08-2026
A3: Reference No. | B3: Reference Date | C3: Booking Date | D3: Department | E3: Location | F3: Passenger Name | G3: Employee Code | H3: Cost Center | I3: Cost Code | J3: Product Line | K3: Travel Date | L3: Sector | M3: Airline | N3: Flight No. | O3: Class | P3: Ticket No. | Q3: Taxable Fare | R3: Exempt Fare | S3: Other Taxes | T3: Airline GST | U3: Total Fare | V3: Travel Management Fee | W3: Approver Name | X3: Approval Status | Y3: Approval Date | Z3: Approval Time | AA3: Flown Status | AB3: Corporate | AC3: Business Unit | AD3: Booking Reference No. | AE3: Trip Unique ID | AF3: Designation | AG3: Type Of Journey | AH3: Type Of Travel | AI3: Job Band | AJ3: Passenger Email Id | AK3: Booking Code | AL3: YQ | AM3: YR | AN3: Request No. | AO3: Request Created Date | AP3: Request Created Time | AQ3: Trip Title | AR3: Fare Type | AS3: Purpose of Visit | AT3: Reissue Status | AU3: Second Approver Name | AV3: Second Approval Status | AW3: Second Approval Date | AX3: Second Approval Time | AY3: Contact No. | AZ3: GST No. | BA3: GST State | BB3: Full Ticket No. | BC3: Airline PNR | BD3: XL Code | BE3: Project | BF3: HSN Code | BG3: Only Travel Date | BH3: Requester Name | BI3: Requester Empid | BJ3: KMS | BK3: Client Req No | BL3: AIR IGST | BM3: AIR CGST | BN3: AIR SGST | BO3: Carbon Emission (Metric Tonnes) | BP3: Arrival Date | BQ3: Event Name | BR3: TR ID | BS3: Debit Cost Code | BT3: Function | BU3: PLANNED_TIME_IN_DAYS | BV3: Source Destination City | BW3: Referred by | BX3: GL Code | BY3: Job Type | BZ3: Division Name | CA3: K3 | CB3: SAP / HR Company Code | CC3: Adani Legal Entity GST Number | CD3: Location Code | CE3: Gender | CF3: Unique ID | CG3: Job Reason | CH3: CC_AUTHCODE | CI3: Zone | CJ3: FIRST_APP_emp_id | CK3: FIRST_APP_mgmtl_name | CL3: SECOND_APP_emp_id | CM3: SECOND_APP_mgmtl_name
A4: DW26/780819 | B4: 16-AUG-2026 | C4: 16-AUG-2026 | D4: Administration | E4: Delhi | F4: MR. M A SIKANDAR | G4: CQ00873075 | H4: NA | I4: NA | K4: 22-08-2026 22:45:00 | L4: Kannur-New Delhi | M4: Indigo | N4: 6E-6148 | O4: Economy | P4: DBS17D | Q4: 17160 | R4: 0 | S4: 1432 | T4: 858 | U4: 19450 | V4: 75 | W4: MS. PRIYANKA THAKUR | X4: Approved | Y4: 16-AUG-2026 | Z4: 12:06 | AA4: FLOWN | AB4: Teamlease Services Ltd | AC4: TLEdtech | AD4: 200117939470 | AE4: 7582415 | AF4: Consultant | AG4: Round Trip | AH4: Domestic | AI4: Consultant | AJ4: masikandar@jamiahamdard.ac.in | AK4: H | AL4: 800 | AM4: 0 | AN4: 44715644 | AO4: 16-AUG-2026 | AP4: 11:56 | AR4: CORPORATE | AS4: Official | AT4: Original | AY4: 9818798949 | AZ4: 27AAPCS2871R1ZB | BA4: Maharashtra | BB4: DBS17D | BC4: DBS17D | BD4: T004S | BE4: - | BF4: 996425 | BG4: 22-08-202/ | BH4: Mr. Satyavan Sawant | BI4: T17247 | BJ4: 1858 | BL4: 858 | BM4: 0 | BN4: 0 | BO4: 0.2952362 | BP4: 23-08-2026 01:45:00 | BU4: 6 | BV4: CNN-DEL | CA4: 858 | CB4: TeamLease Edtech Limited | CC4: 27AAPCS2871R1ZB | CE4: M | CF4: '11793947008222245 | CJ4: T16868 | CK4: L3
A5: DW26/782230 | B5: 16-AUG-2026 | C5: 16-AUG-2026 | D5: Administration | E5: Delhi | F5: MR. ABDUL FAROOQI | G5: CQ00873076 | H5: NA | I5: NA | K5: 22-08-2026 22:45:00 | L5: Kannur-New Delhi | M5: Indigo | N5: 6E-6148 | O5: Economy | P5: ZD8CPG | Q5: 17160 | R5: 0 | S5: 1432 | T5: 858 | U5: 19450 | V5: 75 | W5: MS. PRIYANKA THAKUR | X5: Approved | Y5: 16-AUG-2026 | Z5: 12:06 | AA5: RFND | AB5: Teamlease Services Ltd | AC5: TLEdtech | AD5: 200117939474 | AE5: 7582416 | AF5: Consultant | AG5: Round Trip | AH5: Domestic | AI5: Consultant | AJ5: majid@jamiahamdard.ac.in | AK5: H | AL5: 800 | AM5: 0 | AN5: 44715674 | AO5: 16-AUG-2026 | AP5: 12:00 | AR5: CORPORATE | AS5: Official | AT5: Original | AY5: 9891958565 | AZ5: 27AAPCS2871R1ZB | BA5: Maharashtra | BB5: ZD8CPG | BC5: ZD8CPG | BD5: T004S | BE5: - | BF5: 996425 | BG5: 22-08-202/ | BH5: Mr. Satyavan Sawant | BI5: T17247 | BJ5: 1858 | BL5: 858 | BM5: 0 | BN5: 0 | BO5: 0.2952362 | BP5: 23-08-2026 01:45:00 | BU5: 6 | BV5: CNN-DEL | CA5: 858 | CB5: TeamLease Edtech Limited | CC5: 27AAPCS2871R1ZB | CE5: M | CF5: '11793947408222245 | CJ5: T16868 | CK5: L3
A6: DW26/781796 | B6: 16-AUG-2026 | C6: 16-AUG-2026 | D6: Administration | E6: Delhi | F6: MR. ABDUL FAROOQI | G6: CQ00873076 | H6: NA | I6: NA | K6: 19-08-2026 09:30:00/19-08-2026 13:35:00 | L6: New Delhi-Mumbai/Mumbai-Kannur | M6: Indigo/Indigo | N6: 6E-6107/6E-2011 | O6: Economy | P6: SH8JWH | Q6: 9800 | R6: 0 | S6: 382 | T6: 490 | U6: 10672 | V6: 150 | W6: MS. PRIYANKA THAKUR | X6: Approved | Y6: 16-AUG-2026 | Z6: 12:06 | AA6: RFND/RFND | AB6: Teamlease Services Ltd | AC6: TLEdtech | AD6: 200117939473 | AE6: 7582416 | AF6: Consultant | AG6: Round Trip | AH6: Domestic | AI6: Consultant | AJ6: majid@jamiahamdard.ac.in | AK6: R/R | AL6: 1000 | AM6: 0 | AN6: 44715674 | AO6: 16-AUG-2026 | AP6: 12:00 | AR6: CORPORATE | AS6: Official | AT6: Original | AY6: 9891958565 | AZ6: 27AAPCS2871R1ZB | BA6: Maharashtra | BB6: SH8JWH | BC6: SH8JWH | BD6: T004S | BE6: - | BF6: 996425 | BG6: 19-08-202//19-08-20 | BH6: Mr. Satyavan Sawant | BI6: T17247 | BJ6: 1139/848 | BL6: 490 | BM6: 0 | BN6: 0 | BO6: 0.3157343 | BP6: 19-08-2026 11:55:00/19-08-2026 15:15:00 | BU6: 3 | BV6: DEL-CNN | CA6: 490 | CB6: TeamLease Edtech Limited | CC6: 27AAPCS2871R1ZB | CE6: M | CF6: '11793947308190930/11793947308191335 | CJ6: T16868 | CK6: L3
A7: DW26/780892 | B7: 16-AUG-2026 | C7: 16-AUG-2026 | D7: Administration | E7: Delhi | F7: MR. M A SIKANDAR | G7: CQ00873075 | H7: NA | I7: NA | K7: 19-08-2026 09:30:00/19-08-2026 13:35:00 | L7: New Delhi-Mumbai/Mumbai-Kannur | M7: Indigo/Indigo | N7: 6E-6107/6E-2011 | O7: Economy | P7: EBE7FG | Q7: 9800 | R7: 0 | S7: 382 | T7: 490 | U7: 10672 | V7: 150 | W7: MS. PRIYANKA THAKUR | X7: Approved | Y7: 16-AUG-2026 | Z7: 12:06 | AA7: FLOWN/FLOWN | AB7: Teamlease Services Ltd | AC7: TLEdtech | AD7: 200117939469 | AE7: 7582415 | AF7: Consultant | AG7: Round Trip | AH7: Domestic | AI7: Consultant | AJ7: masikandar@jamiahamdard.ac.in | AK7: R/R | AL7: 1000 | AM7: 0 | AN7: 44715644 | AO7: 16-AUG-2026 | AP7: 11:56 | AR7: CORPORATE | AS7: Official | AT7: Original | AY7: 9818798949 | AZ7: 27AAPCS2871R1ZB | BA7: Maharashtra | BB7: EBE7FG | BC7: EBE7FG | BD7: T004S | BE7: - | BF7: 996425 | BG7: 19-08-202//19-08-20 | BH7: Mr. Satyavan Sawant | BI7: T17247 | BJ7: 1139/848 | BL7: 490 | BM7: 0 | BN7: 0 | BO7: 0.3157343 | BP7: 19-08-2026 11:55:00/19-08-2026 15:15:00 | BU7: 3 | BV7: DEL-CNN | CA7: 490 | CB7: TeamLease Edtech Limited | CC7: 27AAPCS2871R1ZB | CE7: M | CF7: '11793946908190930/11793946908191335 | CJ7: T16868 | CK7: L3
A8: DW26/782006 | B8: 16-AUG-2026 | C8: 16-AUG-2026 | D8: University B2C | E8: Bengaluru | F8: MR. CHETAN DIXIT | G8: SG0506 | H8: 3701618 | I8: 62-MUM-SSS | K8: 19-08-2026 09:30:00/19-08-2026 13:35:00 | L8: New Delhi-Mumbai/Mumbai-Kannur | M8: Indigo/Indigo | N8: 6E-6107/6E-2011 | O8: Economy | P8: W662SL | Q8: 10620 | R8: 0 | S8: 702 | T8: 531 | U8: 11853 | V8: 150 | W8: MR. UDITENDU BOSE | X8: Approved | Y8: 16-AUG-2026 | Z8: 16:43 | AA8: FLOWN/FLOWN | AB8: Teamlease Services Ltd | AC8: TLEdtech | AD8: 200117942128 | AE8: 1388660 | AF8: Vertical Head - Consumer Business | AG8: Round Trip | AH8: Domestic | AI8: L9 | AJ8: chetan.dixit@teamlease.com | AK8: Q/Q | AL8: 1000 | AM8: 0 | AN8: 44718713 | AO8: 16-AUG-2026 | AP8: 16:38 | AR8: CORPORATE | AS8: Official | AT8: Original | AY8: 9811525485 | AZ8: 29AAPCS2871R1Z7 | BA8: Karnataka | BB8: W662SL | BC8: W662SL | BD8: T004S | BE8: - | BF8: 996425 | BG8: 19-08-202//19-08-20 | BH8: Mr. Satyavan Sawant | BI8: T17247 | BJ8: 1139/848 | BL8: 531 | BM8: 0 | BN8: 0 | BO8: 0.3157343 | BP8: 19-08-2026 11:55:00/19-08-2026 15:15:00 | BU8: 3 | BV8: DEL-CNN | CA8: 531 | CB8: TeamLease Edtech Limited | CC8: 29AAPCS2871R1Z7 | CE8: M | CF8: '11794212808190930/11794212808191335 | CJ8: SG0320 | CK8: L10
A9: DW26/780625 | B9: 16-AUG-2026 | C9: 16-AUG-2026 | D9: University B2C | E9: Bengaluru | F9: MR. CHETAN DIXIT | G9: SG0506 | H9: 3701618 | I9: 62-MUM-SSS | K9: 22-08-2026 22:45:00 | L9: Kannur-New Delhi | M9: Indigo | N9: 6E-6148 | O9: Economy | P9: A72B5C | Q9: 17160 | R9: 0 | S9: 1786 | T9: 858 | U9: 19804 | V9: 75 | W9: MR. UDITENDU BOSE | X9: Approved | Y9: 16-AUG-2026 | Z9: 16:43 | AA9: FLOWN | AB9: Teamlease Services Ltd | AC9: TLEdtech | AD9: 200117942129 | AE9: 1388660 | AF9: Vertical Head - Consumer Business | AG9: Round Trip | AH9: Domestic | AI9: L9 | AJ9: chetan.dixit@teamlease.com | AK9: H | AL9: 800 | AM9: 0 | AN9: 44718713 | AO9: 16-AUG-2026 | AP9: 16:38 | AR9: CORPORATE | AS9: Official | AT9: Original | AY9: 9811525485 | AZ9: 29AAPCS2871R1Z7 | BA9: Karnataka | BB9: A72B5C | BC9: A72B5C | BD9: T004S | BE9: - | BF9: 996425 | BG9: 22-08-202/ | BH9: Mr. Satyavan Sawant | BI9: T17247 | BJ9: 1858 | BL9: 858 | BM9: 0 | BN9: 0 | BO9: 0.2952362 | BP9: 23-08-2026 01:45:00 | BU9: 6 | BV9: CNN-DEL | CA9: 858 | CB9: TeamLease Edtech Limited | CC9: 29AAPCS2871R1Z7 | CE9: M | CF9: '11794212908222245 | CJ9: SG0320 | CK9: L10
A10: DW26/781991 | B10: 16-AUG-2026 | C10: 16-AUG-2026 | D10: Administration | E10: Delhi | F10: MR. ABDUL MAJID FAROOQI | G10: CQ00873076 | H10: NA | I10: NA | K10: 19-08-2026 09:30:00/19-08-2026 13:35:00 | L10: New Delhi-Mumbai/Mumbai-Kannur | M10: Indigo/Indigo | N10: 6E-6107/6E-2011 | O10: Economy | P10: VHYEPH | Q10: 10620 | R10: 0 | S10: 389 | T10: 531 | U10: 11540 | V10: 150 | W10: MS. PRIYANKA THAKUR | X10: Approved | Y10: 16-AUG-2026 | Z10: 16:47 | AA10: FLOWN/FLOWN | AB10: Teamlease Services Ltd | AC10: TLEdtech | AD10: 200117942152 | AE10: 7582416 | AF10: Consultant | AG10: Round Trip | AH10: Domestic | AI10: Consultant | AJ10: majid@jamiahamdard.ac.in | AK10: Q/Q | AL10: 1000 | AM10: 0 | AN10: 44718750 | AO10: 16-AUG-2026 | AP10: 16:43 | AR10: CORPORATE | AS10: Official | AT10: Original | AY10: 9891958565 | AZ10: 27AAPCS2871R1ZB | BA10: Maharashtra | BB10: VHYEPH | BC10: VHYEPH | BD10: T004S | BE10: - | BF10: 996425 | BG10: 19-08-202//19-08-20 | BH10: Mr. Satyavan Sawant | BI10: T17247 | BJ10: 1139/848 | BL10: 531 | BM10: 0 | BN10: 0 | BO10: 0.3157343 | BP10: 19-08-2026 11:55:00/19-08-2026 15:15:00 | BU10: 3 | BV10: DEL-CNN | CA10: 531 | CB10: TeamLease Edtech Limited | CC10: 27AAPCS2871R1ZB | CE10: M | CF10: '11794215208190930/11794215208191335 | CJ10: T16868 | CK10: L3
A11: DW26/781403 | B11: 16-AUG-2026 | C11: 16-AUG-2026 | D11: Administration | E11: Delhi | F11: MR. ABDUL MAJID FAROOQI | G11: CQ00873076 | H11: NA | I11: NA | K11: 22-08-2026 22:45:00 | L11: Kannur-New Delhi | M11: Indigo | N11: 6E-6148 | O11: Economy | P11: MBF3YJ | Q11: 17160 | R11: 0 | S11: 1432 | T11: 858 | U11: 19450 | V11: 75 | W11: MS. PRIYANKA THAKUR | X11: Approved | Y11: 16-AUG-2026 | Z11: 16:47 | AA11: FLOWN | AB11: Teamlease Services Ltd | AC11: TLEdtech | AD11: 200117942153 | AE11: 7582416 | AF11: Consultant | AG11: Round Trip | AH11: Domestic | AI11: Consultant | AJ11: majid@jamiahamdard.ac.in | AK11: H | AL11: 800 | AM11: 0 | AN11: 44718750 | AO11: 16-AUG-2026 | AP11: 16:43 | AR11: CORPORATE | AS11: Official | AT11: Original | AY11: 9891958565 | AZ11: 27AAPCS2871R1ZB | BA11: Maharashtra | BB11: MBF3YJ | BC11: MBF3YJ | BD11: T004S | BE11: - | BF11: 996425 | BG11: 22-08-202/ | BH11: Mr. Satyavan Sawant | BI11: T17247 | BJ11: 1858 | BL11: 858 | BM11: 0 | BN11: 0 | BO11: 0.2952362 | BP11: 23-08-2026 01:45:00 | BU11: 6 | BV11: CNN-DEL | CA11: 858 | CB11: TeamLease Edtech Limited | CC11: 27AAPCS2871R1ZB | CE11: M | CF11: '11794215308222245 | CJ11: T16868 | CK11: L3
A12: DW26/785455 | B12: 17-AUG-2026 | C12: 17-AUG-2026 | D12: Leadership | E12: Bengaluru | F12: MR. SHANTANU ROOJ | G12: SG0014 | H12: 3701618 | I12: 68-MUM-LED | K12: 26-08-2026 07:45:00 | L12: Mumbai-Kolkata | M12: Indigo | N12: 6E-5329 | O12: Economy | P12: K6J34F | Q12: 7920 | R12: 0 | S12: 440 | T12: 396 | U12: 8756 | V12: 0 | W12: MR. SHANTANU ROOJ | X12: Approved | Y12: 17-AUG-2026 | Z12: 15:11 | AA12: RFND | AB12: Teamlease Services Ltd | AC12: TLEdtech | AD12: 200117956566 | AE12: 1388000 | AF12: Founder and CEO | AG12: Round Trip | AH12: Domestic | AI12: LST | AJ12: shantanu@teamlease.com | AK12: Q | AL12: 800 | AM12: 0 | AN12: 44739307 | AO12: 17-AUG-2026 | AP12: 14:38 | AR12: CORPORATE | AS12: Official | AT12: Original | AY12: 9870333111 | AZ12: 29AAPCS2871R1Z7 | BA12: Karnataka | BB12: K6J34F | BC12: K6J34F | BD12: T004S | BE12: - | BF12: 996425 | BG12: 26-08-202/ | BH12: Mr. Shantanu Rooj | BI12: SG0014 | BJ12: 1665 | BL12: 396 | BM12: 0 | BN12: 0 | BO12: 0.2645685 | BP12: 26-08-2026 10:30:00 | BU12: 9 | BV12: BOM-CCU | CA12: 396 | CB12: TeamLease Edtech Limited | CC12: 29AAPCS2871R1Z7 | CE12: M | CF12: '11795656608260745 | CJ12: SG0014 | CK12: LST
A13: DW26/783895 | B13: 17-AUG-2026 | C13: 17-AUG-2026 | D13: Leadership | E13: Bengaluru | F13: MR. SHANTANU ROOJ | G13: SG0014 | H13: 3701618 | I13: 68-MUM-LED | K13: 26-08-2026 18:45:00 | L13: Kolkata-Mumbai | M13: Indigo | N13: 6E-5128 | O13: Economy | P13: BYCZRJ | Q13: 7920 | R13: 0 | S13: 967 | T13: 396 | U13: 9283 | V13: 0 | W13: MR. SHANTANU ROOJ | X13: Approved | Y13: 17-AUG-2026 | Z13: 15:11 | AA13: RFND | AB13: Teamlease Services Ltd | AC13: TLEdtech | AD13: 200117956567 | AE13: 1388000 | AF13: Founder and CEO | AG13: Round Trip | AH13: Domestic | AI13: LST | AJ13: shantanu@teamlease.com | AK13: Q | AL13: 800 | AM13: 0 | AN13: 44739307 | AO13: 17-AUG-2026 | AP13: 14:38 | AR13: CORPORATE | AS13: Official | AT13: Original | AY13: 9870333111 | AZ13: 29AAPCS2871R1Z7 | BA13: Karnataka | BB13: BYCZRJ | BC13: BYCZRJ | BD13: T004S | BE13: - | BF13: 996425 | BG13: 26-08-202/ | BH13: Mr. Shantanu Rooj | BI13: SG0014 | BJ13: 1665 | BL13: 396 | BM13: 0 | BN13: 0 | BO13: 0.2645685 | BP13: 26-08-2026 21:30:00 | BU13: 9 | BV13: CCU-BOM | CA13: 396 | CB13: TeamLease Edtech Limited | CC13: 29AAPCS2871R1Z7 | CE13: M | CF13: '11795656708261845 | CJ13: SG0014 | CK13: LST
A14: DW26/785429 | B14: 17-AUG-2026 | C14: 17-AUG-2026 | D14: Operations | E14: Bengaluru | F14: MR. ROSHAN DEEPAK PINTO | G14: T11294 | H14: 3701618 | I14: 67-MUM-ELO | K14: 26-08-2026 22:00:00 | L14: New Delhi-Bangalore | M14: Indigo | N14: 6E-0846 | O14: Economy | P14: JYRBGJ | Q14: 8280 | R14: 0 | S14: 382 | T14: 414 | U14: 9076 | V14: 75 | W14: MR. JAIDEEP KEWALRAMANI | X14: Approved | Y14: 17-AUG-2026 | Z14: 23:57 | AA14: FLOWN | AB14: Teamlease Services Ltd | AC14: TLEdtech | AD14: 200117967830 | AE14: 1388166 | AF14: Senior General Manager | AG14: Round Trip | AH14: Domestic | AI14: L9 | AJ14: roshan.pinto@teamlease.com | AK14: R | AL14: 800 | AM14: 0 | AN14: 44724877 | AO14: 17-AUG-2026 | AP14: 09:44 | AR14: CORPORATE | AS14: Official | AT14: Original | AY14: 9743374888 | AZ14: 29AAPCS2871R1Z7 | BA14: Karnataka | BB14: JYRBGJ | BC14: JYRBGJ | BD14: T004S | BE14: - | BF14: 996425 | BG14: 26-08-202/ | BH14: MR. Roshan Deepak Pinto | BI14: T11294 | BJ14: 1709 | BL14: 414 | BM14: 0 | BN14: 0 | BO14: 0.2715601 | BP14: 27-08-2026 00:55:00 | BU14: 9 | BV14: DEL-BLR | CA14: 414 | CB14: TeamLease Edtech Limited | CC14: 29AAPCS2871R1Z7 | CE14: M | CF14: '11796783008262200 | CJ14: T12553 | CK14: LST
A15: DW26/784868 | B15: 17-AUG-2026 | C15: 17-AUG-2026 | D15: Operations | E15: Bengaluru | F15: MR. ROSHAN DEEPAK PINTO | G15: T11294 | H15: 3701618 | I15: 67-MUM-ELO | K15: 24-08-2026 18:15:00 | L15: Bangalore-New Delhi | M15: Indigo | N15: 6E-6034 | O15: Economy | P15: H55U3Y | Q15: 8140 | R15: 0 | S15: 958 | T15: 407 | U15: 9505 | V15: 75 | W15: MR. JAIDEEP KEWALRAMANI | X15: Approved | Y15: 17-AUG-2026 | Z15: 23:57 | AA15: FLOWN | AB15: Teamlease Services Ltd | AC15: TLEdtech | AD15: 200117967829 | AE15: 1388166 | AF15: Senior General Manager | AG15: Round Trip | AH15: Domestic | AI15: L9 | AJ15: roshan.pinto@teamlease.com | AK15: Q | AL15: 800 | AM15: 0 | AN15: 44724877 | AO15: 17-AUG-2026 | AP15: 09:44 | AR15: CORPORATE | AS15: Official | AT15: Original | AY15: 9743374888 | AZ15: 29AAPCS2871R1Z7 | BA15: Karnataka | BB15: H55U3Y | BC15: H55U3Y | BD15: T004S | BE15: - | BF15: 996425 | BG15: 24-08-202/ | BH15: MR. Roshan Deepak Pinto | BI15: T11294 | BJ15: 1709 | BL15: 0 | BM15: 0 | BN15: 0 | BO15: 0.2715601 | BP15: 24-08-2026 21:05:00 | BU15: 7 | BV15: BLR-DEL | CA15: 407 | CB15: TeamLease Edtech Limited | CC15: 29AAPCS2871R1Z7 | CE15: M | CF15: '11796782908241815 | CJ15: T12553 | CK15: LST
A16: DW26/795993 | B16: 18-AUG-2026 | C16: 18-AUG-2026 | D16: University Bd | E16: Bengaluru | F16: MR. ASHUTOSH DUBEY | G16: T17010 | I16: 61-MUM-USE | K16: 24-08-2026 08:10:00 | L16: New Delhi-Guwahati | M16: AirIndia Express | N16: IX-1035 | O16: Economy | P16: R4C82C | Q16: 0 | R16: 6723 | S16: 1595 | T16: 0 | U16: 8318 | V16: 75 | W16: MR. MAHESH KUMAR | X16: Approved | Y16: 18-AUG-2026 | Z16: 10:15 | AA16: FLOWN | AB16: Teamlease Services Ltd | AC16: TLEdtech | AD16: 200117970188 | AE16: 6003228 | AF16: Senior Manager | AG16: One Way | AH16: Domestic | AI16: L7 | AJ16: ashutosh.dubey@teamlease.com | AK16: G | AL16: 549 | AM16: 0 | AN16: 44759631 | AO16: 18-AUG-2026 | AP16: 10:01 | AR16: CORPORATE | AS16: Official | AT16: Original | AY16: 8010118799 | AZ16: 29AAPCS2871R1Z7 | BA16: Karnataka | BB16: R4C82C | BC16: R4C82C | BD16: T004S | BE16: - | BF16: 996425 | BG16: 24-08-202/ | BH16: Mr. ASHUTOSH DUBEY | BI16: T17010 | BJ16: 1454 | BL16: 0 | BM16: 0 | BN16: 0 | BO16: 0.2310406 | BP16: 24-08-2026 10:40:00 | BU16: 6 | BV16: DEL-GAU | CA16: 0 | CB16: TeamLease Edtech Limited | CC16: 29AAPCS2871R1Z7 | CE16: M | CF16: '11797018808240810 | CJ16: T15604 | CK16: L8
A17: DA26/178427 | B17: 18-AUG-2026 | C17: 18-AUG-2026 | D17: Operations | E17: Bengaluru | F17: MR. AAYUSH LAL | G17: T16161 | I17: 69-MUM-PBP | K17: 21-08-2026 23:20:00 | L17: Chennai-New Delhi | M17: Air India | N17: AI-1845 | O17: Economy | P17: 5808869063 | Q17: 13300 | R17: 0 | S17: 787 | T17: 665 | U17: 14752 | V17: 75 | W17: MS. NIDHI RAJESH BAGLA | X17: Approved | Y17: 18-AUG-2026 | Z17: 10:43 | AA17: FLOWN | AB17: Teamlease Services Ltd | AC17: TLEdtech | AD17: 200117970808 | AE17: 3937212 | AF17: Senior Project Manager | AG17: Round Trip | AH17: Domestic | AI17: L7 | AJ17: aayush.lal@teamlease.com | AK17: K | AL17: 749 | AM17: 170 | AN17: 44725527 | AO17: 18-AUG-2026 | AP17: 10:31 | AR17: CORPORATE | AS17: Official | AT17: Original | AY17: 7076663907 | AZ17: 29AAPCS2871R1Z7 | BA17: Karnataka | BB17: '0985808869063 | BC17: E8LTZ6 | BD17: T004S | BE17: - | BF17: 996425 | BG17: 21-08-202/ | BH17: Mr. AAYUSH LAL | BI17: T16161 | BJ17: 1760 | BL17: 0 | BM17: 0 | BN17: 0 | BO17: 0.279664 | BP17: 22-08-2026 02:15:00 | BU17: 3 | BV17: MAA-DEL | CA17: 665 | CB17: TeamLease Edtech Limited | CC17: 29AAPCS2871R1Z7 | CE17: M | CF17: '11797080808212320 | CJ17: T17642 | CK17: L8
A18: DW26/796548 | B18: 18-AUG-2026 | C18: 18-AUG-2026 | D18: Operations | E18: Bengaluru | F18: MR. AAYUSH LAL | G18: T16161 | I18: 69-MUM-PBP | K18: 19-08-2026 14:30:00 | L18: New Delhi-Chennai | M18: SpiceJet | N18: SG-9300 | O18: Economy | P18: FFKVQD | Q18: 7760 | R18: 0 | S18: 378 | T18: 388 | U18: 8526 | V18: 75 | W18: MS. NIDHI RAJESH BAGLA | X18: Approved | Y18: 18-AUG-2026 | Z18: 10:43 | AA18: RFND | AB18: Teamlease Services Ltd | AC18: TLEdtech | AD18: 200117970807 | AE18: 3937212 | AF18: Senior Project Manager | AG18: Round Trip | AH18: Domestic | AI18: L7 | AJ18: aayush.lal@teamlease.com | AK18: W | AL18: 699 | AM18: 0 | AN18: 44725527 | AO18: 18-AUG-2026 | AP18: 10:31 | AR18: CORPORATE | AS18: Official | AT18: Original | AY18: 7076663907 | AZ18: 29AAPCS2871R1Z7 | BA18: Karnataka | BB18: FFKVQD | BC18: FFKVQD | BD18: T004S | BE18: - | BF18: 996425 | BG18: 19-08-202/ | BH18: Mr. AAYUSH LAL | BI18: T16161 | BJ18: 1760 | BL18: 388 | BM18: 0 | BN18: 0 | BO18: 0.279664 | BP18: 19-08-2026 17:30:00 | BU18: 1 | BV18: DEL-MAA | CA18: 388 | CB18: TeamLease Edtech Limited | CC18: 29AAPCS2871R1Z7 | CE18: M | CF18: '11797080708191430 | CJ18: T17642 | CK18: L8
A19: DW26/791733 | B19: 18-AUG-2026 | C19: 18-AUG-2026 | D19: Operations | E19: Bengaluru | F19: MR. AAYUSH LAL | G19: T16161 | I19: 69-MUM-PBP | K19: 25-08-2026 09:10:00 | L19: New Delhi-Gaya | M19: Indigo | N19: 6E-2448 | O19: Economy | P19: CDD3JA | Q19: 6100 | R19: 0 | S19: 381 | T19: 305 | U19: 6786 | V19: 75 | W19: MS. NIDHI RAJESH BAGLA | X19: Approved | Y19: 18-AUG-2026 | Z19: 16:34 | AA19: FLOWN | AB19: Teamlease Services Ltd | AC19: TLEdtech | AD19: 200117979769 | AE19: 3937212 | AF19: Senior Project Manager | AG19: One Way | AH19: Domestic | AI19: L7 | AJ19: aayush.lal@teamlease.com | AK19: O | AL19: 400 | AM19: 0 | AN19: 44773152 | AO19: 18-AUG-2026 | AP19: 15:36 | AR19: CORPORATE | AS19: Scheduled Visit | AT19: Original | AY19: 7076663907 | AZ19: 29AAPCS2871R1Z7 | BA19: Karnataka | BB19: CDD3JA | BC19: CDD3JA | BD19: T004S | BE19: - | BF19: 996425 | BG19: 25-08-202/ | BH19: Mr. AAYUSH LAL | BI19: T16161 | BJ19: 886 | BL19: 305 | BM19: 0 | BN19: 0 | BO19: 0.1407854 | BP19: 25-08-2026 11:00:00 | BU19: 7 | BV19: DEL-GAY | CA19: 305 | CB19: TeamLease Edtech Limited | CC19: 29AAPCS2871R1Z7 | CE19: M | CF19: '11797976908250910 | CJ19: T17642 | CK19: L8
A20: DW26/791750 | B20: 18-AUG-2026 | C20: 18-AUG-2026 | D20: Operations | E20: Bengaluru | F20: MR. AAYUSH LAL | G20: T16161 | I20: 69-MUM-PBP | K20: 30-08-2026 20:35:00 | L20: Ranchi-New Delhi | M20: Indigo | N20: 6E-6274 | O20: Economy | P20: CEUFVK | Q20: 6200 | R20: 0 | S20: 1233 | T20: 310 | U20: 7743 | V20: 75 | W20: MS. NIDHI RAJESH BAGLA | X20: Approved | Y20: 18-AUG-2026 | Z20: 16:37 | AA20: FLOWN | AB20: Teamlease Services Ltd | AC20: TLEdtech | AD20: 200117979829 | AE20: 3937212 | AF20: Senior Project Manager | AG20: One Way | AH20: Domestic | AI20: L7 | AJ20: aayush.lal@teamlease.com | AK20: R | AL20: 600 | AM20: 0 | AN20: 44775874 | AO20: 18-AUG-2026 | AP20: 16:34 | AR20: CORPORATE | AS20: Scheduled Visit | AT20: Original | AY20: 7076663907 | AZ20: 29AAPCS2871R1Z7 | BA20: Karnataka | BB20: CEUFVK | BC20: CEUFVK | BD20: T004S | BE20: - | BF20: 996425 | BG20: 30-08-202/ | BH20: Mr. AAYUSH LAL | BI20: T16161 | BJ20: 1007 | BL20: 310 | BM20: 0 | BN20: 0 | BO20: 0.1600123 | BP20: 30-08-2026 22:35:00 | BU20: 12 | BV20: IXR-DEL | CA20: 310 | CB20: TeamLease Edtech Limited | CC20: 29AAPCS2871R1Z7 | CE20: M | CF20: '11797982908302035 | CJ20: T17642 | CK20: L8
A21: DW26/798332 | B21: 19-AUG-2026 | C21: 19-AUG-2026 | D21: Operations | E21: Bengaluru | F21: MR. AAYUSH LAL | G21: T16161 | I21: 69-MUM-PBP | K21: 19-08-2026 11:00:00 | L21: New Delhi-Chennai | M21: Indigo | N21: 6E-0434 | O21: Economy | P21: BYS3SW | Q21: 9240 | R21: 0 | S21: 397 | T21: 462 | U21: 10099 | V21: 75 | W21: MS. NIDHI RAJESH BAGLA | X21: Approved | Y21: 19-AUG-2026 | Z21: 07:33 | AA21: FLOWN | AB21: Teamlease Services Ltd | AC21: TLEdtech | AD21: 200117988871 | AE21: 3937212 | AF21: Senior Project Manager | AG21: One Way | AH21: Domestic | AI21: L7 | AJ21: aayush.lal@teamlease.com | AK21: R | AL21: 800 | AM21: 0 | AN21: 44787679 | AO21: 19-AUG-2026 | AP21: 07:27 | AR21: CORPORATE | AS21: Official | AT21: Original | AY21: 7076663907 | AZ21: 29AAPCS2871R1Z7 | BA21: Karnataka | BB21: BYS3SW | BC21: BYS3SW | BD21: T004S | BE21: - | BF21: 996425 | BG21: 19-08-202/ | BH21: Mr. AAYUSH LAL | BI21: T16161 | BJ21: 1760 | BL21: 462 | BM21: 0 | BN21: 0 | BO21: 0.279664 | BP21: 19-08-2026 13:50:00 | BU21: 0 | BV21: DEL-MAA | CA21: 462 | CB21: TeamLease Edtech Limited | CC21: 29AAPCS2871R1Z7 | CE21: M | CF21: '11798887108191100 | CJ21: T17642 | CK21: L8
A22: DA26/181264 | B22: 19-AUG-2026 | C22: 19-AUG-2026 | D22: University B2C | E22: Bengaluru | F22: MR. UDITENDU BOSE | G22: SG0320 | H22: 3701618 | I22: 62-MUM-SSS | K22: 24-08-2026 10:30:00 | L22: Kolkata-Mumbai | M22: Air India | N22: AI-2772 | O22: Economy | P22: 5808907262 | Q22: 7840 | R22: 0 | S22: 967 | T22: 392 | U22: 9199 | V22: 75 | W22: MR. SHANTANU ROOJ | X22: Approved | Y22: 19-AUG-2026 | Z22: 16:09 | AA22: RFND | AB22: Teamlease Services Ltd | AC22: TLEdtech | AD22: 200117997990 | AE22: 1388087 | AF22: Vice President - Consumer Sales | AG22: Round Trip | AH22: Domestic | AI22: L10 | AJ22: uditendu.bose@teamlease.com | AK22: T | AL22: 749 | AM22: 170 | AN22: 44798324 | AO22: 19-AUG-2026 | AP22: 13:59 | AR22: CORPORATE | AS22: Official | AT22: Original | AY22: 9971252225 | AZ22: 29AAPCS2871R1Z7 | BA22: Karnataka | BB22: '0985808907262 | BC22: ETRM8B | BD22: T004S | BE22: - | BF22: 996425 | BG22: 24-08-202/ | BH22: Ms. Priyanka Thakur | BI22: T16868 | BJ22: 1665 | BL22: 0 | BM22: 0 | BN22: 0 | BO22: 0.2645685 | BP22: 24-08-2026 13:35:00 | BU22: 5 | BV22: CCU-BOM | CA22: 392 | CB22: TeamLease Edtech Limited | CC22: 29AAPCS2871R1Z7 | CE22: M | CF22: '11799799008241030 | CJ22: SG0014 | CK22: LST
A23: DA26/181266 | B23: 19-AUG-2026 | C23: 19-AUG-2026 | D23: University B2C | E23: Bengaluru | F23: MR. UDITENDU BOSE | G23: SG0320 | H23: 3701618 | I23: 62-MUM-SSS | K23: 27-08-2026 06:55:00 | L23: Mumbai-Kolkata | M23: Air India | N23: AI-2771 | O23: Economy | P23: 5808907264 | Q23: 7840 | R23: 0 | S23: 439 | T23: 392 | U23: 8671 | V23: 75 | W23: MR. SHANTANU ROOJ | X23: Approved | Y23: 19-AUG-2026 | Z23: 16:09 | AA23: FLOWN | AB23: Teamlease Services Ltd | AC23: TLEdtech | AD23: 200117997991 | AE23: 1388087 | AF23: Vice President - Consumer Sales | AG23: Round Trip | AH23: Domestic | AI23: L10 | AJ23: uditendu.bose@teamlease.com | AK23: T | AL23: 749 | AM23: 170 | AN23: 44798324 | AO23: 19-AUG-2026 | AP23: 13:59 | AR23: CORPORATE | AS23: Official | AT23: Original | AY23: 9971252225 | AZ23: 29AAPCS2871R1Z7 | BA23: Karnataka | BB23: '0985808907264 | BC23: ETQQ6X | BD23: T004S | BE23: - | BF23: 996425 | BG23: 27-08-202/ | BH23: Ms. Priyanka Thakur | BI23: T16868 | BJ23: 1665 | BL23: 0 | BM23: 0 | BN23: 0 | BO23: 0.2645685 | BP23: 27-08-2026 09:45:00 | BU23: 8 | BV23: BOM-CCU | CA23: 392 | CB23: TeamLease Edtech Limited | CC23: 29AAPCS2871R1Z7 | CE23: M | CF23: '11799799108270655 | CJ23: SG0014 | CK23: LST
A24: DW26/799416 | B24: 19-AUG-2026 | C24: 19-AUG-2026 | D24: University B2C | E24: Bengaluru | F24: MR. UDITENDU BOSE | G24: SG0320 | H24: 3701618 | I24: 62-MUM-SSS | K24: 23-08-2026 11:35:00 | L24: Kolkata-Mumbai | M24: Indigo | N24: 6E-5288 | O24: Economy | P24: KDJR9N | Q24: 8220 | R24: 0 | S24: 978 | T24: 411 | U24: 9609 | V24: 75 | W24: MR. SHANTANU ROOJ | X24: Approved | Y24: 19-AUG-2026 | Z24: 17:05 | AA24: FLOWN | AB24: Teamlease Services Ltd | AC24: TLEdtech | AD24: 200117999595 | AE24: 1388087 | AF24: Vice President - Consumer Sales | AG24: One Way | AH24: Domestic | AI24: L10 | AJ24: uditendu.bose@teamlease.com | AK24: R | AL24: 800 | AM24: 0 | AN24: 44806175 | AO24: 19-AUG-2026 | AP24: 16:55 | AR24: CORPORATE | AS24: Official | AT24: Original | AY24: 9971252225 | AZ24: 29AAPCS2871R1Z7 | BA24: Karnataka | BB24: KDJR9N | BC24: KDJR9N | BD24: T004S | BE24: - | BF24: 996425 | BG24: 23-08-202/ | BH24: Ms. Priyanka Thakur | BI24: T16868 | BJ24: 1665 | BL24: 411 | BM24: 0 | BN24: 0 | BO24: 0.2645685 | BP24: 23-08-2026 14:35:00 | BU24: 4 | BV24: CCU-BOM | CA24: 411 | CB24: TeamLease Edtech Limited | CC24: 29AAPCS2871R1Z7 | CE24: M | CF24: '11799959508231135 | CJ24: SG0014 | CK24: LST
A25: DW26/799382 | B25: 19-AUG-2026 | C25: 19-AUG-2026 | D25: Leadership | E25: Bengaluru | F25: MR. SHANTANU ROOJ | G25: SG0014 | H25: 3701618 | I25: 68-MUM-LED | K25: 21-08-2026 20:45:00 | L25: New Delhi-Mumbai | M25: Indigo | N25: 6E-0853 | O25: Economy | P25: K9PBJM | Q25: 7560 | R25: 0 | S25: 485 | T25: 378 | U25: 8423 | V25: 0 | W25: MR. SHANTANU ROOJ | X25: Approved | Y25: 19-AUG-2026 | Z25: 18:37 | AA25: RFND | AB25: Teamlease Services Ltd | AC25: TLEdtech | AD25: 200118001834 | AE25: 1388000 | AF25: Founder and CEO | AG25: Round Trip | AH25: Domestic | AI25: LST | AJ25: shantanu@teamlease.com | AK25: O | AL25: 600 | AM25: 0 | AN25: 44809720 | AO25: 19-AUG-2026 | AP25: 18:30 | AR25: CORPORATE | AS25: Official | AT25: Original | AY25: 9870333111 | AZ25: 29AAPCS2871R1Z7 | BA25: Karnataka | BB25: K9PBJM | BC25: K9PBJM | BD25: T004S | BE25: - | BF25: 996425 | BG25: 21-08-202/ | BH25: Mr. Shantanu Rooj | BI25: SG0014 | BJ25: 1139 | BL25: 378 | BM25: 0 | BN25: 0 | BO25: 0.1809871 | BP25: 21-08-2026 23:00:00 | BU25: 2 | BV25: DEL-BOM | CA25: 378 | CB25: TeamLease Edtech Limited | CC25: 29AAPCS2871R1Z7 | CE25: M | CF25: '11800183408212045 | CJ25: SG0014 | CK25: LST
A26: DA26/181589 | B26: 19-AUG-2026 | C26: 19-AUG-2026 | D26: Leadership | E26: Bengaluru | F26: MR. SHANTANU ROOJ | G26: SG0014 | H26: 3701618 | I26: 68-MUM-LED | K26: 21-08-2026 08:30:00 | L26: Mumbai-New Delhi | M26: Air India | N26: AI-2970 | O26: Economy | P26: 5808911595 | Q26: 6480 | R26: 0 | S26: 505 | T26: 324 | U26: 7309 | V26: 0 | W26: MR. SHANTANU ROOJ | X26: Approved | Y26: 19-AUG-2026 | Z26: 18:37 | AA26: FLOWN | AB26: Teamlease Services Ltd | AC26: TLEdtech | AD26: 200118001833 | AE26: 1388000 | AF26: Founder and CEO | AG26: Round Trip | AH26: Domestic | AI26: LST | AJ26: shantanu@teamlease.com | AK26: T | AL26: 549 | AM26: 170 | AN26: 44809720 | AO26: 19-AUG-2026 | AP26: 18:30 | AR26: CORPORATE | AS26: Official | AT26: Original | AY26: 9870333111 | AZ26: 29AAPCS2871R1Z7 | BA26: Karnataka | BB26: '0985808911595 | BC26: EVL5VE | BD26: T004S | BE26: - | BF26: 996425 | BG26: 21-08-202/ | BH26: Mr. Shantanu Rooj | BI26: SG0014 | BJ26: 1139 | BL26: 0 | BM26: 0 | BN26: 0 | BO26: 0.1809871 | BP26: 21-08-2026 10:50:00 | BU26: 2 | BV26: BOM-DEL | CA26: 324 | CB26: TeamLease Edtech Limited | CC26: 29AAPCS2871R1Z7 | CE26: M | CF26: '11800183308210830 | CJ26: SG0014 | CK26: LST
A27: DA26/182479 | B27: 20-AUG-2026 | C27: 20-AUG-2026 | D27: Leadership | E27: Bengaluru | F27: MR. SHANTANU ROOJ | G27: SG0014 | H27: 3701618 | I27: 68-MUM-LED | K27: 21-08-2026 21:30:00 | L27: New Delhi-Mumbai | M27: Air India | N27: AI-2433 | O27: Economy | P27: 5808926793 | Q27: 7620 | R27: 0 | S27: 477 | T27: 381 | U27: 8478 | V27: 0 | W27: MR. SHANTANU ROOJ | X27: Approved | Y27: 20-AUG-2026 | Z27: 13:24 | AA27: FLOWN | AB27: Teamlease Services Ltd | AC27: TLEdtech | AD27: 200118013519 | AE27: 1388000 | AF27: Founder and CEO | AG27: One Way | AH27: Domestic | AI27: LST | AJ27: shantanu@teamlease.com | AK27: G | AL27: 549 | AM27: 170 | AN27: 44824925 | AO27: 20-AUG-2026 | AP27: 13:19 | AR27: CORPORATE | AS27: Official | AT27: Original | AY27: 9870333111 | AZ27: 29AAPCS2871R1Z7 | BA27: Karnataka | BB27: '0985808926793 | BC27: FB4UCA | BD27: T004S | BE27: - | BF27: 996425 | BG27: 21-08-202/ | BH27: Mr. Shantanu Rooj | BI27: SG0014 | BJ27: 1139 | BL27: 0 | BM27: 0 | BN27: 0 | BO27: 0.1809871 | BP27: 21-08-2026 23:55:00 | BU27: 1 | BV27: DEL-BOM | CA27: 381 | CB27: TeamLease Edtech Limited | CC27: 29AAPCS2871R1Z7 | CE27: M | CF27: '11801351908212130 | CJ27: SG0014 | CK27: LST
A28: DW26/806555 | B28: 20-AUG-2026 | C28: 20-AUG-2026 | D28: Leadership | E28: Bengaluru | F28: MR. SHANTANU ROOJ | G28: SG0014 | H28: 3701618 | I28: 68-MUM-LED | K28: 28-08-2026 19:35:00 | L28: Ahmedabad-Mumbai | M28: Indigo | N28: 6E-5160 | O28: Economy | P28: R8PE7P | Q28: 8620 | R28: 0 | S28: 1030 | T28: 431 | U28: 10081 | V28: 0 | W28: MR. SHANTANU ROOJ | X28: Approved | Y28: 20-AUG-2026 | Z28: 15:11 | AA28: FLOWN | AB28: Teamlease Services Ltd | AC28: TLEdtech | AD28: 200118015907 | AE28: 1388000 | AF28: Founder and CEO | AG28: Round Trip | AH28: Domestic | AI28: LST | AJ28: shantanu@teamlease.com | AK28: V | AL28: 275 | AM28: 0 | AN28: 44828403 | AO28: 20-AUG-2026 | AP28: 14:53 | AR28: CORPORATE | AS28: Official | AT28: Original | AY28: 9870333111 | AZ28: 29AAPCS2871R1Z7 | BA28: Karnataka | BB28: R8PE7P | BC28: R8PE7P | BD28: T004S | BE28: - | BF28: 996425 | BG28: 28-08-202/ | BH28: Mr. Shantanu Rooj | BI28: SG0014 | BJ28: 442 | BL28: 431 | BM28: 0 | BN28: 0 | BO28: 0.0702338 | BP28: 28-08-2026 21:05:00 | BU28: 8 | BV28: AMD-BOM | CA28: 431 | CB28: TeamLease Edtech Limited | CC28: 29AAPCS2871R1Z7 | CE28: M | CF28: '11801590708281935 | CJ28: SG0014 | CK28: LST
A29: DA26/182688 | B29: 20-AUG-2026 | C29: 20-AUG-2026 | D29: Leadership | E29: Bengaluru | F29: MR. SHANTANU ROOJ | G29: SG0014 | H29: 3701618 | I29: 68-MUM-LED | K29: 28-08-2026 10:20:00 | L29: Mumbai-Ahmedabad | M29: Air India | N29: AI-2847 | O29: Economy | P29: 5808929510 | Q29: 6940 | R29: 0 | S29: 424 | T29: 347 | U29: 7711 | V29: 0 | W29: MR. SHANTANU ROOJ | X29: Approved | Y29: 20-AUG-2026 | Z29: 15:11 | AA29: FLOWN | AB29: Teamlease Services Ltd | AC29: TLEdtech | AD29: 200118015906 | AE29: 1388000 | AF29: Founder and CEO | AG29: Round Trip | AH29: Domestic | AI29: LST | AJ29: shantanu@teamlease.com | AK29: Q | AL29: 299 | AM29: 170 | AN29: 44828403 | AO29: 20-AUG-2026 | AP29: 14:53 | AR29: CORPORATE | AS29: Official | AT29: Original | AY29: 9870333111 | AZ29: 29AAPCS2871R1Z7 | BA29: Karnataka | BB29: '0985808929510 | BC29: FCBVSC | BD29: T004S | BE29: - | BF29: 996425 | BG29: 28-08-202/ | BH29: Mr. Shantanu Rooj | BI29: SG0014 | BJ29: 442 | BL29: 0 | BM29: 0 | BN29: 0 | BO29: 0.0702338 | BP29: 28-08-2026 11:50:00 | BU29: 8 | BV29: BOM-AMD | CA29: 347 | CB29: TeamLease Edtech Limited | CC29: 29AAPCS2871R1Z7 | CE29: M | CF29: '11801590608281020 | CJ29: SG0014 | CK29: LST
A30: DW26/808707 | B30: 20-AUG-2026 | C30: 20-AUG-2026 | D30: Premier B2C | E30: Bengaluru | F30: MS. SHRUTIKA SHARMA | G30: T16151 | I30: 69-MUM-PBD | K30: 03-09-2026 17:45:00 | L30: Bangalore-Mumbai | M30: Akasa Air | N30: QP-1986 | O30: Economy | P30: YYS1MT | Q30: 6160 | R30: 0 | S30: 991 | T30: 308 | U30: 7459 | V30: 75 | W30: MS. GEETIKA KOHLI | X30: Approved | Y30: 20-AUG-2026 | Z30: 16:47 | AB30: Teamlease Services Ltd | AC30: TLEdtech | AD30: 200118018169 | AE30: 3906980 | AF30: Assistant General Manager | AG30: Round Trip | AH30: Domestic | AI30: L8 | AJ30: shrutika.sharma@teamlease.com | AK30: R2 | AL30: 0 | AM30: 0 | AN30: 44829110 | AO30: 20-AUG-2026 | AP30: 15:12 | AR30: CORPORATE | AS30: Official | AT30: Original | AY30: 9930515039 | AZ30: 29AAPCS2871R1Z7 | BA30: Karnataka | BB30: YYS1MT | BC30: YYS1MT | BD30: T004S | BE30: - | BF30: 996425 | BG30: 03-09-202/ | BH30: Mr. Satyavan Sawant | BI30: T17247 | BJ30: 835 | BL30: 0 | BM30: 154 | BN30: 154 | BO30: 0.1326815 | BP30: 03-09-2026 19:40:00 | BU30: 14 | BV30: BLR-BOM | CA30: 308 | CB30: TeamLease Edtech Limited | CC30: 29AAPCS2871R1Z7 | CE30: F | CF30: '11801816909031745 | CJ30: SG0400 | CK30: L10
A31: DW26/806969 | B31: 20-AUG-2026 | C31: 20-AUG-2026 | D31: Premier B2C | E31: Bengaluru | F31: MS. SHRUTIKA SHARMA | G31: T16151 | I31: 69-MUM-PBD | K31: 31-08-2026 08:05:00 | L31: Mumbai-Bangalore | M31: Indigo | N31: 6E-5193 | O31: Economy | P31: TH3MFH | Q31: 7520 | R31: 0 | S31: 437 | T31: 376 | U31: 8333 | V31: 75 | W31: MS. GEETIKA KOHLI | X31: Approved | Y31: 20-AUG-2026 | Z31: 16:47 | AA31: FLOWN | AB31: Teamlease Services Ltd | AC31: TLEdtech | AD31: 200118018168 | AE31: 3906980 | AF31: Assistant General Manager | AG31: Round Trip | AH31: Domestic | AI31: L8 | AJ31: shrutika.sharma@teamlease.com | AK31: P | AL31: 400 | AM31: 0 | AN31: 44829110 | AO31: 20-AUG-2026 | AP31: 15:12 | AR31: CORPORATE | AS31: Official | AT31: Original | AY31: 9930515039 | AZ31: 29AAPCS2871R1Z7 | BA31: Karnataka | BB31: TH3MFH | BC31: TH3MFH | BD31: T004S | BE31: - | BF31: 996425 | BG31: 31-08-202/ | BH31: Mr. Satyavan Sawant | BI31: T17247 | BJ31: 835 | BL31: 376 | BM31: 0 | BN31: 0 | BO31: 0.1326815 | BP31: 31-08-2026 09:55:00 | BU31: 11 | BV31: BOM-BLR | CA31: 376 | CB31: TeamLease Edtech Limited | CC31: 29AAPCS2871R1Z7 | CE31: F | CF31: '11801816808310805 | CJ31: SG0400 | CK31: L10
A32: DW26/807439 | B32: 20-AUG-2026 | C32: 20-AUG-2026 | D32: Operations | E32: Bengaluru | F32: MR. DINESH KUMAR | G32: T11310 | H32: 3701618 | I32: 63-DEL-DAS | K32: 27-08-2026 21:20:00 | L32: Aurangabad-New Delhi | M32: Indigo | N32: 6E-6257 | O32: Economy | P32: WG7C4X | Q32: 6660 | R32: 0 | S32: 1120 | T32: 333 | U32: 8113 | V32: 75 | W32: MR. NIPUN SHARMA | X32: Approved | Y32: 20-AUG-2026 | Z32: 19:08 | AA32: FLOWN | AB32: Teamlease Services Ltd | AC32: TL Digital | AD32: 200118021115 | AE32: 1388459 | AF32: Head - Operations (Enterprise Services) | AG32: Round Trip | AH32: Domestic | AI32: L9 | AJ32: dinesh.gupta@teamlease.com | AK32: R | AL32: 400 | AM32: 0 | AN32: 44833854 | AO32: 20-AUG-2026 | AP32: 18:21 | AR32: CORPORATE | AS32: Official | AT32: Original | AY32: 8826526715 | AZ32: 29AAPCS2871R1Z7 | BA32: Karnataka | BB32: WG7C4X | BC32: WG7C4X | BD32: T004S | BE32: - | BF32: 996425 | BG32: 27-08-202/ | BH32: Mr. DINESH KUMAR | BI32: T11310 | BJ32: 983 | BL32: 333 | BM32: 0 | BN32: 0 | BO32: 0.1561987 | BP32: 27-08-2026 23:25:00 | BU32: 7 | BV32: IXU-DEL | CA32: 333 | CB32: TeamLease Edtech Limited | CC32: 29AAPCS2871R1Z7 | CE32: M | CF32: '11802111508272120 | CJ32: T16237 | CK32: LST
A33: DW26/807631 | B33: 20-AUG-2026 | C33: 20-AUG-2026 | D33: Operations | E33: Bengaluru | F33: MR. DINESH KUMAR | G33: T11310 | H33: 3701618 | I33: 63-DEL-DAS | K33: 23-08-2026 19:10:00 | L33: New Delhi-Aurangabad | M33: Indigo | N33: 6E-6256 | O33: Economy | P33: XHHZ8U | Q33: 7280 | R33: 0 | S33: 392 | T33: 364 | U33: 8036 | V33: 75 | W33: MR. NIPUN SHARMA | X33: Approved | Y33: 20-AUG-2026 | Z33: 19:08 | AA33: FLOWN | AB33: Teamlease Services Ltd | AC33: TL Digital | AD33: 200118021114 | AE33: 1388459 | AF33: Head - Operations (Enterprise Services) | AG33: Round Trip | AH33: Domestic | AI33: L9 | AJ33: dinesh.gupta@teamlease.com | AK33: P | AL33: 400 | AM33: 0 | AN33: 44833854 | AO33: 20-AUG-2026 | AP33: 18:21 | AR33: CORPORATE | AS33: Official | AT33: Original | AY33: 8826526715 | AZ33: 29AAPCS2871R1Z7 | BA33: Karnataka | BB33: XHHZ8U | BC33: XHHZ8U | BD33: T004S | BE33: - | BF33: 996425 | BG33: 23-08-202/ | BH33: Mr. DINESH KUMAR | BI33: T11310 | BJ33: 983 | BL33: 364 | BM33: 0 | BN33: 0 | BO33: 0.1561987 | BP33: 23-08-2026 20:50:00 | BU33: 3 | BV33: DEL-IXU | CA33: 364 | CB33: TeamLease Edtech Limited | CC33: 29AAPCS2871R1Z7 | CE33: M | CF33: '11802111408231910 | CJ33: T16237 | CK33: LST
A34: DW26/818659 | B34: 22-AUG-2026 | C34: 22-AUG-2026 | D34: Operations | E34: Bengaluru | F34: MRS. SRIMATHI R | G34: SG0444 | H34: 3701618 | I34: 61-MUM-ASO | K34: 31-08-2026 13:30:00 | L34: Mumbai-Gwalior | M34: Indigo | N34: 6E-5276 | O34: Economy | P34: XHSK3E | Q34: 6000 | R34: 0 | S34: 443 | T34: 300 | U34: 6743 | V34: 75 | W34: MR. JAIDEEP KEWALRAMANI | X34: Approved | Y34: 22-AUG-2026 | Z34: 03:59 | AA34: FLOWN | AB34: Teamlease Services Ltd | AC34: TLEdtech | AD34: 200118040752 | AE34: 1388479 | AF34: Head - University Operations | AG34: Round Trip | AH34: Domestic | AI34: L10 | AJ34: srimathi.krishnan@teamlease.com | AK34: O | AL34: 400 | AM34: 0 | AN34: 44856343 | AO34: 21-AUG-2026 | AP34: 16:31 | AR34: CORPORATE | AS34: Official | AT34: Original | AY34: 8903128200 | AZ34: 29AAPCS2871R1Z7 | BA34: Karnataka | BB34: XHSK3E | BC34: XHSK3E | BD34: T004S | BE34: - | BF34: 996425 | BG34: 31-08-202/ | BH34: Mrs. SRIMATHI R | BI34: SG0444 | BJ34: 972 | BL34: 300 | BM34: 0 | BN34: 0 | BO34: 0.1544508 | BP34: 31-08-2026 15:40:00 | BU34: 10 | BV34: BOM-GWL | CA34: 300 | CB34: TeamLease Edtech Limited | CC34: 29AAPCS2871R1Z7 | CE34: F | CF34: '11804075208311330 | CJ34: T12553 | CK34: LST
A35: DW26/817320 | B35: 22-AUG-2026 | C35: 22-AUG-2026 | D35: Operations | E35: Bengaluru | F35: MRS. SRIMATHI R | G35: SG0444 | H35: 3701618 | I35: 61-MUM-ASO | K35: 02-09-2026 16:15:00 | L35: Gwalior-Mumbai | M35: Indigo | N35: 6E-5265 | O35: Economy | P35: IE8PPA | Q35: 6780 | R35: 0 | S35: 1136 | T35: 339 | U35: 8255 | V35: 75 | W35: MR. JAIDEEP KEWALRAMANI | X35: Approved | Y35: 22-AUG-2026 | Z35: 03:59 | AA35: RFND | AB35: Teamlease Services Ltd | AC35: TLEdtech | AD35: 200118040753 | AE35: 1388479 | AF35: Head - University Operations | AG35: Round Trip | AH35: Domestic | AI35: L10 | AJ35: srimathi.krishnan@teamlease.com | AK35: V | AL35: 400 | AM35: 0 | AN35: 44856343 | AO35: 21-AUG-2026 | AP35: 16:31 | AR35: CORPORATE | AS35: Official | AT35: Original | AY35: 8903128200 | AZ35: 29AAPCS2871R1Z7 | BA35: Karnataka | BB35: IE8PPA | BC35: IE8PPA | BD35: T004S | BE35: - | BF35: 996425 | BG35: 02-09-202/ | BH35: Mrs. SRIMATHI R | BI35: SG0444 | BJ35: 972 | BL35: 339 | BM35: 0 | BN35: 0 | BO35: 0.1544508 | BP35: 02-09-2026 18:10:00 | BU35: 12 | BV35: GWL-BOM | CA35: 339 | CB35: TeamLease Edtech Limited | CC35: 29AAPCS2871R1Z7 | CE35: F | CF35: '11804075309021615 | CJ35: T12553 | CK35: LST
A36: DW26/817440 | B36: 22-AUG-2026 | C36: 22-AUG-2026 | D36: Operations | E36: Bengaluru | F36: MR. PRATHAMESH JADHAV | G36: T16692 | I36: 62-MUM-PBO | K36: 27-08-2026 16:40:00 | L36: Chennai-Mumbai | M36: Indigo | N36: 6E-5104 | O36: Economy | P36: K6M28F | Q36: 7800 | R36: 0 | S36: 805 | T36: 390 | U36: 8995 | V36: 75 | W36: MS. NIDHI RAJESH BAGLA | X36: Approved | Y36: 22-AUG-2026 | Z36: 11:02 | AA36: RFND | AB36: Teamlease Services Ltd | AC36: TLEdtech | AD36: 200118042397 | AE36: 5246483 | AF36: Manager | AG36: Round Trip | AH36: Domestic | AI36: L6 | AJ36: prathamesh.jadhav@teamlease.com | AK36: P | AL36: 600 | AM36: 0 | AN36: 44855536 | AO36: 21-AUG-2026 | AP36: 16:04 | AR36: CORPORATE | AS36: Official | AT36: Original | AY36: 9867718072 | AZ36: 29AAPCS2871R1Z7 | BA36: Karnataka | BB36: K6M28F | BC36: K6M28F | BD36: T004S | BE36: - | BF36: 996425 | BG36: 27-08-202/ | BH36: Mr. Prathamesh JADHAV | BI36: T16692 | BJ36: 1034 | BL36: 390 | BM36: 0 | BN36: 0 | BO36: 0.1643026 | BP36: 27-08-2026 18:40:00 | BU36: 6 | BV36: MAA-BOM | CA36: 390 | CB36: TeamLease Edtech Limited | CC36: 29AAPCS2871R1Z7 | CE36: M | CF36: '11804239708271640 | CJ36: T17642 | CK36: L8
A37: DW26/818413 | B37: 22-AUG-2026 | C37: 22-AUG-2026 | D37: Operations | E37: Bengaluru | F37: MR. PRATHAMESH JADHAV | G37: T16692 | I37: 62-MUM-PBO | K37: 23-08-2026 17:25:00 | L37: Mumbai-Chennai | M37: Indigo | N37: 6E-5048 | O37: Economy | P37: V5S74Y | Q37: 8260 | R37: 0 | S37: 436 | T37: 413 | U37: 9109 | V37: 75 | W37: MS. NIDHI RAJESH BAGLA | X37: Approved | Y37: 22-AUG-2026 | Z37: 11:02 | AA37: RFND | AB37: Teamlease Services Ltd | AC37: TLEdtech | AD37: 200118042396 | AE37: 5246483 | AF37: Manager | AG37: Round Trip | AH37: Domestic | AI37: L6 | AJ37: prathamesh.jadhav@teamlease.com | AK37: J | AL37: 600 | AM37: 0 | AN37: 44855536 | AO37: 21-AUG-2026 | AP37: 16:04 | AR37: CORPORATE | AS37: Official | AT37: Original | AY37: 9867718072 | AZ37: 29AAPCS2871R1Z7 | BA37: Karnataka | BB37: V5S74Y | BC37: V5S74Y | BD37: T004S | BE37: - | BF37: 996425 | BG37: 23-08-202/ | BH37: Mr. Prathamesh JADHAV | BI37: T16692 | BJ37: 1034 | BL37: 413 | BM37: 0 | BN37: 0 | BO37: 0.1643026 | BP37: 23-08-2026 19:35:00 | BU37: 2 | BV37: BOM-MAA | CA37: 413 | CB37: TeamLease Edtech Limited | CC37: 29AAPCS2871R1Z7 | CE37: M | CF37: '11804239608231725 | CJ37: T17642 | CK37: L8
A38: DA26/185880 | B38: 23-AUG-2026 | C38: 23-AUG-2026 | D38: University Bd | E38: Bengaluru | F38: MS. DEEPTI DEEPTI | G38: T17404 | I38: 61-MUM-USE | K38: 27-08-2026 12:00:00 | L38: Jaipur-New Delhi | M38: Air India | N38: AI-0430 | O38: Economy | P38: 5808985901 | Q38: 4080 | R38: 0 | S38: 1450 | T38: 204 | U38: 5734 | V38: 75 | W38: MR. SHANTANU ROOJ | X38: Approved | Y38: 23-AUG-2026 | Z38: 13:07 | AA38: FLOWN | AB38: Teamlease Services Ltd | AC38: TLEdtech | AD38: 200118054129 | AE38: 6900149 | AF38: Assistant General Manager | AG38: Round Trip | AH38: Domestic | AI38: L8 | AJ38: deepti.thakur@teamlease.com | AK38: W | AL38: 299 | AM38: 170 | AN38: 44881914 | AO38: 23-AUG-2026 | AP38: 13:03 | AR38: CORPORATE | AS38: Official | AT38: Original | AY38: 9899203334 | AZ38: 29AAPCS2871R1Z7 | BA38: Karnataka | BB38: '0985808985901 | BC38: DSRJ3S | BD38: T004S | BE38: - | BF38: 996425 | BG38: 27-08-202/ | BH38: Ms. Deepti DEEPTI | BI38: T17404 | BJ38: 233 | BL38: 0 | BM38: 0 | BN38: 0 | BO38: 0.0370237 | BP38: 27-08-2026 13:10:00 | BU38: 4 | BV38: JAI-DEL | CA38: 204 | CB38: TeamLease Edtech Limited | CC38: 29AAPCS2871R1Z7 | CE38: F | CF38: '11805412908271200 | CJ38: SG0014 | CK38: LST
A39: DW26/820993 | B39: 23-AUG-2026 | C39: 23-AUG-2026 | D39: University Bd | E39: Bengaluru | F39: MS. DEEPTI DEEPTI | G39: T17404 | I39: 61-MUM-USE | K39: 26-08-2026 07:40:00 | L39: New Delhi-Jaipur | M39: Indigo | N39: 6E-6190 | O39: Economy | P39: FGRS4R | Q39: 3900 | R39: 0 | S39: 874 | T39: 195 | U39: 4969 | V39: 75 | W39: MR. SHANTANU ROOJ | X39: Approved | Y39: 23-AUG-2026 | Z39: 13:07 | AA39: FLOWN | AB39: Teamlease Services Ltd | AC39: TLEdtech | AD39: 200118054128 | AE39: 6900149 | AF39: Assistant General Manager | AG39: Round Trip | AH39: Domestic | AI39: L8 | AJ39: deepti.thakur@teamlease.com | AK39: L | AL39: 275 | AM39: 0 | AN39: 44881914 | AO39: 23-AUG-2026 | AP39: 13:03 | AR39: CORPORATE | AS39: Official | AT39: Original | AY39: 9899203334 | AZ39: 29AAPCS2871R1Z7 | BA39: Karnataka | BB39: FGRS4R | BC39: FGRS4R | BD39: T004S | BE39: - | BF39: 996425 | BG39: 26-08-202/ | BH39: Ms. Deepti DEEPTI | BI39: T17404 | BJ39: 233 | BL39: 195 | BM39: 0 | BN39: 0 | BO39: 0.0370237 | BP39: 26-08-2026 08:40:00 | BU39: 3 | BV39: DEL-JAI | CA39: 195 | CB39: TeamLease Edtech Limited | CC39: 29AAPCS2871R1Z7 | CE39: F | CF39: '11805412808260740 | CJ39: SG0014 | CK39: LST
A40: DW26/832334 | B40: 25-AUG-2026 | C40: 25-AUG-2026 | D40: University Bd | E40: Bengaluru | F40: MR. KHUNJAMAYUM DAVID SINGH | G40: T17743 | I40: 61-MUM-USE | K40: 29-08-2026 16:15:00 | L40: Mysore-Hyderabad | M40: Indigo | N40: 6E-7141 | O40: Economy | P40: JC142D | Q40: 12780 | R40: 0 | S40: 475 | T40: 639 | U40: 13894 | V40: 75 | W40: MR. SHANTANU ROOJ | X40: Approved | Y40: 25-AUG-2026 | Z40: 11:04 | AA40: FLOWN | AB40: Teamlease Services Ltd | AC40: TLEdtech | AD40: 200118081816 | AE40: 7442895 | AF40: Regional Head | AG40: Round Trip | AH40: Domestic | AI40: L8 | AJ40: david.singh@teamlease.com | AK40: C | AL40: 400 | AM40: 0 | AN40: 44918655 | AO40: 25-AUG-2026 | AP40: 08:19 | AR40: CORPORATE | AS40: Official | AT40: Original | AY40: 9205927758 | AZ40: 29AAPCS2871R1Z7 | BA40: Karnataka | BB40: JC142D | BC40: JC142D | BD40: T004S | BE40: - | BF40: 996425 | BG40: 29-08-202/ | BH40: Mr. Satyavan Sawant | BI40: T17247 | BJ40: 580 | BL40: 0 | BM40: 0 | BN40: 0 | BO40: 0.092162 | BP40: 29-08-2026 18:05:00 | BU40: 4 | BV40: MYQ-HYD | CA40: 639 | CB40: TeamLease Edtech Limited | CC40: 29AAPCS2871R1Z7 | CE40: M | CF40: '11808181608291615 | CJ40: SG0014 | CK40: LST
A41: DW26/833735 | B41: 25-AUG-2026 | C41: 25-AUG-2026 | D41: University Bd | E41: Bengaluru | F41: MR. KHUNJAMAYUM DAVID SINGH | G41: T17743 | I41: 61-MUM-USE | K41: 28-08-2026 14:00:00 | L41: Hyderabad-Mysore | M41: Indigo | N41: 6E-7126 | O41: Economy | P41: RBH4UJ | Q41: 7680 | R41: 0 | S41: 1114 | T41: 384 | U41: 9178 | V41: 75 | W41: MR. SHANTANU ROOJ | X41: Approved | Y41: 25-AUG-2026 | Z41: 11:04 | AA41: FLOWN | AB41: Teamlease Services Ltd | AC41: TLEdtech | AD41: 200118081815 | AE41: 7442895 | AF41: Regional Head | AG41: Round Trip | AH41: Domestic | AI41: L8 | AJ41: david.singh@teamlease.com | AK41: M | AL41: 400 | AM41: 0 | AN41: 44918655 | AO41: 25-AUG-2026 | AP41: 08:19 | AR41: CORPORATE | AS41: Official | AT41: Original | AY41: 9205927758 | AZ41: 29AAPCS2871R1Z7 | BA41: Karnataka | BB41: RBH4UJ | BC41: RBH4UJ | BD41: T004S | BE41: - | BF41: 996425 | BG41: 28-08-202/ | BH41: Mr. Satyavan Sawant | BI41: T17247 | BJ41: 580 | BL41: 384 | BM41: 0 | BN41: 0 | BO41: 0.092162 | BP41: 28-08-2026 15:55:00 | BU41: 3 | BV41: HYD-MYQ | CA41: 384 | CB41: TeamLease Edtech Limited | CC41: 29AAPCS2871R1Z7 | CE41: M | CF41: '11808181508281400 | CJ41: SG0014 | CK41: LST
A42: DW26/833890 | B42: 25-AUG-2026 | C42: 25-AUG-2026 | D42: Premier BD | E42: Bengaluru | F42: MR. VIKASH SHARMA | G42: T12988 | H42: 3701618 | I42: 69-MUM-PBD | K42: 26-08-2026 13:05:00 | L42: New Delhi-Jharsuguda | M42: Indigo | N42: 6E-6053 | O42: Economy | P42: S81BHF | Q42: 10020 | R42: 0 | S42: 397 | T42: 501 | U42: 10918 | V42: 75 | W42: MS. GEETIKA KOHLI | X42: Approved | Y42: 25-AUG-2026 | Z42: 18:32 | AA42: FLOWN | AB42: Teamlease Services Ltd | AC42: TLEdtech | AD42: 200118091876 | AE42: 1389203 | AF42: Senior Manager | AG42: One Way | AH42: Domestic | AI42: L7 | AJ42: vikash.sharma@teamlease.com | AK42: U | AL42: 600 | AM42: 0 | AN42: 44932177 | AO42: 25-AUG-2026 | AP42: 15:52 | AR42: CORPORATE | AS42: Official | AT42: Original | AY42: 7976560374 | AZ42: 29AAPCS2871R1Z7 | BA42: Karnataka | BB42: S81BHF | BC42: S81BHF | BD42: T004S | BE42: - | BF42: 996425 | BG42: 26-08-202/ | BH42: MR. Vikash Sharma | BI42: T12988 | BJ42: 1017 | BL42: 501 | BM42: 0 | BN42: 0 | BO42: 0.15358734 | BP42: 26-08-2026 14:55:00 | BU42: 1 | BV42: DEL-JRG | CA42: 501 | CB42: TeamLease Edtech Limited | CC42: 29AAPCS2871R1Z7 | CE42: M | CF42: '11809187608261305 | CJ42: SG0400 | CK42: L10
A43: DW26/840946 | B43: 26-AUG-2026 | C43: 26-AUG-2026 | D43: Operations | E43: Bengaluru | F43: MRS. SRIMATHI R | G43: SG0444 | H43: 3701618 | I43: 61-MUM-ASO | K43: 02-09-2026 20:45:00 | L43: New Delhi-Mumbai | M43: Indigo | N43: 6E-0853 | O43: Economy | P43: VC3TTJ | Q43: 6320 | R43: 0 | S43: 483 | T43: 316 | U43: 7119 | V43: 75 | W43: MR. JAIDEEP KEWALRAMANI | X43: Approved | Y43: 26-AUG-2026 | Z43: 11:22 | AB43: Teamlease Services Ltd | AC43: TLEdtech | AD43: 200118099614 | AE43: 1388479 | AF43: Head - University Operations | AG43: One Way | AH43: Domestic | AI43: L10 | AJ43: srimathi.krishnan@teamlease.com | AK43: P | AL43: 600 | AM43: 0 | AN43: 44946726 | AO43: 26-AUG-2026 | AP43: 10:43 | AR43: CORPORATE | AS43: Official | AT43: Original | AY43: 8903128200 | AZ43: 29AAPCS2871R1Z7 | BA43: Karnataka | BB43: VC3TTJ | BC43: VC3TTJ | BD43: T004S | BE43: - | BF43: 996425 | BG43: 02-09-202/ | BH43: Mrs. SRIMATHI R | BI43: SG0444 | BJ43: 1139 | BL43: 316 | BM43: 0 | BN43: 0 | BO43: 0.1809871 | BP43: 02-09-2026 23:00:00 | BU43: 7 | BV43: DEL-BOM | CA43: 316 | CB43: TeamLease Edtech Limited | CC43: 29AAPCS2871R1Z7 | CE43: F | CF43: '11809961409022045 | CJ43: T12553 | CK43: LST
A44: DW26/848307 | B44: 27-AUG-2026 | C44: 27-AUG-2026 | D44: Premier BD | E44: Bengaluru | F44: MR. SHASHWAT SAGAR DUBEY | G44: T13872 | H44: 3701618 | I44: 69-MUM-PBD | K44: 01-09-2026 09:45:00 | L44: New Delhi-Jodhpur | M44: Indigo | N44: 6E-2298 | O44: Economy | P44: Z48MNE | Q44: 7520 | R44: 0 | S44: 394 | T44: 376 | U44: 8290 | V44: 75 | W44: MS. GEETIKA KOHLI | X44: Approved | Y44: 27-AUG-2026 | Z44: 18:06 | AA44: FLOWN | AB44: Teamlease Services Ltd | AC44: TLEdtech | AD44: 200118124580 | AE44: 1389805 | AF44: Senior Manager | AG44: Round Trip | AH44: Domestic | AI44: L7 | AJ44: shashwat.dubey@teamlease.com | AK44: Q | AL44: 275 | AM44: 0 | AN44: 44979006 | AO44: 27-AUG-2026 | AP44: 17:58 | AR44: CORPORATE | AS44: Official | AT44: Original | AY44: 8082227857 | AZ44: 29AAPCS2871R1Z7 | BA44: Karnataka | BB44: Z48MNE | BC44: Z48MNE | BD44: T004S | BE44: - | BF44: 996425 | BG44: 01-09-202/ | BH44: MR. Shashwat Sagar Dubey | BI44: T13872 | BJ44: 474 | BL44: 376 | BM44: 0 | BN44: 0 | BO44: 0.0753186 | BP44: 01-09-2026 10:55:00 | BU44: 5 | BV44: DEL-JDH | CA44: 376 | CB44: TeamLease Edtech Limited | CC44: 29AAPCS2871R1Z7 | CE44: M | CF44: '11812458009010945 | CJ44: SG0400 | CK44: L10
A45: DW26/844617 | B45: 27-AUG-2026 | C45: 27-AUG-2026 | D45: Premier BD | E45: Bengaluru | F45: MR. SHASHWAT SAGAR DUBEY | G45: T13872 | H45: 3701618 | I45: 69-MUM-PBD | K45: 03-09-2026 11:35:00 | L45: Jodhpur-New Delhi | M45: Indigo | N45: 6E-2299 | O45: Economy | P45: DYS24G | Q45: 7160 | R45: 0 | S45: 1231 | T45: 358 | U45: 8749 | V45: 75 | W45: MS. GEETIKA KOHLI | X45: Approved | Y45: 27-AUG-2026 | Z45: 18:06 | AB45: Teamlease Services Ltd | AC45: TLEdtech | AD45: 200118124581 | AE45: 1389805 | AF45: Senior Manager | AG45: Round Trip | AH45: Domestic | AI45: L7 | AJ45: shashwat.dubey@teamlease.com | AK45: Q | AL45: 275 | AM45: 0 | AN45: 44979006 | AO45: 27-AUG-2026 | AP45: 17:58 | AR45: CORPORATE | AS45: Official | AT45: Original | AY45: 8082227857 | AZ45: 29AAPCS2871R1Z7 | BA45: Karnataka | BB45: DYS24G | BC45: DYS24G | BD45: T004S | BE45: - | BF45: 996425 | BG45: 03-09-202/ | BH45: MR. Shashwat Sagar Dubey | BI45: T13872 | BJ45: 474 | BL45: 358 | BM45: 0 | BN45: 0 | BO45: 0.0753186 | BP45: 03-09-2026 13:00:00 | BU45: 7 | BV45: JDH-DEL | CA45: 358 | CB45: TeamLease Edtech Limited | CC45: 29AAPCS2871R1Z7 | CE45: M | CF45: '11812458109031135 | CJ45: SG0400 | CK45: L10
A46: DA26/192370 | B46: 28-AUG-2026 | C46: 28-AUG-2026 | D46: University B2C | E46: Bengaluru | F46: MR. UDITENDU BOSE | G46: SG0320 | H46: 3701618 | I46: 62-MUM-SSS | K46: 04-09-2026 07:30:00 | L46: New Delhi-Kolkata | M46: Air India | N46: AI-2705 | O46: Economy | P46: 5809088474 | Q46: 8280 | R46: 0 | S46: 384 | T46: 414 | U46: 9078 | V46: 75 | W46: MR. SHANTANU ROOJ | X46: Approved | Y46: 28-AUG-2026 | Z46: 09:35 | AB46: Teamlease Services Ltd | AC46: TLEdtech | AD46: 200118130210 | AE46: 1388087 | AF46: Vice President - Consumer Sales | AG46: One Way | AH46: Domestic | AI46: L10 | AJ46: uditendu.bose@teamlease.com | AK46: T | AL46: 549 | AM46: 170 | AN46: 44990798 | AO46: 28-AUG-2026 | AP46: 09:25 | AR46: CORPORATE | AS46: Official | AT46: Original | AY46: 9971252225 | AZ46: 29AAPCS2871R1Z7 | BA46: Karnataka | BB46: '0985809088474 | BC46: DAJ446 | BD46: T004S | BE46: - | BF46: 996425 | BG46: 04-09-202/ | BH46: Mr. Satyavan Sawant | BI46: T17247 | BJ46: 1313 | BL46: 0 | BM46: 0 | BN46: 0 | BO46: 0.2086357 | BP46: 04-09-2026 09:50:00 | BU46: 7 | BV46: DEL-CCU | CA46: 414 | CB46: TeamLease Edtech Limited | CC46: 29AAPCS2871R1Z7 | CE46: M | CF46: '11813021009040730 | CJ46: SG0014 | CK46: LST
A47: DA26/192415 | B47: 28-AUG-2026 | C47: 28-AUG-2026 | D47: University B2C | E47: Bengaluru | F47: MR. UDITENDU BOSE | G47: SG0320 | H47: 3701618 | I47: 62-MUM-SSS | K47: 31-08-2026 16:10:00 | L47: Kolkata-New Delhi | M47: Air India | N47: AI-1805 | O47: Economy | P47: 5809093019 | Q47: 8620 | R47: 0 | S47: 945 | T47: 431 | U47: 9996 | V47: 75 | W47: MR. SHANTANU ROOJ | X47: Approved | Y47: 28-AUG-2026 | Z47: 10:23 | AA47: FLOWN | AB47: Teamlease Services Ltd | AC47: TLEdtech | AD47: 200118130772 | AE47: 1388087 | AF47: Vice President - Consumer Sales | AG47: One Way | AH47: Domestic | AI47: L10 | AJ47: uditendu.bose@teamlease.com | AK47: L | AL47: 549 | AM47: 170 | AN47: 44990409 | AO47: 28-AUG-2026 | AP47: 08:28 | AR47: CORPORATE | AS47: Official | AT47: Original | AY47: 9971252225 | AZ47: 29AAPCS2871R1Z7 | BA47: Karnataka | BB47: '0985809093019 | BC47: DAZ5OE | BD47: T004S | BE47: - | BF47: 996425 | BG47: 31-08-202/ | BH47: Mr. Satyavan Sawant | BI47: T17247 | BJ47: 1313 | BL47: 0 | BM47: 0 | BN47: 0 | BO47: 0.2086357 | BP47: 31-08-2026 18:40:00 | BU47: 3 | BV47: CCU-DEL | CA47: 431 | CB47: TeamLease Edtech Limited | CC47: 29AAPCS2871R1Z7 | CE47: M | CF47: '11813077208311610 | CJ47: SG0014 | CK47: LST
A48: DW26/857059 | B48: 29-AUG-2026 | C48: 29-AUG-2026 | D48: Impact | E48: Bengaluru | F48: MR. VARUN MAHESHWARI | G48: T15657 | I48: 64-BAN-CSS | K48: 04-09-2026 19:45:00 | L48: Mumbai-New Delhi | M48: Indigo | N48: 6E-6049 | O48: Economy | P48: BB56NW | Q48: 6320 | R48: 0 | S48: 515 | T48: 316 | U48: 7151 | V48: 75 | W48: MR. JAIDEEP KEWALRAMANI | X48: Approved | Y48: 29-AUG-2026 | Z48: 20:08 | AB48: Teamlease Services Ltd | AC48: TLEdtech | AD48: 200118152635 | AE48: 2897978 | AF48: General Manager | AG48: One Way | AH48: Domestic | AI48: L9 | AJ48: varun.maheshwari@teamlease.com | AK48: P | AL48: 600 | AM48: 0 | AN48: 45018050 | AO48: 29-AUG-2026 | AP48: 15:35 | AR48: CORPORATE | AS48: Official | AT48: Original | AY48: 7840040488 | AZ48: 29AAPCS2871R1Z7 | BA48: Karnataka | BB48: BB56NW | BC48: BB56NW | BD48: T004S | BE48: - | BF48: 996425 | BG48: 04-09-202/ | BH48: Mr. Satyavan Sawant | BI48: T17247 | BJ48: 1139 | BL48: 316 | BM48: 0 | BN48: 0 | BO48: 0.1809871 | BP48: 04-09-2026 21:55:00 | BU48: 6 | BV48: BOM-DEL | CA48: 316 | CB48: TeamLease Edtech Limited | CC48: 29AAPCS2871R1Z7 | CE48: M | CF48: '11815263509041945 | CJ48: T12553 | CK48: LST
A49: DW26/857148 | B49: 29-AUG-2026 | C49: 29-AUG-2026 | D49: Impact | E49: Bengaluru | F49: MR. VARUN MAHESHWARI | G49: T15657 | I49: 64-BAN-CSS | K49: 31-08-2026 18:30:00 | L49: New Delhi-Vadodara | M49: Indigo | N49: 6E-5014 | O49: Economy | P49: C69H3F | Q49: 9140 | R49: 0 | S49: 392 | T49: 457 | U49: 9989 | V49: 75 | W49: MR. JAIDEEP KEWALRAMANI | X49: Approved | Y49: 29-AUG-2026 | Z49: 20:09 | AA49: FLOWN | AB49: Teamlease Services Ltd | AC49: TLEdtech | AD49: 200118154275 | AE49: 2897978 | AF49: General Manager | AG49: One Way | AH49: Domestic | AI49: L9 | AJ49: varun.maheshwari@teamlease.com | AK49: N | AL49: 400 | AM49: 0 | AN49: 45014660 | AO49: 29-AUG-2026 | AP49: 13:42 | AR49: CORPORATE | AS49: Official | AT49: Original | AY49: 7840040488 | AZ49: 29AAPCS2871R1Z7 | BA49: Karnataka | BB49: C69H3F | BC49: C69H3F | BD49: T004S | BE49: - | BF49: 996425 | BG49: 31-08-202/ | BH49: Mr. Satyavan Sawant | BI49: T17247 | BJ49: 794 | BL49: 457 | BM49: 0 | BN49: 0 | BO49: 0.11975886 | BP49: 31-08-2026 19:55:00 | BU49: 2 | BV49: DEL-BDQ | CA49: 457 | CB49: TeamLease Edtech Limited | CC49: 29AAPCS2871R1Z7 | CE49: M | CF49: '11815427508311830 | CJ49: T12553 | CK49: LST
A50: DA26/194567 | B50: 30-AUG-2026 | C50: 30-AUG-2026 | D50: University B2C | E50: Bengaluru | F50: MR. SIDDHARTHA BOSE | G50: T17566 | I50: 62-MUM-SSS | K50: 04-09-2026 19:40:00 | L50: New Delhi-Kolkata | M50: Air India | N50: AI-2709 | O50: Economy | P50: 5809133822 | Q50: 8700 | R50: 0 | S50: 372 | T50: 435 | U50: 9507 | V50: 75 | W50: MR. CHETAN DIXIT | X50: Approved | Y50: 30-AUG-2026 | Z50: 13:42 | AB50: Teamlease Services Ltd | AC50: TLEdtech | AD50: 200118158130 | AE50: 7189632 | AF50: Assistant General Manager | AG50: Round Trip | AH50: Domestic | AI50: L8 | AJ50: siddhartha.bose@teamlease.com | AK50: U | AL50: 549 | AM50: 170 | AN50: 44999935 | AO50: 28-AUG-2026 | AP50: 15:44 | AR50: CORPORATE | AS50: Official | AT50: Original | AY50: 6289241114 | AZ50: 29AAPCS2871R1Z7 | BA50: Karnataka | BB50: '0985809133822 | BC50: EE2VTI | BD50: T004S | BE50: - | BF50: 996425 | BG50: 04-09-202/ | BH50: Mr. SIDDHARTHA BOSE | BI50: T17566 | BJ50: 1313 | BL50: 0 | BM50: 0 | BN50: 0 | BO50: 0.2086357 | BP50: 04-09-2026 21:50:00 | BU50: 7 | BV50: DEL-CCU | CA50: 435 | CB50: TeamLease Edtech Limited | CC50: 29AAPCS2871R1Z7 | CE50: M | CF50: '11815813009041940 | CJ50: SG0506 | CK50: L9
A51: DW26/863827 | B51: 30-AUG-2026 | C51: 30-AUG-2026 | D51: University B2C | E51: Bengaluru | F51: MR. SIDDHARTHA BOSE | G51: T17566 | I51: 62-MUM-SSS | K51: 01-09-2026 09:05:00 | L51: Kolkata-New Delhi | M51: Akasa Air | N51: QP-1802 | O51: Economy | P51: D8MDXW | Q51: 7480 | R51: 0 | S51: 943 | T51: 374 | U51: 8797 | V51: 75 | W51: MR. CHETAN DIXIT | X51: Approved | Y51: 30-AUG-2026 | Z51: 13:42 | AB51: Teamlease Services Ltd | AC51: TLEdtech | AD51: 200118158503 | AE51: 7189632 | AF51: Assistant General Manager | AG51: Round Trip | AH51: Domestic | AI51: L8 | AJ51: siddhartha.bose@teamlease.com | AK51: R1 | AL51: 0 | AM51: 0 | AN51: 44999935 | AO51: 28-AUG-2026 | AP51: 15:44 | AR51: CORPORATE | AS51: Official | AT51: Original | AY51: 6289241114 | AZ51: 29AAPCS2871R1Z7 | BA51: Karnataka | BB51: D8MDXW | BC51: D8MDXW | BD51: T004S | BE51: - | BF51: 996425 | BG51: 01-09-202/ | BH51: Mr. SIDDHARTHA BOSE | BI51: T17566 | BJ51: 1313 | BL51: 374 | BM51: 0 | BN51: 0 | BO51: 0.19828926 | BP51: 01-09-2026 11:25:00 | BU51: 4 | BV51: CCU-DEL | CA51: 374 | CB51: TeamLease Edtech Limited | CC51: 29AAPCS2871R1Z7 | CE51: M | CF51: '11815850309010905 | CJ51: SG0506 | CK51: L9
A52: DW26/870675 | B52: 31-AUG-2026 | C52: 31-AUG-2026 | D52: University Bd | E52: Bengaluru | F52: MR. NAKUL JOSHI | G52: T15226 | I52: 61-MUM-USE | K52: 02-09-2026 07:30:00 | L52: Mumbai-Bhopal | M52: Indigo | N52: 6E-6128 | O52: Economy | P52: ZIHIME | Q52: 7500 | R52: 0 | S52: 439 | T52: 375 | U52: 8314 | V52: 75 | W52: MS. DEEPTI DEEPTI | X52: Approved | Y52: 31-AUG-2026 | Z52: 15:58 | AB52: Teamlease Services Ltd | AC52: TLEdtech | AD52: 200118175743 | AE52: 2413020 | AF52: Senior Manager | AG52: One Way | AH52: Domestic | AI52: L7 | AJ52: nakul.joshi@teamlease.com | AK52: J | AL52: 400 | AM52: 0 | AN52: 45014017 | AO52: 29-AUG-2026 | AP52: 13:23 | AR52: CORPORATE | AS52: Official | AT52: Original | AY52: 8169563452 | AZ52: 29AAPCS2871R1Z7 | BA52: Karnataka | BB52: ZIHIME | BC52: ZIHIME | BD52: T004S | BE52: - | BF52: 996425 | BG52: 02-09-202/ | BH52: MR. NAKUL JOSHI | BI52: T15226 | BJ52: 658 | BL52: 375 | BM52: 0 | BN52: 0 | BO52: 0.09937116 | BP52: 02-09-2026 09:00:00 | BU52: 4 | BV52: BOM-BHO | CA52: 375 | CB52: TeamLease Edtech Limited | CC52: 29AAPCS2871R1Z7 | CE52: M | CF52: '11817574309020730 | CJ52: T17404 | CK52: L8
A53: DW26/871267 | B53: 31-AUG-2026 | C53: 31-AUG-2026 | D53: University Bd | E53: Bengaluru | F53: MS. DEEPTI DEEPTI | G53: T17404 | I53: 61-MUM-USE | K53: 04-09-2026 15:20:00 | L53: Bhopal-New Delhi | M53: AirIndia Express | N53: IX-1790 | O53: Economy | P53: V8J36T | Q53: 3980 | R53: 0 | S53: 1216 | T53: 199 | U53: 5395 | V53: 75 | W53: MR. SHANTANU ROOJ | X53: Approved | Y53: 31-AUG-2026 | Z53: 16:35 | AB53: Teamlease Services Ltd | AC53: TLEdtech | AD53: 200118176211 | AE53: 6900149 | AF53: Assistant General Manager | AG53: Round Trip | AH53: Domestic | AI53: L8 | AJ53: deepti.thakur@teamlease.com | AK53: G | AL53: 399 | AM53: 0 | AN53: 45055044 | AO53: 31-AUG-2026 | AP53: 16:02 | AR53: WEB | AS53: Official | AT53: Original | AY53: 9899203334 | AZ53: 29AAPCS2871R1Z7 | BA53: Karnataka | BB53: V8J36T | BC53: V8J36T | BD53: T004S | BE53: - | BF53: 996425 | BG53: 04-09-202/ | BH53: Ms. Priyanka Thakur | BI53: T16868 | BJ53: 589 | BL53: 199 | BM53: 0 | BN53: 0 | BO53: 0.0935921 | BP53: 04-09-2026 16:50:00 | BU53: 4 | BV53: BHO-DEL | CA53: 199 | CB53: TeamLease Edtech Limited | CC53: 29AAPCS2871R1Z7 | CE53: F | CF53: '11817621109041520 | CJ53: SG0014 | CK53: LST
A54: DW26/870937 | B54: 31-AUG-2026 | C54: 31-AUG-2026 | D54: University Bd | E54: Bengaluru | F54: MS. DEEPTI DEEPTI | G54: T17404 | I54: 61-MUM-USE | K54: 02-09-2026 08:35:00 | L54: New Delhi-Bhopal | M54: AirIndia Express | N54: IX-1789 | O54: Economy | P54: E91NGQ | Q54: 5260 | R54: 0 | S54: 383 | T54: 263 | U54: 5906 | V54: 75 | W54: MR. SHANTANU ROOJ | X54: Approved | Y54: 31-AUG-2026 | Z54: 16:35 | AB54: Teamlease Services Ltd | AC54: TLEdtech | AD54: 200118176431 | AE54: 6900149 | AF54: Assistant General Manager | AG54: Round Trip | AH54: Domestic | AI54: L8 | AJ54: deepti.thakur@teamlease.com | AK54: K | AL54: 399 | AM54: 0 | AN54: 45055044 | AO54: 31-AUG-2026 | AP54: 16:02 | AR54: WEB | AS54: Official | AT54: Original | AY54: 9899203334 | AZ54: 29AAPCS2871R1Z7 | BA54: Karnataka | BB54: E91NGQ | BC54: E91NGQ | BD54: T004S | BE54: - | BF54: 996425 | BG54: 02-09-202/ | BH54: Ms. Priyanka Thakur | BI54: T16868 | BJ54: 589 | BL54: 263 | BM54: 0 | BN54: 0 | BO54: 0.08849772 | BP54: 02-09-2026 10:05:00 | BU54: 2 | BV54: DEL-BHO | CA54: 263 | CB54: TeamLease Edtech Limited | CC54: 29AAPCS2871R1Z7 | CE54: F | CF54: '11817643109020835 | CJ54: SG0014 | CK54: LST
A55: Total | Q55: =SUM(Q4:Q54) -> 426660 | R55: =SUM(R4:R54) -> 6723 | S55: =SUM(S4:S54) -> 38527 | T55: =SUM(T4:T54) -> 21333 | U55: =SUM(U4:U54) -> 493243 | V55: =SUM(V4:V54) -> 3600
B58: Statement Summary | C58: Amount
B60: Airline Domestic Debit | C60: =U55 -> 493243
B62: Airline Domestic Misc. Debit | C62: ='MISCELLANEOUS DEBIT'!Q7 -> 1628
B64: Rail Debit | C64: ='RAIL DEBIT'!O18 -> 15901
B66: Bus Debit | C66: ='BUS DEBIT'!M5 -> 1470
B68: Hotel Debit | C68: ='HOTEL DEBIT'!W29 -> 196377
B70: Airline Domestic Credit | C70: ='DOMESTIC CREDIT'!X15 -> 116382
B72: Rail Credit | C72: ='RAIL CREDIT'!R5 -> 995
B74: Hotel Credit | C74: ='HOTEL CREDIT'!S6 -> 15960
B76: Service Chgs | C76: 7658 | D76: MS26-12279
B78: Total Due | C78: =SUM(C60:C69)-SUM(C70:C75)+C76 -> 582940

Sheet MISCELLANEOUS DEBIT
A1: Domestic Air Travel Miscellaneous Statement for the period 16-08-2026 to 31-08-2026
A3: Reference No. | B3: Reference Date | C3: Booking Date | D3: Department | E3: Location | F3: Passenger Name | G3: Employee Code | H3: Cost Center | I3: Cost Code | J3: Product Line | K3: Travel Date | L3: Sector | M3: Airline | N3: Flight No. | O3: Class | P3: Ticket No. | Q3: Total Fare | R3: Travel Management Fee | S3: Approver Name | T3: Approval Status | U3: Approval Date | V3: Approval Time | W3: Flown Status | X3: Corporate | Y3: Business Unit | Z3: Booking Reference No. | AA3: Trip Unique ID | AB3: Designation | AC3: Type Of Journey | AD3: Type Of Travel | AE3: Job Band | AF3: Passenger Email Id | AG3: Booking Code | AH3: YQ | AI3: YR | AJ3: Request No. | AK3: Request Created Date | AL3: Request Created Time | AM3: Trip Title | AN3: Fare Type | AO3: Purpose of Visit | AP3: Reissue Status | AQ3: Second Approver Name | AR3: Second Approval Status | AS3: Second Approval Date | AT3: Second Approval Time | AU3: Contact No. | AV3: GST No. | AW3: GST State | AX3: Service | AY3: Main Inv. No. | AZ3: Main Inv. Date | BA3: XL Code | BB3: HSN Code | BC3: Only Travel Date | BD3: TR ID | BE3: Debit Cost Code | BF3: Referred by | BG3: GL Code | BH3: Job Type | BI3: SAP / HR Company Code | BJ3: Adani Legal Entity GST Number | BK3: Job Reason | BL3: APPROVER_EMP_ID | BM3: APPROVER_BAND
A4: MW26/42976 | B4: 20-AUG-2026 | C4: 19/08/2026 | D4: University B2C | E4: Bengaluru | F4: Mr. UDITENDU BOSE | G4: SG0320 | H4: 3701618 | I4: 62-MUM-SSS | K4: 23/08/2026 11:35 | L4: Kolkata-Mumbai | M4: Indigo | N4: 6E-5288 | O4: Economy | P4: KDJR9N | Q4: 428 | R4: 80 | S4: Mr.ShantanuRooj | T4: Approved | U4: 19-08-2026 12:00:00 AM | W4: FLOWN | X4: Teamlease Services Ltd | Y4: TEAMLEASE EDTECH LIMITED | Z4: 200117999595 | AA4: 1388087 | AB4: Vice President - Consumer Sales | AC4: One Way | AD4: Domestic | AE4: L10 | AF4: uditendu.bose@teamlease.com | AG4: R | AH4: 0 | AI4: 0 | AJ4: 44806175 | AK4: 19-AUG-2026 | AL4: 16:55 | AN4: CORPORATE | AO4: Official | AP4: Original | AU4: 9971252225 | AV4: 29AAPCS2871R1Z7 | AW4: Karnataka | AX4: Seat Charges | AY4: DW26/799416 | AZ4: 19-08-2026 12:00:00 AM | BA4: T004S | BB4: 9963 | BC4: 23/08/2026 | BI4: TeamLease Edtech Limited | BJ4: 29AAPCS2871R1Z7 | BL4: SG0014 | BM4: LST
A5: DD26/6247 | B5: 19-AUG-2026 | C5: 19/08/2026 | D5: University B2C | E5: Bengaluru | F5: BOSE/UDITENDU MR | G5: SG0320 | H5: 3701618 | I5: 62-MUM-SSS | K5: 27-08-2026 12:00:00 AM | L5: Mumbai-Kolkata | M5: AIR INDIA LTD. | N5: AI2771 | O5: Economy | P5: 1946780348 | Q5: 975 | R5: 80 | S5: Mr.ShantanuRooj,Mr.ShantanuRooj | T5: Approved,Approved | U5: 19-AUG-2026,19-AUG-2026 | W5: FLOWN | X5: Teamlease Services Ltd | Y5: TEAMLEASE EDTECH LIMITED | Z5: 200117997991 | AA5: 1388087 | AB5: Vice President - Consumer Sales | AC5: Round Trip | AD5: Domestic | AE5: L10 | AF5: uditendu.bose@teamlease.com | AH5: 0 | AI5: 0 | AJ5: 44798324 | AK5: 19-AUG-2026 | AL5: 13:59 | AN5: CORPORATE | AO5: Official | AP5: Original | AU5: 9971252225 | AV5: 29AAPCS2871R1Z7 | AW5: Karnataka | AY5: DA26/181266 | AZ5: 19-08-2026 12:00:00 AM | BA5: T004S | BB5: 9963 | BC5: 27/08/2026 | BI5: TeamLease Edtech Limited | BJ5: 29AAPCS2871R1Z7 | BL5: SG0014,SG0014 | BM5: LST,LST
A6: DD26/6814 | B6: 30-AUG-2026 | C6: 30/08/2026 | D6: University B2C | E6: Bengaluru | F6: BOSE/UDITENDU MR | G6: SG0320 | H6: 3701618 | I6: 62-MUM-SSS | K6: 31-08-2026 12:00:00 AM | L6: Kolkata-New Delhi | M6: AIR INDIA LTD. | N6: AI1805 | O6: Economy | P6: 1946816928 | Q6: 225 | R6: 80 | S6: Mr.ShantanuRooj | T6: Approved | U6: 28-AUG-2026 | W6: FLOWN | X6: Teamlease Services Ltd | Y6: TEAMLEASE EDTECH LIMITED | Z6: 200118130772 | AA6: 1388087 | AB6: Vice President - Consumer Sales | AC6: One Way | AD6: Domestic | AE6: L10 | AF6: uditendu.bose@teamlease.com | AH6: 0 | AI6: 0 | AJ6: 44990409 | AK6: 28-AUG-2026 | AL6: 08:28 | AN6: CORPORATE | AO6: Official | AP6: Original | AU6: 9971252225 | AV6: 29AAPCS2871R1Z7 | AW6: Karnataka | AY6: DA26/192415 | AZ6: 28-08-2026 12:00:00 AM | BA6: T004S | BB6: 9963 | BC6: 31/08/2026 | BI6: TeamLease Edtech Limited | BJ6: 29AAPCS2871R1Z7 | BL6: SG0014 | BM6: LST
A7: Total | Q7: =SUM(Q4:Q6) -> 1628 | R7: =SUM(R4:R6) -> 240

Sheet RAIL DEBIT
A1: Rail Travel Statement for the period 16-08-2026 to 31-08-2026
A3: Reference No. | B3: Reference Date | C3: Booking Date | D3: Department | E3: Location | F3: Passenger Name | G3: Employee Code | H3: Cost Center | I3: Cost Code | J3: Travel Date | K3: Sector | L3: Train | M3: Class | N3: PNR No. | O3: Total Fare | P3: Travel Management Fee | Q3: Approver Name | R3: Approval Status | S3: Corporate | T3: Business Unit | U3: Booking Reference No. | V3: Trip Unique ID | W3: Rail Transation ID | X3: Rail Portal Code | Y3: Self Arranged | Z3: Request No. | AA3: Request Created Date | AB3: Purpose of Visit | AC3: Train Quota | AD3: Sector Short | AE3: Trip Title | AF3: State Name | AG3: XL Code | AH3: Job Band | AI3: KM | AJ3: Client Req No | AK3: PROJECT | AL3: TR ID | AM3: Debit Cost Code | AN3: Function | AO3: Referred By | AP3: GL Code | AQ3: Job Type | AR3: SAP / HR Company Code | AS3: Adani Legal Entity GST Number | AT3: Location Code | AU3: Gender | AV3: Unique ID | AW3: Gst Invoice No | AX3: Supplier GST No | AY3: Taxable Amt | AZ3: CGST Rate | BA3: CGST Amt | BB3: SGST UGST Rate | BC3: SGST UGST Amt | BD3: IGST Rate | BE3: IGST Amt | BF3: Total Tax | BG3: Job Reason | BH3: APPROVER_GRADE | BI3: APPROVER_EMPID | BJ3: GST_NO
A4: LW26/154872 | B4: 16-AUG-2026 | C4: 16-AUG-2026 | D4: University B2C | E4: Bengaluru | F4: MR. PREETISH GUPTA | G4: SG0516 | H4: 3701618 | I4: 62-MUM-SSS | J4: 17-AUG-2026 | K4: BORIVALI - BVI-GANDHINAGAR CAP - GNC | L4: ADI SHATABDI EXP | M4: CC | N4: 8152258307 | O4: 1462 | P4: 300 | Q4: Mr. UDITENDU BOSE | R4: Approved | S4: Teamlease Services Ltd | T4: TLEdtech | U4: 600117938493 | V4: Official | W4: 8152258307 | X4: EAKDANTA ENTERPRISES | Y4: N | Z4: 44714065 | AA4: 16-08-2026 09:16:03 AM | AB4: Official | AC4: TATKAL | AD4: BVI-GNC | AE4: Rail Service | AF4: Karnataka | AG4: T004S | AH4: L9 | AI4: 462 | AK4: - | AR4: TeamLease Edtech Limited | AS4: 29AAPCS2871R1Z7 | AU4: M | AV4: '11793849301388534 | AW4: 0 | AX4: 0 | AY4: 0 | AZ4: 0 | BA4: 0 | BB4: 0 | BC4: 0 | BD4: 0 | BE4: 0 | BF4: 0 | BH4: L10 | BI4: SG0320 | BJ4: 29AAPCS2871R1Z7
A5: LW26/156223 | B5: 17-AUG-2026 | C5: 17-AUG-2026 | D5: University Bd | E5: Bengaluru | F5: MR. NAKUL JOSHI | G5: T15226 | I5: 61-MUM-USE | J5: 18-AUG-2026 | K5: MUMBAI CENTRAL - MMCT-VADODARA JN - BRC | L5: ADI SHATABDI EX | M5: CC | N5: 8833051579 | O5: 1193 | P5: 300 | Q5: Ms. Deepti DEEPTI | R5: Approved | S5: Teamlease Services Ltd | T5: TLEdtech | U5: 600117949444 | V5: Official | W5: 100006776270404 | X5: GUPTA TRAVELS PUNE | Y5: N | Z5: 44666082 | AA5: 13-08-2026 04:42:02 PM | AB5: Official | AC5: TATKAL | AD5: MMCT-BRC | AE5: Rail Service | AF5: Karnataka | AG5: T004S | AH5: L7 | AI5: 392 | AK5: - | AR5: TeamLease Edtech Limited | AS5: 29AAPCS2871R1Z7 | AU5: M | AV5: '11794944402413020 | AW5: 100006776270404 | AX5: 100006776270404 | AY5: 0 | AZ5: 0 | BA5: 0 | BB5: 0 | BC5: 0 | BD5: 0 | BE5: 0 | BF5: 0 | BH5: L8 | BI5: T17404 | BJ5: 29AAPCS2871R1Z7
A6: LW26/155606 | B6: 17-AUG-2026 | C6: 17-AUG-2026 | D6: University B2C | E6: Bengaluru | F6: MR. MALLA HARI KRISHNA NA | G6: T14999 | I6: 62-MUM-USP | J6: 18-AUG-2026 | K6: VIJAYAWADA JN - BZA-ANANTAPUR - ATP | L6: MTM DMM EXP | M6: 3A | N6: 4343122003 | O6: 1027 | P6: 100 | Q6: Mr. VENKATA SWAMI NAIDU SURISETTY | R6: Approved | S6: Teamlease Services Ltd | T6: TLEdtech | U6: 600117954902 | V6: Official | W6: 4343122003 | X6: AKHTAR HOSSAIN | Y6: N | Z6: 44732008 | AA6: 17-08-2026 12:17:48 PM | AB6: Official | AC6: GENERAL | AD6: BZA-ATP | AE6: Rail Service | AF6: Karnataka | AG6: T004S | AH6: L6 | AI6: 581 | AK6: - | AR6: TeamLease Edtech Limited | AS6: 29AAPCS2871R1Z7 | AU6: M | AV6: '11795490201919861 | AW6: PS26434312200311 | AX6: 07AAAGM0289C1ZL | AY6: 900 | AZ6: 2.5 | BA6: 0 | BB6: 5 | BC6: 0 | BD6: 5 | BE6: 5.4 | BF6: 5.4 | BH6: L8 | BI6: T16637 | BJ6: 29AAPCS2871R1Z7
A7: LW26/155922 | B7: 17-AUG-2026 | C7: 17-AUG-2026 | D7: University B2C | E7: Bengaluru | F7: MR. MALLA HARI KRISHNA NA | G7: T14999 | I7: 62-MUM-USP | J7: 18-AUG-2026 | K7: VISHAKAPATNAM - VSKP-VIJAYAWADA JN - BZA | L7: RATNANCHAL SF EX | M7: 2S | N7: 6948256362 | O7: 219 | P7: 300 | Q7: Mr. VENKATA SWAMI NAIDU SURISETTY | R7: Approved | S7: Teamlease Services Ltd | T7: TLEdtech | U7: 600117954881 | V7: Official | W7: 6948256362 | X7: BHARAT TRAVELS | Y7: N | Z7: 44732008 | AA7: 17-08-2026 12:17:48 PM | AB7: Official | AC7: TATKAL | AD7: VSKP-BZA | AE7: Rail Service | AF7: Karnataka | AG7: T004S | AH7: L6 | AI7: 350 | AK7: - | AR7: TeamLease Edtech Limited | AS7: 29AAPCS2871R1Z7 | AU7: M | AV7: '11795488101919861 | AW7: PS26694825636211 | AX7: 07AAAGM0289C1ZL | AY7: 180 | AZ7: 0 | BA7: 0 | BB7: 0 | BC7: 0 | BD7: 0 | BE7: 0 | BF7: 0 | BH7: L8 | BI7: T16637 | BJ7: 29AAPCS2871R1Z7
A8: LW26/156901 | B8: 17-AUG-2026 | C8: 17-AUG-2026 | D8: University B2C | E8: Bengaluru | F8: MR. MALLA HARI KRISHNA NA | G8: T14999 | I8: 62-MUM-USP | J8: 20-AUG-2026 | K8: NELLORE - NLR-VIJAYAWADA JN - BZA | L8: SIMHAPURI SF EX | M8: 3E | N8: 4763105013 | O8: 645 | P8: 100 | Q8: Mr. VENKATA SWAMI NAIDU SURISETTY | R8: Approved | S8: Teamlease Services Ltd | T8: TLEdtech | U8: 600117963586 | V8: Official | W8: 100006777333268 | X8: GUPTA TRAVELS PUNE | Y8: N | Z8: 44746254 | AA8: 17-08-2026 05:07:16 PM | AB8: Official | AC8: GENERAL | AD8: NLR-BZA | AE8: Rail Service | AF8: Karnataka | AG8: T004S | AH8: L6 | AI8: 255 | AK8: - | AR8: TeamLease Edtech Limited | AS8: 29AAPCS2871R1Z7 | AU8: M | AV8: '11796358601919861 | AW8: PS26476310501311 | AX8: 07AAAGM0289C1ZL | AY8: 538 | AZ8: 0 | BA8: 0 | BB8: 0 | BC8: 0 | BD8: 5 | BE8: 0 | BF8: 0 | BH8: L8 | BI8: T16637 | BJ8: 29AAPCS2871R1Z7
A9: LW26/157627 | B9: 18-AUG-2026 | C9: 18-AUG-2026 | D9: University Bd | E9: Bengaluru | F9: MR. ASHUTOSH DUBEY | G9: T17010 | I9: 61-MUM-USE | J9: 25-AUG-2026 | K9: KAMAKHYA - KYQ-PATNA JN - PNBE | L9: CAPITAL EXPRESS | M9: 3A | N9: 6608204369 | O9: 1411 | P9: 100 | Q9: Mr. MAHESH KUMAR | R9: Approved | S9: Teamlease Services Ltd | T9: TLEdtech | U9: 600117975205 | V9: Official | W9: 6608204369 | X9: Akbar - 1 | Y9: N | Z9: 44764099 | AA9: 18-08-2026 12:04:50 PM | AB9: Official | AC9: GENERAL | AD9: KYQ-PNBE | AE9: Rail Service | AF9: Karnataka | AG9: T004S | AH9: L7 | AI9: 980 | AK9: - | AR9: TeamLease Edtech Limited | AS9: 29AAPCS2871R1Z7 | AU9: M | AV9: '11797520506003228 | AW9: PS26660820436911 | AX9: 07AAAGM0289C1ZL | AY9: 1262 | AZ9: 0 | BA9: 0 | BB9: 0 | BC9: 0 | BD9: 5 | BE9: 62.95 | BF9: 62.95 | BH9: L8 | BI9: T15604 | BJ9: 29AAPCS2871R1Z7
A10: LW26/162124 | B10: 21-AUG-2026 | C10: 21-AUG-2026 | D10: University B2C | E10: Bengaluru | F10: MR. ABHISHEK MATONDKAR | G10: T17720 | I10: 62-MUM-SSS | J10: 22-AUG-2026 | K10: BORIVALI - BVI-SURAT - ST | L10: ADI SHATABDI EXP | M10: CC | N10: 8940700511 | O10: 932 | P10: 300 | Q10: MR. Preetish Gupta | R10: Approved | S10: Teamlease Services Ltd | T10: TLEdtech | U10: 600118029094 | V10: Official | W10: 8940700511 | X10: SIDDHIVINAYAK TOUR & TRAVELS | Y10: N | Z10: 44835799 | AA10: 20-08-2026 06:23:06 PM | AB10: Official | AC10: TATKAL | AD10: BVI-ST | AE10: Rail Service | AF10: Karnataka | AG10: T004S | AH10: L5 | AI10: 233 | AK10: - | AR10: TeamLease Edtech Limited | AS10: 29AAPCS2871R1Z7 | AU10: M | AV10: '11802909407403372 | AW10: PS26894070051111 | AX10: 07AAAGM0289C1ZL | AY10: 687 | AZ10: 0 | BA10: 0 | BB10: 0 | BC10: 0 | BD10: 5 | BE10: 34.35 | BF10: 34.35 | BH10: L9 | BI10: SG0516 | BJ10: 29AAPCS2871R1Z7
A11: LW26/164005 | B11: 23-AUG-2026 | C11: 23-AUG-2026 | D11: University Bd | E11: Bengaluru | F11: MR. NAKUL JOSHI | G11: T15226 | I11: 61-MUM-USE | J11: 26-AUG-2026 | K11: MUMBAI CST (CSMT) - CSMT-C SAMBHAJINAGAR - CPSN | L11: NED VANDEBHARAT | M11: CC | N11: 8752577922 | O11: 1274 | P11: 100 | Q11: Ms. Deepti DEEPTI | R11: Approved | S11: Teamlease Services Ltd | T11: TLEdtech | U11: 600118055399 | V11: Official | W11: 8752577922 | X11: igandhi00239 | Y11: N | Z11: 44873126 | AA11: 22-08-2026 03:37:52 PM | AB11: Official | AC11: GENERAL | AD11: CSMT-CPSN | AE11: Rail Service | AF11: Karnataka | AG11: T004S | AH11: L7 | AI11: 374 | AK11: - | AR11: TeamLease Edtech Limited | AS11: 29AAPCS2871R1Z7 | AU11: M | AV11: '11805539902413020 | AW11: PS26875257792211 | AX11: 07AAAGM0289C1ZL | AY11: 840 | AZ11: 0 | BA11: 0 | BB11: 0 | BC11: 0 | BD11: 5 | BE11: 42 | BF11: 42 | BH11: L8 | BI11: T17404 | BJ11: 29AAPCS2871R1Z7
A12: LW26/164098 | B12: 23-AUG-2026 | C12: 23-AUG-2026 | D12: University Bd | E12: Bengaluru | F12: MR. NAKUL JOSHI | G12: T15226 | I12: 61-MUM-USE | J12: 24-AUG-2026 | K12: AHMEDABAD JN - ADI-BORIVALI - BVI | L12: VANDE BHARAT EXP | M12: CC | N12: 8352563039 | O12: 1496 | P12: 300 | Q12: Ms. Deepti DEEPTI | R12: Approved | S12: Teamlease Services Ltd | T12: TLEdtech | U12: 600118052657 | V12: Official | W12: 100006789472344 | X12: GUPTA TRAVELS PUNE | Y12: N | Z12: 44869781 | AA12: 22-08-2026 12:50:32 PM | AB12: Official | AC12: TATKAL | AD12: ADI-BVI | AE12: Rail Service | AF12: Karnataka | AG12: T004S | AH12: L7 | AI12: 462 | AK12: - | AR12: TeamLease Edtech Limited | AS12: 29AAPCS2871R1Z7 | AU12: M | AV12: '11805265702413020 | AW12: PS26835256303911 | AX12: 07AAAGM0289C1ZL | AY12: 1208 | AZ12: 0 | BA12: 0 | BB12: 0 | BC12: 0 | BD12: 5 | BE12: 0 | BF12: 0 | BH12: L8 | BI12: T17404 | BJ12: 29AAPCS2871R1Z7
A13: LW26/166726 | B13: 26-AUG-2026 | C13: 26-AUG-2026 | D13: Operations | E13: Bengaluru | F13: MRS. SRIMATHI R | G13: SG0444 | H13: 3701618 | I13: 61-MUM-ASO | J13: 01-SEP-2026 | K13: JHANSI C B - JCO-AGRA CANTT - AGC | L13: VANDE BHARAT EXP | M13: CC | N13: 2742577678 | O13: 1013 | P13: 100 | Q13: Mr. JAIDEEP KEWALRAMANI | R13: Approved | S13: Teamlease Services Ltd | T13: TLEdtech | U13: 600118102038 | V13: Official | W13: 2742577678 | X13: EAKDANTA ENTERPRISES | Y13: N | Z13: 44947720 | AA13: 26-08-2026 11:15:18 AM | AB13: Official | AC13: GENERAL | AD13: JCO-AGC | AE13: Rail Service | AF13: Karnataka | AG13: T004S | AH13: L10 | AI13: 216 | AK13: - | AR13: TeamLease Edtech Limited | AS13: 29AAPCS2871R1Z7 | AU13: F | AV13: '11810203801388479 | AW13: PS26274257767811 | AX13: 07AAAGM0289C1ZL | AY13: 593 | AZ13: 2.5 | BA13: 0 | BB13: 2.5 | BC13: 0 | BD13: 5 | BE13: 29.5 | BF13: 29.5 | BH13: LST | BI13: T12553 | BJ13: 29AAPCS2871R1Z7
A14: LW26/166954 | B14: 26-AUG-2026 | C14: 26-AUG-2026 | D14: University Bd | E14: Bengaluru | F14: MR. NAKUL JOSHI | G14: T15226 | I14: 61-MUM-USE | J14: 27-AUG-2026 | K14: C SAMBHAJINAGAR - CPSN-MUMBAI CST - CSMT | L14: DEVAGIRI EXP | M14: 2A | N14: 4863577613 | O14: 1652 | P14: 300 | Q14: Ms. Deepti DEEPTI | R14: Approved | S14: Teamlease Services Ltd | T14: TLEdtech | U14: 600118099770 | V14: Official | W14: 4863577613 | X14: EAKDANTA ENTERPRISES | Y14: N | Z14: 44926431 | AA14: 25-08-2026 01:09:39 PM | AB14: Official | AC14: TATKAL | AD14: CPSN-CSMT | AE14: Rail Service | AF14: Karnataka | AG14: T004S | AH14: L7 | AI14: 374 | AK14: - | AR14: TeamLease Edtech Limited | AS14: 29AAPCS2871R1Z7 | AU14: M | AV14: '11809977002413020 | AW14: PS26486357761311 | AX14: 07AAAGM0289C1ZL | AY14: 1490 | AZ14: 2.5 | BA14: 0 | BB14: 2.5 | BC14: 0 | BD14: 5 | BE14: 74.3 | BF14: 74.3 | BH14: L8 | BI14: T17404 | BJ14: 29AAPCS2871R1Z7
A15: LW26/168101 | B15: 27-AUG-2026 | C15: 27-AUG-2026 | D15: University B2C | E15: Bengaluru | F15: MR. BIPIN KUMAR TIWARI | G15: T16960 | I15: 72-MUM-HBC | J15: 01-SEP-2026 | K15: H NIZAMUDDIN - NZM-V LAKSHMIBAI - VGLJ | L15: VANDE BHARAT EXP | M15: CC | N15: 2958012094 | O15: 1124 | P15: 100 | Q15: MR. Chetan Dixit | R15: Approved | S15: Teamlease Services Ltd | T15: TLEdtech | U15: 600118123120 | V15: Official | W15: 2958012094 | X15: Akbar - 1 | Y15: N | Z15: 44979641 | AA15: 27-08-2026 03:33:04 PM | AB15: Scheduled Visit | AC15: GENERAL | AD15: NZM-VGLJ | AE15: Rail Service | AF15: Karnataka | AG15: T004S | AH15: L8 | AI15: 403 | AK15: - | AR15: TeamLease Edtech Limited | AS15: 29AAPCS2871R1Z7 | AU15: M | AV15: '11812312005920959 | AW15: PS26295801209411 | AX15: 07AAAGM0289C1ZL | AY15: 889 | AZ15: 0 | BA15: 22.22 | BB15: 0 | BC15: 0 | BD15: 0 | BE15: 0 | BF15: 44.44 | BH15: L9 | BI15: SG0506 | BJ15: 29AAPCS2871R1Z7
A16: LW26/168100 | B16: 27-AUG-2026 | C16: 27-AUG-2026 | D16: University Bd | E16: Bengaluru | F16: MR. SHUBHAM DUBEY | G16: T15255 | I16: 61-MUM-USE | J16: 01-SEP-2026 | K16: H NIZAMUDDIN - NZM-V LAKSHMIBAI - VGLJ | L16: VANDE BHARAT EXP | M16: CC | N16: 2958012094 | O16: 1124 | P16: 100 | Q16: Mr. MAHESH KUMAR | R16: Approved | S16: Teamlease Services Ltd | T16: TLEdtech | U16: 600118123113 | V16: Official | W16: 2958012094 | X16: Akbar - 1 | Y16: N | Z16: 44979533 | AA16: 27-08-2026 03:27:20 PM | AB16: Official | AC16: GENERAL | AD16: NZM-VGLJ | AE16: Rail Service | AF16: Karnataka | AG16: T004S | AH16: L7 | AI16: 403 | AK16: - | AR16: TeamLease Edtech Limited | AS16: 29AAPCS2871R1Z7 | AU16: M | AV16: '11812311302467576 | AW16: PS26295801209411 | AX16: 07AAAGM0289C1ZL | AY16: 889.5 | AZ16: 0 | BA16: 22.22 | BB16: 0 | BC16: 0 | BD16: 0 | BE16: 0 | BF16: 44.44 | BH16: L8 | BI16: T15604 | BJ16: 29AAPCS2871R1Z7
A17: LW26/169345 | B17: 28-AUG-2026 | C17: 28-AUG-2026 | D17: University B2C | E17: Bengaluru | F17: MR. BIPIN KUMAR TIWARI | G17: T16960 | I17: 72-MUM-HBC | J17: 02-SEP-2026 | K17: V LAKSHMIBAI - VGLJ-H NIZAMUDDIN - NZM | L17: VANDE BHARAT EXP | M17: CC | N17: 2523921693 | O17: 1329 | P17: 100 | Q17: MR. Chetan Dixit | R17: Approved | S17: Teamlease Services Ltd | T17: TLEdtech | U17: 600118140227 | V17: Official | W17: 2523921693 | X17: AKHTAR HOSSAIN | Y17: N | Z17: 44979641 | AA17: 27-08-2026 03:33:04 PM | AB17: Scheduled Visit | AC17: GENERAL | AD17: VGLJ-NZM | AE17: Rail Service | AF17: Karnataka | AG17: T004S | AH17: L8 | AI17: 403 | AK17: - | AR17: TeamLease Edtech Limited | AS17: 29AAPCS2871R1Z7 | AU17: M | AV17: '11814022705920959 | AW17: PS26252392169311 | AX17: 07AAAGM0289C1ZL | AY17: 893 | AZ17: 2.5 | BA17: 0 | BB17: 5 | BC17: 0 | BD17: 5 | BE17: 5.4 | BF17: 5.4 | BH17: L9 | BI17: SG0506 | BJ17: 29AAPCS2871R1Z7
A18: Total | O18: =SUM(O4:O17) -> 15901 | P18: =SUM(P4:P17) -> 2600

Sheet BUS DEBIT
A1: Bus Travel Statement for the period 16-08-2026 to 31-08-2026
A3: Reference No. | B3: Reference Date | C3: Booking Date | D3: Department | E3: Passenger Name | F3: Employee Code | G3: Cost Center | H3: Travel Date | I3: Sector | J3: Bus Type | K3: Seat No. | L3: Ticket No. | M3: Total Fare | N3: Travel Management Fee | O3: Approver Name | P3: Approval Status | Q3: Corporate | R3: Business Unit | S3: Booking Reference No. | T3: Trip Unique Id | U3: Purpose | V3: Designation | W3: Job Band | X3: Passenger Email Id | Y3: Request No. | Z3: Self Arranged | AA3: Travels Name | AB3: State Name | AC3: XL Code | AD3: Only Travel Date | AE3: Cost Code | AF3: Client Req No | AG3: Function | AH3: TR ID | AI3: Debit Cost Code | AJ3: Referred By | AK3: GL Code | AL3: Job Type | AM3: Location | AN3: SAP / HR Company Code | AO3: Adani Legal Entity GST Number | AP3: Unique ID | AQ3: Job Reason | AR3: APPROVER_EMPID | AS3: APPROVER_GRADE
A4: MW26/45813 | B4: 29-08-2026 12:00:00 AM | C4: 29-08-2026 08:08:43 PM | D4: Impact | E4: MR. VARUN MAHESHWARI | F4: T15657 | H4: 01-09-2026 09:00:00 PM | I4: Baroda - Pune | J4: Bharat Benz A/C Sleeper (2+1) | K4: C | L4: 9B6976AV | M4: 1470 | N4: 50 | O4: Mr. JAIDEEP KEWALRAMANI | P4: Approved | Q4: Teamlease Services Ltd | R4: TLEdtech | S4: 120730597 | T4: 45014729 | U4: Official | V4: General Manager | W4: L9 | X4: varun.maheshwari@teamlease.com | Y4: 45014729 | Z4: N | AA4: Shrinath Solitaire | AB4: Karnataka | AC4: T004S | AD4: 01-09-2026 | AE4: 64-BAN-CSS | AM4: Bengaluru | AN4: TeamLease Edtech Limited | AO4: 29AAPCS2871R1Z7 | AP4: '73059702897978 | AR4: T12553 | AS4: LST
A5: Total | M5: =SUM(M4:M4) -> 1470 | N5: =SUM(N4:N4) -> 50

Sheet HOTEL DEBIT
A1: Hotel Statement for the period 16-08-2026 to 31-08-2026
A3: Reference No. | B3: Reference Date | C3: Request No. | D3: Reference No. | E3: Booking Reference No. | F3: Employee Id | G3: Employee Name | H3: Designation | I3: Cost Center | J3: Cost Code | K3: Check In Date | L3: Check Out Date | M3: No. of Rooms | N3: No. of Nights | O3: Hotel City | P3: Hotel State | Q3: Hotel Name | R3: Base Fare | S3: GST | T3: Extra Guest Charge | U3: Hotel Service Charge | V3: Discount | W3: Q2T Invoice Amount | X3: Approver Name | Y3: Approval Status | Z3: Corporate | AA3: Business Unit | AB3: Purpose | AC3: Request Created Date | AD3: Purpose | AE3: Estimated Cost | AF3: Booking Status | AG3: Cancellation Reason | AH3: Cancel Date & Time | AI3: XL Code | AJ3: Client GST No. | AK3: GST Assured | AL3: Project | AM3: Emp Grade | AN3: First Approver Name | AO3: Second Approver Name | AP3: API Used | AQ3: Department | AR3: Client Req No | AS3: Travel Management Fee | AT3: TR ID | AU3: Debit Cost Code | AV3: Function | AW3: Referred By | AX3: GL Code | AY3: Job Type | AZ3: Location | BA3: Booking Id | BB3: Division Name | BC3: SAP / HR Company Code | BD3: Adani Legal Entity GST Number | BE3: Gender | BF3: Hotel Group | BG3: Location Name | BH3: Hotel Type | BI3: Occupancy type | BJ3: first Approval Date | BK3: first Approval time | BL3: secound Approval Date | BM3: secound Approval time | BN3: Agent Number | BO3: Job Reason | BP3: APPROVER_EMP_ID1 | BQ3: APPROVER_EMP_ID2 | BR3: APPROVER_GRADE1 | BS3: APPROVER_GRADE2
A4: HW26/350900 | B4: 17-08-2026 12:00:00 AM | C4: 44748981 | D4: 69849233 | E4: 500117962121 | F4: T14999 | G4: Mr. Malla Hari Krishna Na | H4: Manager | J4: 62-MUM-USP | K4: 19-08-2026 12:00:00 PM | L4: 20-08-2026 12:00:00 PM | M4: 1 | N4: 1 | O4: Nellore | P4: Andhra Pradesh | Q4: Hotel Inn The Centre | R4: 1650 | S4: 82.5 | T4: 0 | U4: 0 | V4: 66 | W4: 1667 | X4: Mr. VENKATA SWAMI NAIDU SURISETTY | Y4: Approved | Z4: Teamlease Services Ltd | AA4: TLEdtech | AB4: Official | AC4: 17-08-2026 12:00:00 AM | AD4: Official | AE4: 1584 | AF4: Booked | AI4: T004S | AJ4: 27AAPCS2871R1ZB | AK4: Y | AL4: - | AM4: L6 | AN4: Mr. VENKATA SWAMI NAIDU SURISETTY | AP4: MMT | AQ4: University B2C | AS4: 0 | AZ4: Bengaluru | BA4: NH13100509867280 | BC4: TeamLease Edtech Limited | BD4: 27AAPCS2871R1ZB | BE4: M | BH4: D | BI4: Single | BJ4: 17-08-2026 | BK4: 18:11 | BP4: T16637 | BR4: L8
A5: HW26/351987 | B5: 17-08-2026 12:00:00 AM | C5: 44724877 | D5: 69804994 | E5: 500117967831 | F5: T11294 | G5: Mr. Roshan Deepak Pinto | H5: Senior General Manager | I5: 3701618 | J5: 67-MUM-ELO | K5: 24-08-2026 01:00:00 PM | L5: 26-08-2026 12:00:00 PM | M5: 1 | N5: 2 | O5: Noida | P5: Uttar Pradesh | Q5: Mosaic Original, Noida | R5: 12462.29 | S5: 623.12 | T5: 0 | U5: 0 | V5: 498 | W5: 12587 | X5: Mr. JAIDEEP KEWALRAMANI | Y5: Approved | Z5: Teamlease Services Ltd | AA5: TLEdtech | AB5: Official | AC5: 17-08-2026 12:00:00 AM | AD5: Official | AE5: 11964 | AF5: Booked | AI5: T004S | AJ5: 27AAPCS2871R1ZB | AK5: Y | AL5: - | AM5: L9 | AN5: Mr. JAIDEEP KEWALRAMANI | AP5: MMT | AQ5: Operations | AS5: 0 | AZ5: Bengaluru | BA5: NH17063509952910 | BC5: TeamLease Edtech Limited | BD5: 27AAPCS2871R1ZB | BE5: M | BF5: Mosaic Group | BH5: D | BI5: Single | BJ5: 17-08-2026 | BK5: 23:57 | BP5: T12553 | BR5: LST
A6: HW26/352534 | B6: 18-08-2026 12:00:00 AM | C6: 44759631 | D6: 69868418 | E6: 500117970189 | F6: T17010 | G6: Mr. Ashutosh Dubey | H6: Senior Manager | J6: 61-MUM-USE | K6: 24-08-2026 12:00:00 PM | L6: 25-08-2026 11:00:00 AM | M6: 1 | N6: 1 | O6: Guwahati | P6: Assam | Q6: The Ornate | R6: 3925 | S6: 196.25 | T6: 0 | U6: 0 | V6: 157 | W6: 3964 | X6: Mr. MAHESH KUMAR | Y6: Approved | Z6: Teamlease Services Ltd | AA6: TLEdtech | AB6: Official | AC6: 18-08-2026 12:00:00 AM | AD6: Official | AE6: 3768 | AF6: Booked | AI6: T004S | AJ6: 27AAPCS2871R1ZB | AK6: Y | AL6: - | AM6: L7 | AN6: Mr. MAHESH KUMAR | AP6: MMT | AQ6: University Bd | AS6: 0 | AZ6: Bengaluru | BA6: NH15167509996686 | BC6: TeamLease Edtech Limited | BD6: 27AAPCS2871R1ZB | BE6: M | BF6: Aiosell | BH6: D | BI6: Single | BJ6: 18-08-2026 | BK6: 10:15 | BP6: T15604 | BR6: L8
A7: HW26/352639 | B7: 18-08-2026 12:00:00 AM | C7: 44725527 | D7: 69870043 | E7: 500117970809 | F7: T16161 | G7: Mr. Aayush Lal | H7: Senior Project Manager | J7: 69-MUM-PBP | K7: 19-08-2026 12:00:00 PM | L7: 21-08-2026 11:00:00 AM | M7: 1 | N7: 2 | O7: Tada | P7: Andhra Pradesh | Q7: Hotel SRM GRANDEURS | R7: 7110 | S7: 355.5 | T7: 0 | U7: 0 | V7: 284 | W7: 7182 | X7: MS. NIDHI RAJESH BAGLA | Y7: Approved | Z7: Teamlease Services Ltd | AA7: TLEdtech | AB7: Official | AC7: 18-08-2026 12:00:00 AM | AD7: Official | AE7: 7182 | AF7: Booked | AI7: T004S | AJ7: 27AAPCS2871R1ZB | AK7: Y | AL7: - | AM7: L7 | AN7: MS. NIDHI RAJESH BAGLA | AP7: MMT | AQ7: Operations | AS7: 0 | AZ7: Bengaluru | BA7: NH14054510002466 | BC7: TeamLease Edtech Limited | BD7: 27AAPCS2871R1ZB | BE7: M | BH7: D | BI7: Single | BJ7: 18-08-2026 | BK7: 10:43 | BP7: T17642 | BR7: L8
A8: HW26/353638 | B8: 18-08-2026 12:00:00 AM | C8: 44767096 | D8: 69882096 | E8: 500117975942 | F8: SG0516 | G8: Mr. Preetish Gupta | H8: Associate Sales Director | I8: 3701618 | J8: 62-MUM-SSS | K8: 19-08-2026 01:00:00 PM | L8: 21-08-2026 12:00:00 PM | M8: 1 | N8: 2 | O8: Bengaluru | P8: Karnataka | Q8: Goldfinch Hotel Bangalore | R8: 12398 | S8: 619.9 | T8: 0 | U8: 0 | V8: 495 | W8: 12523 | X8: Mr. UDITENDU BOSE | Y8: Approved | Z8: Teamlease Services Ltd | AA8: TLEdtech | AB8: Official | AC8: 18-08-2026 12:00:00 AM | AD8: Official | AE8: 11903 | AF8: Booked | AI8: T004S | AJ8: 29AAPCS2871R1Z7 | AK8: Y | AL8: - | AM8: L9 | AN8: Mr. UDITENDU BOSE | AP8: MMT | AQ8: University B2C | AS8: 0 | AZ8: Bengaluru | BA8: NH10110510050346 | BC8: TeamLease Edtech Limited | BD8: 29AAPCS2871R1Z7 | BE8: M | BF8: Goldfinch Hotels | BH8: D | BI8: Single | BJ8: 18-08-2026 | BK8: 14:00 | BP8: SG0320 | BR8: L10
A9: HW26/356491 | B9: 19-08-2026 12:00:00 AM | C9: 44759053 | D9: 69867347 | E9: 500117988695 | F9: T11294 | G9: Mr. Roshan Deepak Pinto | H9: Senior General Manager | I9: 3701618 | J9: 67-MUM-ELO | K9: 19-08-2026 12:00:00 PM | L9: 21-08-2026 12:00:00 PM | M9: 1 | N9: 2 | O9: Vijayawada | P9: Andhra Pradesh | Q9: Jade Suites - Luxury Boutique Hotel | R9: 8550 | S9: 427.5 | T9: 0 | U9: 0 | V9: 342 | W9: 8636 | X9: Mr. JAIDEEP KEWALRAMANI | Y9: Approved | Z9: Teamlease Services Ltd | AA9: TLEdtech | AB9: Official | AC9: 18-08-2026 09:37:19 AM | AD9: Official | AE9: 9600 | AF9: Booked | AI9: T004S | AJ9: 27AAPCS2871R1ZB | AK9: Y | AL9: - | AM9: L9 | AN9: Mr. JAIDEEP KEWALRAMANI | AP9: MMT | AQ9: Operations | AS9: 0 | AZ9: Bengaluru | BA9: NH16239510227936 | BC9: TeamLease Edtech Limited | BD9: 27AAPCS2871R1ZB | BE9: M | BH9: D | BI9: Single | BJ9: 18-08-2026 | BK9: 23:27 | BP9: T12553 | BR9: LST
A10: HW26/362339 | B10: 20-08-2026 12:00:00 AM | C10: 44829212 | D10: 69991281 | E10: 500118018642 | F10: T16151 | G10: Ms. Shrutika Sharma | H10: Assistant General Manager | J10: 69-MUM-PBD | K10: 31-08-2026 02:00:00 PM | L10: 03-09-2026 11:00:00 AM | M10: 1 | N10: 3 | O10: Bengaluru | P10: Karnataka | Q10: Bloom Hotel HAL Old Airport Rd | R10: 14522.67 | S10: 726.12 | T10: 0 | U10: 0 | V10: 580 | W10: 14669 | X10: MS. Geetika Kohli | Y10: Approved | Z10: Teamlease Services Ltd | AA10: TLEdtech | AB10: Official | AC10: 20-08-2026 12:00:00 AM | AD10: Official | AE10: 13943 | AF10: Booked | AI10: T004S | AJ10: 29AAPCS2871R1Z7 | AK10: Y | AL10: - | AM10: L8 | AN10: MS. Geetika Kohli | AP10: MMT | AQ10: Premier B2C | AS10: 0 | AZ10: Bengaluru | BA10: NH19149510618050 | BC10: TeamLease Edtech Limited | BD10: 29AAPCS2871R1Z7 | BE10: F | BF10: Bloom Rooms | BH10: D | BI10: Single | BJ10: 20-08-2026 | BK10: 17:10 | BP10: SG0400 | BR10: L10
A11: HW26/365169 | B11: 21-08-2026 12:00:00 AM | C11: 44858020 | D11: 70039755 | E11: 500118035080 | F11: T16692 | G11: Mr. Prathamesh Jadhav | H11: Manager | J11: 62-MUM-PBO | K11: 23-08-2026 01:00:00 PM | L11: 27-08-2026 11:00:00 AM | M11: 1 | N11: 4 | O11: Tada | P11: Andhra Pradesh | Q11: Monarch Express, Sri City | R11: 13618.53 | S11: 680.93 | T11: 0 | U11: 0 | V11: 544 | W11: 13755 | X11: MS. NIDHI RAJESH BAGLA | Y11: Approved | Z11: Teamlease Services Ltd | AA11: TLEdtech | AB11: Official | AC11: 21-08-2026 12:00:00 AM | AD11: Official | AE11: 13075 | AF11: Booked | AG11: Plan changed and cancelled. | AH11: 22-08-2026 03:17:58 PM | AI11: T004S | AJ11: 27AAPCS2871R1ZB | AK11: Y | AL11: - | AM11: L6 | AN11: MS. NIDHI RAJESH BAGLA | AP11: MMT | AQ11: Operations | AS11: 0 | AZ11: Bengaluru | BA11: NH14000510876368 | BC11: TeamLease Edtech Limited | BD11: 27AAPCS2871R1ZB | BE11: M | BH11: D | BI11: Single | BJ11: 21-08-2026 | BK11: 17:18 | BP11: T17642 | BR11: L8
A12: HW26/366258 | B12: 22-08-2026 12:00:00 AM | C12: 44856343 | D12: 70036749 | E12: 500118040754 | F12: SG0444 | G12: Mrs. Srimathi R | H12: Head - University Operations | I12: 3701618 | J12: 61-MUM-ASO | K12: 31-08-2026 02:00:00 PM | L12: 02-09-2026 12:00:00 PM | M12: 1 | N12: 2 | O12: Jhansi | P12: Uttar Pradesh | Q12: Nataraj Sarovar Portico | R12: 8001 | S12: 400.05 | T12: 0 | U12: 0 | V12: 320 | W12: 8081 | X12: Mr. JAIDEEP KEWALRAMANI | Y12: Approved | Z12: Teamlease Services Ltd | AA12: TLEdtech | AB12: Official | AC12: 21-08-2026 12:00:00 AM | AD12: Official | AE12: 7901 | AF12: Booked | AG12: Quest Portal is not executing partial cancellation request . Hence as advised by Quest, cancelling it fully and doing a fresh booking for one night stay at Jhansi | AH12: 26-08-2026 02:50:55 PM | AI12: T004S | AJ12: 27AAPCS2871R1ZB | AK12: Y | AL12: - | AM12: L10 | AN12: Mr. JAIDEEP KEWALRAMANI | AP12: MMT | AQ12: Operations | AS12: 0 | AZ12: Bengaluru | BA12: NH15247510997794 | BC12: TeamLease Edtech Limited | BD12: 27AAPCS2871R1ZB | BE12: F | BF12: Sarovar Group of Hotels | BH12: D | BI12: Single | BJ12: 22-08-2026 | BK12: 03:59 | BP12: T12553 | BR12: LST
A13: HW26/367255 | B13: 22-08-2026 12:00:00 AM | C13: 44875697 | D13: 70069549 | E13: 500118048222 | F13: T15255 | G13: Mr. Shubham Dubey | H13: Senior Manager | J13: 61-MUM-USE | K13: 24-08-2026 02:00:00 PM | L13: 25-08-2026 11:00:00 AM | M13: 1 | N13: 1 | O13: Dehradun | P13: Uttarakhand | Q13: Sterling Marbella Dehradun | R13: 3445.64 | S13: 172.28 | T13: 0 | U13: 0 | V13: 137 | W13: 3481 | X13: Mr. MAHESH KUMAR | Y13: Approved | Z13: Teamlease Services Ltd | AA13: TLEdtech | AB13: Official | AC13: 22-08-2026 12:00:00 AM | AD13: Official | AE13: 3309 | AF13: Booked | AI13: T004S | AJ13: 27AAPCS2871R1ZB | AK13: Y | AL13: - | AM13: L7 | AN13: Mr. MAHESH KUMAR | AP13: MMT | AQ13: University Bd | AS13: 0 | AZ13: Bengaluru | BA13: NH15064511149934 | BC13: TeamLease Edtech Limited | BD13: 27AAPCS2871R1ZB | BE13: M | BF13: Sterling group of hotels | BH13: D | BI13: Single | BJ13: 22-08-2026 | BK13: 18:41 | BP13: T15604 | BR13: L8
A14: HW26/367572 | B14: 22-08-2026 12:00:00 AM | C14: 44873126 | D14: 70065034 | E14: 500118050635 | F14: T15226 | G14: Mr. Nakul Joshi | H14: Senior Manager | J14: 61-MUM-USE | K14: 26-08-2026 02:00:00 PM | L14: 27-08-2026 12:00:00 PM | M14: 1 | N14: 1 | O14: Aurangabad | P14: Maharashtra | Q14: The Fern Residency, Aurangabad (Chhatrapati Sambhaji Nagar) | R14: 4742.24 | S14: 237.11 | T14: 0 | U14: 0 | V14: 189 | W14: 4790 | X14: Ms. Deepti DEEPTI | Y14: Approved | Z14: Teamlease Services Ltd | AA14: TLEdtech | AB14: Official | AC14: 22-08-2026 12:00:00 AM | AD14: Official | AE14: 4790 | AF14: Booked | AI14: T004S | AJ14: 27AAPCS2871R1ZB | AK14: Y | AL14: - | AM14: L7 | AN14: Ms. Deepti DEEPTI | AP14: MMT | AQ14: University Bd | AS14: 0 | AZ14: Bengaluru | BA14: NH10192511211644 | BC14: TeamLease Edtech Limited | BD14: 27AAPCS2871R1ZB | BE14: M | BF14: Concept Hospitality | BH14: D | BI14: Single | BJ14: 22-08-2026 | BK14: 23:05 | BP14: T17404 | BR14: L8
A15: HW26/368045 | B15: 23-08-2026 12:00:00 AM | C15: 44881914 | D15: 70078790 | E15: 500118054130 | F15: T17404 | G15: Ms. Deepti Deepti | H15: Assistant General Manager | J15: 61-MUM-USE | K15: 26-08-2026 03:00:00 PM | L15: 27-08-2026 12:00:00 PM | M15: 1 | N15: 1 | O15: Jaipur | P15: Rajasthan | Q15: Radisson Blu Hotel Jaipur | R15: 4701.45 | S15: 213.7 | T15: 0 | U15: 0 | V15: 170 | W15: 4745 | X15: Mr. Shantanu Rooj | Y15: Approved | Z15: Teamlease Services Ltd | AA15: TLEdtech | AB15: Official | AC15: 23-08-2026 12:00:00 AM | AD15: Official | AE15: 4531 | AF15: Booked | AI15: T004S | AJ15: 27AAPCS2871R1ZB | AK15: Y | AL15: - | AM15: L8 | AN15: Mr. Shantanu Rooj | AP15: MMT | AQ15: University Bd | AS15: 0 | AZ15: Bengaluru | BA15: NH12160511301610 | BC15: TeamLease Edtech Limited | BD15: 27AAPCS2871R1ZB | BE15: F | BF15: Radisson | BH15: D | BI15: Single | BJ15: 23-08-2026 | BK15: 13:07 | BP15: SG0014 | BR15: LST
A16: HW26/372434 | B16: 25-08-2026 12:00:00 AM | C16: 44918678 | D16: 70140834 | E16: 500118081806 | F16: T17743 | G16: Mr. Khunjamayum David Singh | H16: Regional Head | J16: 61-MUM-USE | K16: 28-08-2026 02:00:00 PM | L16: 29-08-2026 12:00:00 PM | M16: 1 | N16: 1 | O16: Mysore | P16: Karnataka | Q16: The Quorum | R16: 3616.92 | S16: 180.85 | T16: 0 | U16: 0 | V16: 144 | W16: 3654 | X16: Mr. Shantanu Rooj | Y16: Approved | Z16: Teamlease Services Ltd | AA16: TLEdtech | AB16: Official | AC16: 25-08-2026 12:00:00 AM | AD16: Official | AE16: 3473 | AF16: Booked | AI16: T004S | AJ16: 29AAPCS2871R1Z7 | AK16: Y | AL16: - | AM16: L8 | AN16: Mr. Shantanu Rooj | AP16: MMT | AQ16: University Bd | AS16: 0 | AZ16: Bengaluru | BA16: NH15022511736434 | BC16: TeamLease Edtech Limited | BD16: 29AAPCS2871R1Z7 | BE16: M | BH16: D | BI16: Single | BJ16: 25-08-2026 | BK16: 11:04 | BP16: SG0014 | BR16: LST
A17: HW26/372693 | B17: 25-08-2026 12:00:00 AM | C17: 44924021 | D17: 70148750 | E17: 500118083886 | F17: T17843 | G17: Mr. Md Nabeel Anwar | H17: Counselor | J17: 62-MUM-USP | K17: 26-08-2026 02:00:00 PM | L17: 27-08-2026 12:00:00 PM | M17: 1 | N17: 1 | O17: Jamshedpur | P17: Jharkhand | Q17: Ginger Jamshedpur | R17: 2307.65 | S17: 115.38 | T17: 0 | U17: 0 | V17: 92 | W17: 2331 | X17: MR. VIVEK KUMAR | Y17: Approved | Z17: Teamlease Services Ltd | AA17: TLEdtech | AB17: Official | AC17: 25-08-2026 12:00:00 AM | AD17: Official | AE17: 2216 | AF17: Booked | AI17: T004S | AJ17: 27AAPCS2871R1ZB | AK17: Y | AL17: - | AM17: L2 | AN17: MR. VIVEK KUMAR | AP17: MMT | AQ17: University B2C | AS17: 0 | AZ17: Bengaluru | BA17: NH18165511758134 | BC17: TeamLease Edtech Limited | BD17: 27AAPCS2871R1ZB | BE17: M | BF17: IHCL - Ginger Hotels | BH17: D | BI17: Single | BJ17: 25-08-2026 | BK17: 12:36 | BP17: T16451 | BR17: L6
A18: HW26/374009 | B18: 25-08-2026 12:00:00 AM | C18: 44932177 | D18: 70160240 | E18: 500118091652 | F18: T12988 | G18: Mr. Vikash Sharma | H18: Senior Manager | I18: 3701618 | J18: 69-MUM-PBD | K18: 26-08-2026 12:00:00 PM | L18: 27-08-2026 11:00:00 AM | M18: 1 | N18: 1 | O18: Sambalpur | P18: Odisha | Q18: Regenta Inn Sambalpur | R18: 4189.5 | S18: 209.48 | T18: 0 | U18: 0 | V18: 167 | W18: 4232 | X18: MS. Geetika Kohli | Y18: Approved | Z18: Teamlease Services Ltd | AA18: TLEdtech | AB18: Official | AC18: 25-08-2026 12:00:00 AM | AD18: Official | AE18: 4022 | AF18: Booked | AI18: T004S | AJ18: 27AAPCS2871R1ZB | AK18: Y | AL18: - | AM18: L7 | AN18: MS. Geetika Kohli | AP18: MMT | AQ18: Premier BD | AS18: 0 | AZ18: Bengaluru | BA18: NH18165511845784 | BC18: TeamLease Edtech Limited | BD18: 27AAPCS2871R1ZB | BE18: M | BF18: Royal Orchid Group | BH18: D | BI18: Single | BJ18: 25-08-2026 | BK18: 18:32 | BP18: SG0400 | BR18: L10
A19: HW26/375275 | B19: 26-08-2026 12:00:00 AM | C19: 44946973 | D19: 70184610 | E19: 500118099613 | F19: SG0444 | G19: Mrs. Srimathi R | H19: Head - University Operations | I19: 3701618 | J19: 61-MUM-ASO | K19: 01-09-2026 03:00:00 PM | L19: 02-09-2026 12:00:00 PM | M19: 1 | N19: 1 | O19: Agra | P19: Uttar Pradesh | Q19: Radisson Hotel Agra | R19: 3990.55 | S19: 199.53 | T19: 0 | U19: 0 | V19: 159 | W19: 4031 | X19: Mr. JAIDEEP KEWALRAMANI | Y19: Approved | Z19: Teamlease Services Ltd | AA19: TLEdtech | AB19: Official | AC19: 26-08-2026 12:00:00 AM | AD19: Official | AE19: 3832 | AF19: Booked | AI19: T004S | AJ19: 27AAPCS2871R1ZB | AK19: Y | AL19: - | AM19: L10 | AN19: Mr. JAIDEEP KEWALRAMANI | AP19: MMT | AQ19: Operations | AS19: 0 | AZ19: Bengaluru | BA19: NH11005511986212 | BC19: TeamLease Edtech Limited | BD19: 27AAPCS2871R1ZB | BE19: F | BF19: Radisson | BH19: D | BI19: Single | BJ19: 26-08-2026 | BK19: 11:22 | BP19: T12553 | BR19: LST
A20: HW26/377302 | B20: 27-08-2026 12:00:00 AM | C20: 44955250 | D20: 70195947 | E20: 500118113144 | F20: SG0444 | G20: Mrs. Srimathi R | H20: Head - University Operations | I20: 3701618 | J20: 61-MUM-ASO | K20: 31-08-2026 02:00:00 PM | L20: 01-09-2026 12:00:00 PM | M20: 1 | N20: 1 | O20: Jhansi | P20: Uttar Pradesh | Q20: Nataraj Sarovar Portico | R20: 4221 | S20: 211.05 | T20: 0 | U20: 0 | V20: 168 | W20: 4264 | X20: Mr. JAIDEEP KEWALRAMANI | Y20: Approved | Z20: Teamlease Services Ltd | AA20: TLEdtech | AB20: Official | AC20: 26-08-2026 12:00:00 AM | AD20: Official | AE20: 4053 | AF20: Booked | AI20: T004S | AJ20: 27AAPCS2871R1ZB | AK20: Y | AL20: - | AM20: L10 | AN20: Mr. JAIDEEP KEWALRAMANI | AP20: MMT | AQ20: Operations | AS20: 0 | AZ20: Bengaluru | BA20: NH14052512183086 | BC20: TeamLease Edtech Limited | BD20: 27AAPCS2871R1ZB | BE20: F | BF20: Sarovar Group of Hotels | BH20: D | BI20: Single | BJ20: 27-08-2026 | BK20: 03:24 | BP20: T12553 | BR20: LST
A21: HW26/377692 | B21: 27-08-2026 12:00:00 AM | C21: 44971476 | D21: 70220602 | E21: 500118116825 | F21: T15255 | G21: Mr. Shubham Dubey | H21: Senior Manager | J21: 61-MUM-USE | K21: 01-09-2026 02:00:00 PM | L21: 02-09-2026 12:00:00 PM | M21: 1 | N21: 1 | O21: Agra | P21: Uttar Pradesh | Q21: Lemon Tree Hotel Agra | R21: 4888.13 | S21: 244.4 | T21: 0 | U21: 0 | V21: 199 | W21: 4934 | X21: Mr. MAHESH KUMAR | Y21: Approved | Z21: Teamlease Services Ltd | AA21: TLEdtech | AB21: Official | AC21: 27-08-2026 12:00:00 AM | AD21: Official | AE21: 4689 | AF21: Booked | AI21: T004S | AJ21: 27AAPCS2871R1ZB | AK21: Y | AL21: - | AM21: L7 | AN21: Mr. MAHESH KUMAR | AP21: MMT | AQ21: University Bd | AS21: 0 | AZ21: Bengaluru | BA21: NH10087512232078 | BC21: TeamLease Edtech Limited | BD21: 27AAPCS2871R1ZB | BE21: M | BF21: Lemon Tree Hotels | BH21: D | BI21: Single | BJ21: 27-08-2026 | BK21: 12:01 | BP21: T15604 | BR21: L8
A22: HW26/378220 | B22: 27-08-2026 12:00:00 AM | C22: 44972491 | D22: 70231766 | E22: 500118121153 | F22: T16960 | G22: Mr. Bipin Kumar Tiwari | H22: Assistant General Manager | J22: 72-MUM-HBC | K22: 01-09-2026 12:00:00 PM | L22: 02-09-2026 10:00:00 AM | M22: 1 | N22: 1 | O22: Jhansi | P22: Uttar Pradesh | Q22: Hotel K3 Club Residency | R22: 3420 | S22: 171 | T22: 0 | U22: 0 | V22: 136 | W22: 3455 | X22: MR. Chetan Dixit | Y22: Approved | Z22: Teamlease Services Ltd | AA22: TLEdtech | AB22: Official | AC22: 27-08-2026 12:00:00 AM | AD22: Scheduled Visit | AE22: 3284 | AF22: Booked | AI22: T004S | AJ22: 27AAPCS2871R1ZB | AK22: Y | AL22: - | AM22: L8 | AN22: MR. Chetan Dixit | AP22: MMT | AQ22: University B2C | AS22: 0 | AZ22: Bengaluru | BA22: NH10149512279682 | BC22: TeamLease Edtech Limited | BD22: 27AAPCS2871R1ZB | BE22: M | BH22: D | BI22: Single | BJ22: 27-08-2026 | BK22: 15:29 | BP22: SG0506 | BR22: L9
A23: HW26/378696 | B23: 27-08-2026 12:00:00 AM | C23: 44979006 | D23: 70232365 | E23: 500118124582 | F23: T13872 | G23: Mr. Shashwat Sagar Dubey | H23: Senior Manager | I23: 3701618 | J23: 69-MUM-PBD | K23: 01-09-2026 02:00:00 PM | L23: 03-09-2026 12:00:00 PM | M23: 1 | N23: 2 | O23: Jodhpur | P23: Rajasthan | Q23: Park Plaza Jodhpur | R23: 9945 | S23: 497.26 | T23: 0 | U23: 0 | V23: 397 | W23: 10045 | X23: MS. Geetika Kohli | Y23: Approved | Z23: Teamlease Services Ltd | AA23: TLEdtech | AB23: Official | AC23: 27-08-2026 12:00:00 AM | AD23: Official | AE23: 10045 | AF23: Booked | AI23: T004S | AJ23: 27AAPCS2871R1ZB | AK23: Y | AL23: - | AM23: L7 | AN23: MS. Geetika Kohli | AP23: MMT | AQ23: Premier BD | AS23: 0 | AZ23: Bengaluru | BA23: NH11134512316222 | BC23: TeamLease Edtech Limited | BD23: 27AAPCS2871R1ZB | BE23: M | BF23: Radisson | BH23: D | BI23: Single | BJ23: 27-08-2026 | BK23: 18:06 | BP23: SG0400 | BR23: L10
A24: HW26/378873 | B24: 27-08-2026 12:00:00 AM | C24: 44986095 | D24: 70242048 | E24: 500118126012 | F24: T12988 | G24: Mr. Vikash Sharma | H24: Senior Manager | I24: 3701618 | J24: 69-MUM-PBD | K24: 27-08-2026 12:00:00 PM | L24: 28-08-2026 11:00:00 AM | M24: 1 | N24: 1 | O24: Sambalpur | P24: Odisha | Q24: Regenta Inn Sambalpur | R24: 4189.5 | S24: 209.48 | T24: 0 | U24: 0 | V24: 167 | W24: 4232 | X24: MS. Geetika Kohli | Y24: Approved | Z24: Teamlease Services Ltd | AA24: TLEdtech | AB24: Official | AC24: 27-08-2026 12:00:00 AM | AD24: Official | AE24: 4022 | AF24: Booked | AI24: T004S | AJ24: 27AAPCS2871R1ZB | AK24: Y | AL24: - | AM24: L7 | AN24: MS. Geetika Kohli | AP24: MMT | AQ24: Premier BD | AS24: 0 | AZ24: Bengaluru | BA24: NH13111512332258 | BC24: TeamLease Edtech Limited | BD24: 27AAPCS2871R1ZB | BE24: M | BF24: Royal Orchid Group | BH24: D | BI24: Single | BJ24: 27-08-2026 | BK24: 19:18 | BP24: SG0400 | BR24: L10
A25: HW26/381092 | B25: 29-08-2026 12:00:00 AM | C25: 44990831 | D25: 70249375 | E25: 500118143952 | F25: SG0320 | G25: Mr. Uditendu Bose | H25: Vice President - Consumer Sales | I25: 3701618 | J25: 62-MUM-SSS | K25: 31-08-2026 02:00:00 PM | L25: 04-09-2026 12:00:00 PM | M25: 1 | N25: 4 | O25: Noida | P25: Uttar Pradesh | Q25: Ira by Orchid, Noida | R25: 23501.1 | S25: 1175.05 | T25: 0 | U25: 0 | V25: 940 | W25: 23736 | X25: Mr. Shantanu Rooj | Y25: Approved | Z25: Teamlease Services Ltd | AA25: TLEdtech | AB25: Official | AC25: 28-08-2026 12:00:00 AM | AD25: Official | AE25: 22561 | AF25: Booked | AI25: T004S | AJ25: 27AAPCS2871R1ZB | AK25: Y | AL25: - | AM25: L10 | AN25: Mr. Shantanu Rooj | AP25: MMT | AQ25: University B2C | AS25: 0 | AZ25: Bengaluru | BA25: NH10107512653102 | BC25: TeamLease Edtech Limited | BD25: 27AAPCS2871R1ZB | BE25: M | BF25: Kamat Group Of Hotels | BH25: D | BI25: Single | BJ25: 29-08-2026 | BK25: 10:12 | BP25: SG0014 | BR25: LST
A26: HW26/382937 | B26: 30-08-2026 12:00:00 AM | C26: 44999935 | D26: 70263460 | E26: 500118158131 | F26: T17566 | G26: Mr. Siddhartha Bose | H26: Assistant General Manager | J26: 62-MUM-SSS | K26: 01-09-2026 02:00:00 PM | L26: 04-09-2026 12:00:00 PM | M26: 1 | N26: 3 | O26: Noida | P26: Uttar Pradesh | Q26: Ira by Orchid, Noida | R26: 14577.75 | S26: 728.88 | T26: 0 | U26: 0 | V26: 583 | W26: 14724 | X26: MR. Chetan Dixit | Y26: Approved | Z26: Teamlease Services Ltd | AA26: TLEdtech | AB26: Official | AC26: 28-08-2026 12:00:00 AM | AD26: Official | AE26: 13995 | AF26: Booked | AI26: T004S | AJ26: 27AAPCS2871R1ZB | AK26: Y | AL26: - | AM26: L8 | AN26: MR. Chetan Dixit | AP26: MMT | AQ26: University B2C | AS26: 0 | AZ26: Bengaluru | BA26: NH12023512923424 | BC26: TeamLease Edtech Limited | BD26: 27AAPCS2871R1ZB | BE26: M | BF26: Kamat Group Of Hotels | BH26: D | BI26: Single | BJ26: 30-08-2026 | BK26: 13:42 | BP26: SG0506 | BR26: L9
A27: HW26/385388 | B27: 31-08-2026 12:00:00 AM | C27: 45014017 | D27: 70284472 | E27: 500118176053 | F27: T15226 | G27: Mr. Nakul Joshi | H27: Senior Manager | J27: 61-MUM-USE | K27: 02-09-2026 02:00:00 PM | L27: 05-09-2026 12:00:00 PM | M27: 1 | N27: 3 | O27: Bhopal | P27: Madhya Pradesh | Q27: Regenta Place Bhopal by Royal Orchid Hotels Limited | R27: 12653.15 | S27: 632.65 | T27: 0 | U27: 0 | V27: 506 | W27: 12780 | X27: Ms. Deepti DEEPTI | Y27: Approved | Z27: Teamlease Services Ltd | AA27: TLEdtech | AB27: Official | AC27: 29-08-2026 01:23:48 PM | AD27: Official | AE27: 9850 | AF27: Booked | AI27: T004S | AJ27: 27AAPCS2871R1ZB | AK27: Y | AL27: - | AM27: L7 | AN27: Ms. Deepti DEEPTI | AP27: MMT | AQ27: University Bd | AS27: 0 | AZ27: Bengaluru | BA27: NH12006513180642 | BC27: TeamLease Edtech Limited | BD27: 27AAPCS2871R1ZB | BE27: M | BF27: Royal Orchid Group | BH27: D | BI27: Single | BJ27: 31-08-2026 | BK27: 15:58 | BP27: T17404 | BR27: L8
A28: HW26/385513 | B28: 31-08-2026 12:00:00 AM | C28: 45057696 | D28: 70349989 | E28: 500118176989 | F28: T17404 | G28: Ms. Deepti Deepti | H28: Assistant General Manager | J28: 61-MUM-USE | K28: 02-09-2026 12:00:00 PM | L28: 04-09-2026 10:00:00 AM | M28: 1 | N28: 2 | O28: Bhopal | P28: Madhya Pradesh | Q28: Hotel Insignia | R28: 7839.22 | S28: 391.96 | T28: 0 | U28: 0 | V28: 352 | W28: 7879 | X28: Mr. Shantanu Rooj | Y28: Approved | Z28: Teamlease Services Ltd | AA28: TLEdtech | AB28: Official | AC28: 31-08-2026 12:00:00 AM | AD28: Official | AE28: 7487 | AF28: Booked | AG28: Due to change in plan | AH28: 31-08-2026 05:35:03 PM | AI28: T004S | AJ28: 27AAPCS2871R1ZB | AK28: Y | AL28: - | AM28: L8 | AN28: Mr. Shantanu Rooj | AP28: MMT | AQ28: University Bd | AS28: 0 | AZ28: Bengaluru | BA28: NH19083513188468 | BC28: TeamLease Edtech Limited | BD28: 27AAPCS2871R1ZB | BE28: F | BH28: D | BI28: Single | BJ28: 31-08-2026 | BK28: 17:00 | BP28: SG0014 | BR28: LST
A29: Total | W29: =SUM(W4:W28) -> 196377
A39: HW26/362924 | B39: 20-08-2026 12:00:00 AM | C39: 44833854 | D39: 69999151 | E39: 500118021116 | F39: T11310 | G39: Mr. Dinesh Kumar | H39: Head - Operations (Enterprise Services) | I39: 3701618 | J39: 63-DEL-DAS | K39: 23-08-2026 02:00:00 PM | L39: 27-08-2026 12:00:00 PM | M39: 1 | N39: 4 | O39: Aurangabad | P39: Maharashtra | Q39: Spree Hotel Aurangabad | R39: 16190.09 | S39: 809.5 | T39: 0 | U39: 0 | V39: 647 | W39: 16353 | X39: Mr. Nipun SHARMA | Y39: Approved | Z39: Teamlease Services Ltd | AA39: TL Digital | AB39: Official | AC39: 20-08-2026 12:00:00 AM | AD39: Official | AE39: 16353 | AF39: Booked

Sheet Sheet1
A1: Name of Passenger | B1: Emp ID | C1: Invoice Number | D1: Invoice Date | E1: GL Code | F1: Narration | G1: Vendor ID | H1: Invoice/ Credit Note | I1: Sum of Amounts | K1: GL code | L1: GL code-gl
A2: BOSE/UDITENDU MR | B2: SG0320 | C2: DD26/6247 | D2: 46253 | E2: 80003-62-MUM-SSS | F2: Misc BOSE/UDITENDU MR-SG0320-AUG-26-06-05-2026-Mumbai-Kolkata | G2: V03136 | H2: Invoice | I2: 975 | K2: 80003-62-MUM-SSS | L2: 62-MUM-SSS
A3: BOSE/UDITENDU MR | B3: SG0320 | C3: DD26/6814 | D3: 46264 | E3: 80003-62-MUM-SSS | F3: Misc BOSE/UDITENDU MR-SG0320-AUG-26-06-05-2026-Kolkata-New Delhi | G3: V03136 | H3: Invoice | I3: 225 | K3: 80003-62-MUM-SSS | L3: 62-MUM-SSS
A4: MR. AAYUSH LAL | B4: T16161 | C4: DA26/178427 | D4: 46252 | E4: 80003-69-MUM-PBP | F4: Airticket MR. AAYUSH LAL-T16161-AUG-26-06-05-2026-Chennai-New Delhi | G4: V03136 | H4: Invoice | I4: 14752 | K4: 80003-69-MUM-PBP | L4: 69-MUM-PBP
A5: MR. AAYUSH LAL | B5: T16161 | C5: DW26/791733 | D5: 46252 | E5: 80003-69-MUM-PBP | F5: Airticket MR. AAYUSH LAL-T16161-AUG-26-06-05-2026-New Delhi-Gaya | G5: V03136 | H5: Invoice | I5: 6786 | K5: 80003-69-MUM-PBP | L5: 69-MUM-PBP
A6: MR. AAYUSH LAL | B6: T16161 | C6: DW26/791750 | D6: 46252 | E6: 80003-69-MUM-PBP | F6: Airticket MR. AAYUSH LAL-T16161-AUG-26-06-05-2026-Ranchi-New Delhi | G6: V03136 | H6: Invoice | I6: 7743 | K6: 80003-69-MUM-PBP | L6: 69-MUM-PBP
A7: MR. AAYUSH LAL | B7: T16161 | C7: DW26/796548 | D7: 46252 | E7: 80003-69-MUM-PBP | F7: Airticket MR. AAYUSH LAL-T16161-AUG-26-06-05-2026-New Delhi-Chennai | G7: V03136 | H7: Invoice | I7: 8526 | K7: 80003-69-MUM-PBP | L7: 69-MUM-PBP
A8: MR. AAYUSH LAL | B8: T16161 | C8: DW26/798332 | D8: 46253 | E8: 80003-69-MUM-PBP | F8: Airticket MR. AAYUSH LAL-T16161-AUG-26-06-05-2026-New Delhi-Chennai | G8: V03136 | H8: Invoice | I8: 10099 | K8: 80003-69-MUM-PBP | L8: 69-MUM-PBP
A9: MR. AAYUSH LAL | B9: T16161 | C9: HW26/352639 | D9: 46252 | E9: 80003-69-MUM-PBP | F9: Debit Mr. Aayush Lal-T16161-AUG-26-06-05-2026-Andhra Pradesh | G9: V03136 | H9: Invoice | I9: 7182 | K9: 80003-69-MUM-PBP | L9: 69-MUM-PBP
A10: MR. ABDUL FAROOQI | B10: CQ00873076 | C10: DW26/781796 | D10: 46250 | E10: 80003-62-MUM-SSS | F10: Airticket MR. ABDUL FAROOQI-CQ00873076-AUG-26-06-05-2026-New Delhi-Mumbai/Mumbai-Kannur | G10: V03136 | H10: Invoice | I10: 10672 | K10: 80003-62-MUM-SSS | L10: 62-MUM-SSS
A11: MR. ABDUL FAROOQI | B11: CQ00873076 | C11: DW26/782230 | D11: 46250 | E11: 80003-62-MUM-SSS | F11: Airticket MR. ABDUL FAROOQI-CQ00873076-AUG-26-06-05-2026-Kannur-New Delhi | G11: V03136 | H11: Invoice | I11: 19450 | K11: 80003-62-MUM-SSS | L11: 62-MUM-SSS
A12: MR. ABDUL MAJID FAROOQI | B12: CQ00873076 | C12: DW26/781403 | D12: 46250 | E12: 80003-62-MUM-SSS | F12: Airticket MR. ABDUL MAJID FAROOQI-CQ00873076-AUG-26-06-05-2026-Kannur-New Delhi | G12: V03136 | H12: Invoice | I12: 19450 | K12: 80003-62-MUM-SSS | L12: 62-MUM-SSS
A13: MR. ABDUL MAJID FAROOQI | B13: CQ00873076 | C13: DW26/781991 | D13: 46250 | E13: 80003-62-MUM-SSS | F13: Airticket MR. ABDUL MAJID FAROOQI-CQ00873076-AUG-26-06-05-2026-New Delhi-Mumbai/Mumbai-Kannur | G13: V03136 | H13: Invoice | I13: 11540 | K13: 80003-62-MUM-SSS | L13: 62-MUM-SSS
... A93: MS. SHRUTIKA SHARMA | B93: T16151 | C93: HW26/362339 | D93: 46254 | E93: 80003-69-MUM-PBD | F93: Debit Ms. Shrutika Sharma-T16151-AUG-26-06-05-2026-Karnataka | G93: V03136 | H93: Invoice | I93: 14669 | K93: 80003-69-MUM-PBD | L93: 69-MUM-PBD
I94: =SUM(I2:I93) -> 692470
A101: MR. AAYUSH LAL | B101: T16161 | C101: DZ26/140066 | D101: 46252 | E101: 80003-69-MUM-PBP | F101: Credit MR. AAYUSH LAL-T16161-AUG-26-06-05-2026-New Delhi-Chennai | G101: V03136 | H101: Credit Note | I101: 8328 | J101: - | K101: =CONCATENATE(J101,I101) -> -8328 | L101: 80003-69-MUM-PBP | M101: 69-MUM-PBP
A102: MR. ABDUL FAROOQI | B102: CQ00873076 | C102: DZ26/137376 | D102: 46250 | E102: 80003-62-MUM-SSS | F102: Credit MR. ABDUL FAROOQI-CQ00873076-AUG-26-06-05-2026-New Delhi-Mumbai/Mumbai-Kannur | G102: V03136 | H102: Credit Note | I102: 10473 | J102: - | K102: =CONCATENATE(J102,I102) -> -10473 | L102: 80003-62-MUM-SSS | M102: 62-MUM-SSS
A103: MR. ABDUL FAROOQI | B103: CQ00873076 | C103: DZ26/137469 | D103: 46250 | E103: 80003-62-MUM-SSS | F103: Credit MR. ABDUL FAROOQI-CQ00873076-AUG-26-06-05-2026-Kannur-New Delhi | G103: V03136 | H103: Credit Note | I103: 19251 | J103: - | K103: =CONCATENATE(J103,I103) -> -19251 | L103: 80003-62-MUM-SSS | M103: 62-MUM-SSS
A104: MR. NAKUL JOSHI | B104: T15226 | C104: LZ26/17613 | D104: 46252 | E104: 80003-61-MUM-USE | F104: Credit MR. NAKUL JOSHI-T15226-AUG-26-06-05-2026-MUMBAI CENTRAL - MMCT-VADODARA JN - BRC | G104: V03136 | H104: Credit Note | I104: 995 | J104: - | K104: =CONCATENATE(J104,I104) -> -995 | L104: 80003-61-MUM-USE | M104: 61-MUM-USE
A105: MR. PRATHAMESH JADHAV | B105: T16692 | C105: DZ26/143941 | D105: 46256 | E105: 80003-69-MUM-PBO | F105: Credit MR. PRATHAMESH JADHAV-T16692-AUG-26-06-05-2026-Chennai-Mumbai | G105: V03136 | H105: Credit Note | I105: 8796 | J105: - | K105: =CONCATENATE(J105,I105) -> -8796 | L105: 80003-69-MUM-PBO | M105: 69-MUM-PBO
A106: MR. PRATHAMESH JADHAV | B106: T16692 | C106: DZ26/144146 | D106: 46256 | E106: 80003-69-MUM-PBO | F106: Credit MR. PRATHAMESH JADHAV-T16692-AUG-26-06-05-2026-Mumbai-Chennai | G106: V03136 | H106: Credit Note | I106: 8910 | J106: - | K106: =CONCATENATE(J106,I106) -> -8910 | L106: 80003-69-MUM-PBO | M106: 69-MUM-PBO
A107: MR. PREETISH GUPTA | B107: SG0516 | C107: DZ26/137382 | D107: 46250 | E107: 80003-62-MUM-SSS | F107: Credit MR. PREETISH GUPTA-SG0516-AUG-26-06-05-2026-Mumbai-Ahmedabad | G107: V03136 | H107: Credit Note | I107: 17753 | J107: - | K107: =CONCATENATE(J107,I107) -> -17753 | L107: 80003-62-MUM-SSS | M107: 62-MUM-SSS
A108: MR. SHANTANU ROOJ | B108: SG0014 | C108: DZ26/140351 | D108: 46253 | E108: 80003-68-MUM-LED | F108: Credit MR. SHANTANU ROOJ-SG0014-AUG-26-06-05-2026-Kolkata-Mumbai | G108: V03136 | H108: Credit Note | I108: 9084 | J108: - | K108: =CONCATENATE(J108,I108) -> -9084 | L108: 80003-68-MUM-LED | M108: 68-MUM-LED
A109: MR. SHANTANU ROOJ | B109: SG0014 | C109: DZ26/140545 | D109: 46253 | E109: 80003-68-MUM-LED | F109: Credit MR. SHANTANU ROOJ-SG0014-AUG-26-06-05-2026-Mumbai-Kolkata | G109: V03136 | H109: Credit Note | I109: 8557 | J109: - | K109: =CONCATENATE(J109,I109) -> -8557 | L109: 80003-68-MUM-LED | M109: 68-MUM-LED
A110: MR. SHANTANU ROOJ | B110: SG0014 | C110: DZ26/141702 | D110: 46254 | E110: 80003-68-MUM-LED | F110: Credit MR. SHANTANU ROOJ-SG0014-AUG-26-06-05-2026-New Delhi-Mumbai | G110: V03136 | H110: Credit Note | I110: 8224 | J110: - | K110: =CONCATENATE(J110,I110) -> -8224 | L110: 80003-68-MUM-LED | M110: 68-MUM-LED
A111: MR. UDITENDU BOSE | B111: SG0320 | C111: DE26/457846 | D111: 46253 | E111: 80003-62-MUM-SSS | F111: Credit MR. UDITENDU BOSE-SG0320-AUG-26-06-05-2026-Kolkata-Mumbai | G111: V03136 | H111: Credit Note | I111: 8950 | J111: - | K111: =CONCATENATE(J111,I111) -> -8950 | L111: 80003-62-MUM-SSS | M111: 62-MUM-SSS
A112: MRS. SRIMATHI R | B112: SG0444 | C112: DZ26/147806 | D112: 46260 | E112: 80003-61-MUM-ASO | F112: Credit MRS. SRIMATHI R-SG0444-AUG-26-06-05-2026-Gwalior-Mumbai | G112: V03136 | H112: Credit Note | I112: 8056 | J112: - | K112: =CONCATENATE(J112,I112) -> -8056 | L112: 80003-61-MUM-ASO | M112: 61-MUM-ASO
... A114: MS. DEEPTI DEEPTI | B114: T17404 | C114: HR26/19678 | D114: 46265 | E114: 80003-61-MUM-USE | F114: Credit Ms. Deepti Deepti-T17404-AUG-26-06-05-2026-Madhya Pradesh | G114: V03136 | H114: Credit Note | I114: 7879 | J114: - | K114: =CONCATENATE(J114,I114) -> -7879 | L114: 80003-61-MUM-USE | M114: 61-MUM-USE
I115: =SUM(I101:I114) -> 133337

Sheet Working
A1: Invoice/ Credit Note | B1: Travel Month | C1: Name of Passenger | D1: Location | E1: Cost Code | F1: Emp ID | G1: Nature of Transaction | H1: Nature of Ticket | I1: Amounts | J1: Invoice Number | K1: Invoice Date | L1: gl | M1: GL Code | N1: Narration | O1: Vendor ID | P1: Submission Date | Q1: GL Code | R1: BU | S1: Service Month
A2: Invoice | B2: AUG-26 | C2: MR. M A SIKANDAR | D2: Kannur-New Delhi | E2: 62-MUM-SSS | F2: CQ00873075 | G2: Airways Ticket | H2: Airticket | I2: 19450 | J2: DW26/780819 | K2: 16-AUG-2026 | L2: 80003 | M2: =CONCATENATE(L2,"-",E2) -> 80003-62-MUM-SSS | N2: =CONCATENATE(H2," ",C2,"-",F2,"-",B2,"-",P2,"-",D2) -> Airticket MR. M A SIKANDAR-CQ00873075-AUG-26-06-05-2026-Kannur-New Delhi | O2: V03136 | P2: 06-05-2026 | Q2: =E2 -> 62-MUM-SSS | R2: =RIGHT(Q2,3) -> SSS | S2: AUG-26
A3: Invoice | B3: AUG-26 | C3: MR. ABDUL FAROOQI | D3: Kannur-New Delhi | E3: 62-MUM-SSS | F3: CQ00873076 | G3: Airways Ticket | H3: Airticket | I3: 19450 | J3: DW26/782230 | K3: 16-AUG-2026 | L3: 80003 | M3: =CONCATENATE(L3,"-",E3) -> 80003-62-MUM-SSS | N3: =CONCATENATE(H3," ",C3,"-",F3,"-",B3,"-",P3,"-",D3) -> Airticket MR. ABDUL FAROOQI-CQ00873076-AUG-26-06-05-2026-Kannur-New Delhi | O3: V03136 | P3: 06-05-2026 | Q3: =E3 -> 62-MUM-SSS | R3: =RIGHT(Q3,3) -> SSS | S3: AUG-26
A4: Invoice | B4: AUG-26 | C4: MR. ABDUL FAROOQI | D4: New Delhi-Mumbai/Mumbai-Kannur | E4: 62-MUM-SSS | F4: CQ00873076 | G4: Airways Ticket | H4: Airticket | I4: 10672 | J4: DW26/781796 | K4: 16-AUG-2026 | L4: 80003 | M4: =CONCATENATE(L4,"-",E4) -> 80003-62-MUM-SSS | N4: =CONCATENATE(H4," ",C4,"-",F4,"-",B4,"-",P4,"-",D4) -> Airticket MR. ABDUL FAROOQI-CQ00873076-AUG-26-06-05-2026-New Delhi-Mumbai/Mumbai-Kannur | O4: V03136 | P4: 06-05-2026 | Q4: =E4 -> 62-MUM-SSS | R4: =RIGHT(Q4,3) -> SSS | S4: AUG-26
A5: Invoice | B5: AUG-26 | C5: MR. M A SIKANDAR | D5: New Delhi-Mumbai/Mumbai-Kannur | E5: 62-MUM-SSS | F5: CQ00873075 | G5: Airways Ticket | H5: Airticket | I5: 10672 | J5: DW26/780892 | K5: 16-AUG-2026 | L5: 80003 | M5: =CONCATENATE(L5,"-",E5) -> 80003-62-MUM-SSS | N5: =CONCATENATE(H5," ",C5,"-",F5,"-",B5,"-",P5,"-",D5) -> Airticket MR. M A SIKANDAR-CQ00873075-AUG-26-06-05-2026-New Delhi-Mumbai/Mumbai-Kannur | O5: V03136 | P5: 06-05-2026 | Q5: =E5 -> 62-MUM-SSS | R5: =RIGHT(Q5,3) -> SSS | S5: AUG-26
A6: Invoice | B6: AUG-26 | C6: MR. CHETAN DIXIT | D6: New Delhi-Mumbai/Mumbai-Kannur | E6: 62-MUM-SSS | F6: SG0506 | G6: Airways Ticket | H6: Airticket | I6: 11853 | J6: DW26/782006 | K6: 16-AUG-2026 | L6: 80003 | M6: =CONCATENATE(L6,"-",E6) -> 80003-62-MUM-SSS | N6: =CONCATENATE(H6," ",C6,"-",F6,"-",B6,"-",P6,"-",D6) -> Airticket MR. CHETAN DIXIT-SG0506-AUG-26-06-05-2026-New Delhi-Mumbai/Mumbai-Kannur | O6: V03136 | P6: 06-05-2026 | Q6: =E6 -> 62-MUM-SSS | R6: =RIGHT(Q6,3) -> SSS | S6: AUG-26
A7: Invoice | B7: AUG-26 | C7: MR. CHETAN DIXIT | D7: Kannur-New Delhi | E7: 62-MUM-SSS | F7: SG0506 | G7: Airways Ticket | H7: Airticket | I7: 19804 | J7: DW26/780625 | K7: 16-AUG-2026 | L7: 80003 | M7: =CONCATENATE(L7,"-",E7) -> 80003-62-MUM-SSS | N7: =CONCATENATE(H7," ",C7,"-",F7,"-",B7,"-",P7,"-",D7) -> Airticket MR. CHETAN DIXIT-SG0506-AUG-26-06-05-2026-Kannur-New Delhi | O7: V03136 | P7: 06-05-2026 | Q7: =E7 -> 62-MUM-SSS | R7: =RIGHT(Q7,3) -> SSS | S7: AUG-26
A8: Invoice | B8: AUG-26 | C8: MR. ABDUL MAJID FAROOQI | D8: New Delhi-Mumbai/Mumbai-Kannur | E8: 62-MUM-SSS | F8: CQ00873076 | G8: Airways Ticket | H8: Airticket | I8: 11540 | J8: DW26/781991 | K8: 16-AUG-2026 | L8: 80003 | M8: =CONCATENATE(L8,"-",E8) -> 80003-62-MUM-SSS | N8: =CONCATENATE(H8," ",C8,"-",F8,"-",B8,"-",P8,"-",D8) -> Airticket MR. ABDUL MAJID FAROOQI-CQ00873076-AUG-26-06-05-2026-New Delhi-Mumbai/Mumbai-Kannur | O8: V03136 | P8: 06-05-2026 | Q8: =E8 -> 62-MUM-SSS | R8: =RIGHT(Q8,3) -> SSS | S8: AUG-26
A9: Invoice | B9: AUG-26 | C9: MR. ABDUL MAJID FAROOQI | D9: Kannur-New Delhi | E9: 62-MUM-SSS | F9: CQ00873076 | G9: Airways Ticket | H9: Airticket | I9: 19450 | J9: DW26/781403 | K9: 16-AUG-2026 | L9: 80003 | M9: =CONCATENATE(L9,"-",E9) -> 80003-62-MUM-SSS | N9: =CONCATENATE(H9," ",C9,"-",F9,"-",B9,"-",P9,"-",D9) -> Airticket MR. ABDUL MAJID FAROOQI-CQ00873076-AUG-26-06-05-2026-Kannur-New Delhi | O9: V03136 | P9: 06-05-2026 | Q9: =E9 -> 62-MUM-SSS | R9: =RIGHT(Q9,3) -> SSS | S9: AUG-26
A10: Invoice | B10: AUG-26 | C10: MR. SHANTANU ROOJ | D10: Mumbai-Kolkata | E10: 68-MUM-LED | F10: SG0014 | G10: Airways Ticket | H10: Airticket | I10: 8756 | J10: DW26/785455 | K10: 17-AUG-2026 | L10: 80003 | M10: =CONCATENATE(L10,"-",E10) -> 80003-68-MUM-LED | N10: =CONCATENATE(H10," ",C10,"-",F10,"-",B10,"-",P10,"-",D10) -> Airticket MR. SHANTANU ROOJ-SG0014-AUG-26-06-05-2026-Mumbai-Kolkata | O10: V03136 | P10: 06-05-2026 | Q10: =E10 -> 68-MUM-LED | R10: =RIGHT(Q10,3) -> LED | S10: AUG-26
A11: Invoice | B11: AUG-26 | C11: MR. SHANTANU ROOJ | D11: Kolkata-Mumbai | E11: 68-MUM-LED | F11: SG0014 | G11: Airways Ticket | H11: Airticket | I11: 9283 | J11: DW26/783895 | K11: 17-AUG-2026 | L11: 80003 | M11: =CONCATENATE(L11,"-",E11) -> 80003-68-MUM-LED | N11: =CONCATENATE(H11," ",C11,"-",F11,"-",B11,"-",P11,"-",D11) -> Airticket MR. SHANTANU ROOJ-SG0014-AUG-26-06-05-2026-Kolkata-Mumbai | O11: V03136 | P11: 06-05-2026 | Q11: =E11 -> 68-MUM-LED | R11: =RIGHT(Q11,3) -> LED | S11: AUG-26
A12: Invoice | B12: AUG-26 | C12: MR. ROSHAN DEEPAK PINTO | D12: New Delhi-Bangalore | E12: 67-MUM-ELO | F12: T11294 | G12: Airways Ticket | H12: Airticket | I12: 9076 | J12: DW26/785429 | K12: 17-AUG-2026 | L12: 80003 | M12: =CONCATENATE(L12,"-",E12) -> 80003-67-MUM-ELO | N12: =CONCATENATE(H12," ",C12,"-",F12,"-",B12,"-",P12,"-",D12) -> Airticket MR. ROSHAN DEEPAK PINTO-T11294-AUG-26-06-05-2026-New Delhi-Bangalore | O12: V03136 | P12: 06-05-2026 | Q12: =E12 -> 67-MUM-ELO | R12: =RIGHT(Q12,3) -> ELO | S12: AUG-26
A13: Invoice | B13: AUG-26 | C13: MR. ROSHAN DEEPAK PINTO | D13: Bangalore-New Delhi | E13: 67-MUM-ELO | F13: T11294 | G13: Airways Ticket | H13: Airticket | I13: 9505 | J13: DW26/784868 | K13: 17-AUG-2026 | L13: 80003 | M13: =CONCATENATE(L13,"-",E13) -> 80003-67-MUM-ELO | N13: =CONCATENATE(H13," ",C13,"-",F13,"-",B13,"-",P13,"-",D13) -> Airticket MR. ROSHAN DEEPAK PINTO-T11294-AUG-26-06-05-2026-Bangalore-New Delhi | O13: V03136 | P13: 06-05-2026 | Q13: =E13 -> 67-MUM-ELO | R13: =RIGHT(Q13,3) -> ELO | S13: AUG-26
... A107: Credit Note | B107: AUG-26 | C107: Ms. Deepti Deepti | D107: Madhya Pradesh | E107: 61-MUM-USE | F107: T17404 | G107: Hotel | H107: Credit | I107: 7879 | J107: HR26/19678 | K107: 31-08-2026 12:00:00 AM | L107: 80003 | M107: =CONCATENATE(L107,"-",E107) -> 80003-61-MUM-USE | N107: =CONCATENATE(H107," ",C107,"-",F107,"-",B107,"-",P107,"-",D107) -> Credit Ms. Deepti Deepti-T17404-AUG-26-06-05-2026-Madhya Pradesh | O107: V03136 | P107: 06-05-2026 | Q107: =E107 -> 61-MUM-USE | R107: =RIGHT(Q107,3) -> USE | S107: AUG-26

Sheet DOMESTIC CREDIT
A1: Domestic Air Travel Cancellation Statement for the period 16-08-2026 to 31-08-2026
A3: Refund Reference No. | B3: Refund Reference Date | C3: Cancellation Date | D3: Reference No. | E3: Department | F3: Location | G3: Passenger Name | H3: Employee Code | I3: Cost Center | J3: Cost Code | K3: Product Line | L3: Travel Date | M3: Sector | N3: Airline | O3: Flight No. | P3: Class | Q3: Ticket No. | R3: Taxable Fare | S3: Exempt Fare | T3: Other Taxes | U3: Airline GST | V3: Total Fare | W3: Xxln Charges | X3: Refund Amount | Y3: Service Chrgs towards xxln | Z3: Corporate | AA3: Business Unit | AB3: Booking Reference No. | AC3: Trip Unique ID | AD3: Designation | AE3: Type Of Journey | AF3: Type of Travel | AG3: Job Band | AH3: Passenger Email Id | AI3: Booking Code | AJ3: Cancellation Reason | AK3: Request No. | AL3: Request Created Date | AM3: Request Created Time | AN3: YQ | AO3: YR | AP3: Trip Title | AQ3: Fare Type | AR3: Purpose of Visit | AS3: GST No. | AT3: GST State | AU3: Full Ticket No. | AV3: Airline PNR | AW3: XL Code | AX3: Project | AY3: HSN Code | AZ3: Only Travel Date | BA3: Requester Name | BB3: Requester Empid | BC3: AIR IGST | BD3: AIR CGST | BE3: AIR SGST | BF3: Carbon Emission (Metric Tonnes) | BG3: TR ID | BH3: Debit Cost Code | BI3: Function | BJ3: Approver name | BK3: Approver Status | BL3: Source Destination City | BM3: Referred By | BN3: GL Code | BO3: Job Type | BP3: Division Name | BQ3: k3 | BR3: SAP / HR Company Code | BS3: Adani Legal Entity GST Number | BT3: Location Code | BU3: Reissue Invoice No | BV3: Unique ID | BW3: Job Reason | BX3: CC_AUTHCODE | BY3: SOURCE_CITY | BZ3: DESTINATION_CITY | CA3: MILES | CB3: Zone
A4: DZ26/137382 | B4: 16-08-2026 12:00:00 AM | C4: 16-08-2026 11:53:15 AM | D4: DW26/774287 | E4: University B2C | F4: Bengaluru | G4: MR. PREETISH GUPTA | H4: SG0516 | I4: 3701618 | J4: 62-MUM-SSS | L4: 17-08-2026 05:55:00 | M4: Mumbai-Ahmedabad | N4: Indigo | O4: 6E-5144 | P4: Economy | Q4: T8PWRS | R4: 16960 | S4: 0 | T4: 444 | U4: 848 | V4: 18252 | W4: 499 | X4: 17753 | Y4: 0 | Z4: Teamlease Services Ltd | AA4: TLEdtech | AB4: 200117917085 | AC4: 1388534 | AD4: Associate Sales Director | AE4: One Way | AF4: Domestic | AG4: L9 | AH4: preetish.gupta@teamlease.com | AI4: Y | AJ4: CANCEL:change in plan | AK4: 44681994 | AL4: 14-AUG-2026 | AM4: 11:06 | AN4: 275 | AO4: 0 | AQ4: CORPORATE | AR4: Official | AS4: 29AAPCS2871R1Z7 | AT4: Karnataka | AU4: T8PWRS | AV4: T8PWRS | AW4: T004S | AX4: - | AY4: 996425 | AZ4: 17-08-202/ | BA4: Mr. Satyavan Sawant | BB4: T17247 | BC4: 848 | BD4: 0 | BE4: 0 | BF4: 0.10916628 | BJ4: Mr. UDITENDU BOSE | BK4: Approved | BR4: TeamLease Edtech Limited | BS4: 29AAPCS2871R1Z7 | BV4: '11791708508170555 | BY4: BOM | BZ4: AMD | CA4: 442
A5: DZ26/137376 | B5: 16-08-2026 12:00:00 AM | C5: 16-08-2026 04:41:07 PM | D5: DW26/781796 | E5: Administration | F5: Delhi | G5: MR. ABDUL FAROOQI | H5: CQ00873076 | I5: NA | J5: NA | L5: 19-08-2026 09:30:00/19-08-2026 13:35:00 | M5: New Delhi-Mumbai/Mumbai-Kannur | N5: Indigo/Indigo | O5: 6E-6107/6E-2011 | P5: Economy | Q5: SH8JWH | R5: 9800 | S5: 0 | T5: 382 | U5: 490 | V5: 10672 | W5: 199 | X5: 10473 | Y5: 0 | Z5: Teamlease Services Ltd | AA5: TLEdtech | AB5: 200117939473 | AC5: 7582416 | AD5: Consultant | AE5: Round Trip | AF5: Domestic | AG5: Consultant | AH5: majid@jamiahamdard.ac.in | AI5: R/R | AJ5: CANCEL:name correction/CANCEL:name correction | AK5: 44715674 | AL5: 16-AUG-2026 | AM5: 12:00 | AN5: 1000 | AO5: 0 | AQ5: CORPORATE | AR5: Official | AS5: 27AAPCS2871R1ZB | AT5: Maharashtra | AU5: SH8JWH | AV5: SH8JWH | AW5: T004S | AX5: - | AY5: 996425 | AZ5: 19-08-202//19-08-20 | BA5: Mr. Satyavan Sawant | BB5: T17247 | BC5: 490 | BD5: 0 | BE5: 0 | BF5: 0.3157343 | BJ5: Ms. Priyanka Thakur | BK5: Approved | BR5: TeamLease Edtech Limited | BS5: 27AAPCS2871R1ZB | BV5: '11793947308190930/11793947308191335 | BY5: DEL | BZ5: CNN | CA5: 1139/848
A6: DZ26/137469 | B6: 16-08-2026 12:00:00 AM | C6: 16-08-2026 04:41:07 PM | D6: DW26/782230 | E6: Administration | F6: Delhi | G6: MR. ABDUL FAROOQI | H6: CQ00873076 | I6: NA | J6: NA | L6: 22-08-2026 22:45:00 | M6: Kannur-New Delhi | N6: Indigo | O6: 6E-6148 | P6: Economy | Q6: ZD8CPG | R6: 17160 | S6: 0 | T6: 1432 | U6: 858 | V6: 19450 | W6: 199 | X6: 19251 | Y6: 0 | Z6: Teamlease Services Ltd | AA6: TLEdtech | AB6: 200117939474 | AC6: 7582416 | AD6: Consultant | AE6: Round Trip | AF6: Domestic | AG6: Consultant | AH6: majid@jamiahamdard.ac.in | AI6: H | AJ6: CANCEL:name correction | AK6: 44715674 | AL6: 16-AUG-2026 | AM6: 12:00 | AN6: 800 | AO6: 0 | AQ6: CORPORATE | AR6: Official | AS6: 27AAPCS2871R1ZB | AT6: Maharashtra | AU6: ZD8CPG | AV6: ZD8CPG | AW6: T004S | AX6: - | AY6: 996425 | AZ6: 22-08-202/ | BA6: Mr. Satyavan Sawant | BB6: T17247 | BC6: 858 | BD6: 0 | BE6: 0 | BF6: 0.2952362 | BJ6: Ms. Priyanka Thakur | BK6: Approved | BR6: TeamLease Edtech Limited | BS6: 27AAPCS2871R1ZB | BV6: '11793947408222245 | BY6: CNN | BZ6: DEL | CA6: 1858
A7: DZ26/140066 | B7: 18-08-2026 12:00:00 AM | C7: 18-08-2026 11:32:54 PM | D7: DW26/796548 | E7: Operations | F7: Bengaluru | G7: MR. AAYUSH LAL | H7: T16161 | J7: 69-MUM-PBP | L7: 19-08-2026 14:30:00 | M7: New Delhi-Chennai | N7: SpiceJet | O7: SG-9300 | P7: Economy | Q7: FFKVQD | R7: 7760 | S7: 0 | T7: 378 | U7: 388 | V7: 8526 | W7: 198 | X7: 8328 | Y7: 0 | Z7: Teamlease Services Ltd | AA7: TLEdtech | AB7: 200117970807 | AC7: 3937212 | AD7: Senior Project Manager | AE7: Round Trip | AF7: Domestic | AG7: L7 | AH7: aayush.lal@teamlease.com | AI7: W | AJ7: CANCEL:Flight Timing has been rescheduled. | AK7: 44725527 | AL7: 18-AUG-2026 | AM7: 10:31 | AN7: 699 | AO7: 0 | AQ7: CORPORATE | AR7: Official | AS7: 29AAPCS2871R1Z7 | AT7: Karnataka | AU7: FFKVQD | AV7: FFKVQD | AW7: T004S | AX7: - | AY7: 996425 | AZ7: 19-08-202/ | BA7: Mr. AAYUSH LAL | BB7: T16161 | BC7: 388 | BD7: 0 | BE7: 0 | BF7: 0.279664 | BJ7: MS. NIDHI RAJESH BAGLA | BK7: Approved | BR7: TeamLease Edtech Limited | BS7: 29AAPCS2871R1Z7 | BV7: '11797080708191430 | BY7: DEL | BZ7: MAA | CA7: 1760
A8: DZ26/140351 | B8: 19-08-2026 12:00:00 AM | C8: 19-08-2026 12:20:32 PM | D8: DW26/783895 | E8: Leadership | F8: Bengaluru | G8: MR. SHANTANU ROOJ | H8: SG0014 | I8: 3701618 | J8: 68-MUM-LED | L8: 26-08-2026 18:45:00 | M8: Kolkata-Mumbai | N8: Indigo | O8: 6E-5128 | P8: Economy | Q8: BYCZRJ | R8: 7920 | S8: 0 | T8: 967 | U8: 396 | V8: 9283 | W8: 199 | X8: 9084 | Y8: 0 | Z8: Teamlease Services Ltd | AA8: TLEdtech | AB8: 200117956567 | AC8: 1388000 | AD8: Founder and CEO | AE8: Round Trip | AF8: Domestic | AG8: LST | AH8: shantanu@teamlease.com | AI8: Q | AJ8: CANCEL:Meeting cancelled | AK8: 44739307 | AL8: 17-AUG-2026 | AM8: 14:38 | AN8: 800 | AO8: 0 | AQ8: CORPORATE | AR8: Official | AS8: 29AAPCS2871R1Z7 | AT8: Karnataka | AU8: BYCZRJ | AV8: BYCZRJ | AW8: T004S | AX8: - | AY8: 996425 | AZ8: 26-08-202/ | BA8: Mr. Shantanu Rooj | BB8: SG0014 | BC8: 396 | BD8: 0 | BE8: 0 | BF8: 0.2645685 | BJ8: Mr. Shantanu Rooj | BK8: Approved | BR8: TeamLease Edtech Limited | BS8: 29AAPCS2871R1Z7 | BV8: '11795656708261845 | BY8: CCU | BZ8: BOM | CA8: 1665
A9: DZ26/140545 | B9: 19-08-2026 12:00:00 AM | C9: 19-08-2026 12:20:32 PM | D9: DW26/785455 | E9: Leadership | F9: Bengaluru | G9: MR. SHANTANU ROOJ | H9: SG0014 | I9: 3701618 | J9: 68-MUM-LED | L9: 26-08-2026 07:45:00 | M9: Mumbai-Kolkata | N9: Indigo | O9: 6E-5329 | P9: Economy | Q9: K6J34F | R9: 7920 | S9: 0 | T9: 440 | U9: 396 | V9: 8756 | W9: 199 | X9: 8557 | Y9: 0 | Z9: Teamlease Services Ltd | AA9: TLEdtech | AB9: 200117956566 | AC9: 1388000 | AD9: Founder and CEO | AE9: Round Trip | AF9: Domestic | AG9: LST | AH9: shantanu@teamlease.com | AI9: Q | AJ9: CANCEL:Meeting cancelled | AK9: 44739307 | AL9: 17-AUG-2026 | AM9: 14:38 | AN9: 800 | AO9: 0 | AQ9: CORPORATE | AR9: Official | AS9: 29AAPCS2871R1Z7 | AT9: Karnataka | AU9: K6J34F | AV9: K6J34F | AW9: T004S | AX9: - | AY9: 996425 | AZ9: 26-08-202/ | BA9: Mr. Shantanu Rooj | BB9: SG0014 | BC9: 396 | BD9: 0 | BE9: 0 | BF9: 0.2645685 | BJ9: Mr. Shantanu Rooj | BK9: Approved | BR9: TeamLease Edtech Limited | BS9: 29AAPCS2871R1Z7 | BV9: '11795656608260745 | BY9: BOM | BZ9: CCU | CA9: 1665
A10: DE26/457846 | B10: 19-08-2026 12:00:00 AM | C10: 19-08-2026 05:10:10 PM | D10: DA26/181264 | E10: University B2C | F10: Bengaluru | G10: MR. UDITENDU BOSE | H10: SG0320 | I10: 3701618 | J10: 62-MUM-SSS | L10: 24-08-2026 10:30:00 | M10: Kolkata-Mumbai | N10: Air India | O10: AI-2772 | P10: Economy | Q10: 5808907262 | R10: 7840 | S10: 0 | T10: 967 | U10: 392 | V10: 9199 | W10: 249 | X10: 8950 | Y10: 0 | Z10: Teamlease Services Ltd | AA10: TLEdtech | AB10: 200117997990 | AC10: 1388087 | AD10: Vice President - Consumer Sales | AE10: Round Trip | AF10: Domestic | AG10: L10 | AH10: uditendu.bose@teamlease.com | AI10: T | AJ10: CANCEL:Due to change in plan | AK10: 44798324 | AL10: 19-AUG-2026 | AM10: 13:59 | AN10: 749 | AO10: 170 | AQ10: CORPORATE | AR10: Official | AS10: 29AAPCS2871R1Z7 | AT10: Karnataka | AU10: 985808907262 | AV10: ETRM8B | AW10: T004S | AX10: - | AY10: 996425 | AZ10: 24-08-202/ | BA10: Ms. Priyanka Thakur | BB10: T16868 | BC10: 0 | BD10: 0 | BE10: 0 | BF10: 0.2645685 | BJ10: Mr. Shantanu Rooj | BK10: Approved | BR10: TeamLease Edtech Limited | BS10: 29AAPCS2871R1Z7 | BV10: '11799799008241030 | BY10: CCU | BZ10: BOM | CA10: 1665
A11: DZ26/141702 | B11: 20-08-2026 12:00:00 AM | C11: 20-08-2026 04:36:43 PM | D11: DW26/799382 | E11: Leadership | F11: Bengaluru | G11: MR. SHANTANU ROOJ | H11: SG0014 | I11: 3701618 | J11: 68-MUM-LED | L11: 21-08-2026 20:45:00 | M11: New Delhi-Mumbai | N11: Indigo | O11: 6E-0853 | P11: Economy | Q11: K9PBJM | R11: 7560 | S11: 0 | T11: 485 | U11: 378 | V11: 8423 | W11: 199 | X11: 8224 | Y11: 0 | Z11: Teamlease Services Ltd | AA11: TLEdtech | AB11: 200118001834 | AC11: 1388000 | AD11: Founder and CEO | AE11: Round Trip | AF11: Domestic | AG11: LST | AH11: shantanu@teamlease.com | AI11: O | AJ11: CANCEL:Need to take a later flight as one more meeting has come up | AK11: 44809720 | AL11: 19-AUG-2026 | AM11: 18:30 | AN11: 600 | AO11: 0 | AQ11: CORPORATE | AR11: Official | AS11: 29AAPCS2871R1Z7 | AT11: Karnataka | AU11: K9PBJM | AV11: K9PBJM | AW11: T004S | AX11: - | AY11: 996425 | AZ11: 21-08-202/ | BA11: Mr. Shantanu Rooj | BB11: SG0014 | BC11: 378 | BD11: 0 | BE11: 0 | BF11: 0.1809871 | BJ11: Mr. Shantanu Rooj | BK11: Approved | BR11: TeamLease Edtech Limited | BS11: 29AAPCS2871R1Z7 | BV11: '11800183408212045 | BY11: DEL | BZ11: BOM | CA11: 1139
A12: DZ26/143941 | B12: 22-08-2026 12:00:00 AM | C12: 22-08-2026 03:19:21 PM | D12: DW26/817440 | E12: Operations | F12: Bengaluru | G12: MR. PRATHAMESH JADHAV | H12: T16692 | J12: 62-MUM-PBO | L12: 27-08-2026 16:40:00 | M12: Chennai-Mumbai | N12: Indigo | O12: 6E-5104 | P12: Economy | Q12: K6M28F | R12: 7800 | S12: 0 | T12: 805 | U12: 390 | V12: 8995 | W12: 199 | X12: 8796 | Y12: 0 | Z12: Teamlease Services Ltd | AA12: TLEdtech | AB12: 200118042397 | AC12: 5246483 | AD12: Manager | AE12: Round Trip | AF12: Domestic | AG12: L6 | AH12: prathamesh.jadhav@teamlease.com | AI12: P | AJ12: CANCEL:Plan cancelled for the trip. | AK12: 44855536 | AL12: 21-AUG-2026 | AM12: 16:04 | AN12: 600 | AO12: 0 | AQ12: CORPORATE | AR12: Official | AS12: 29AAPCS2871R1Z7 | AT12: Karnataka | AU12: K6M28F | AV12: K6M28F | AW12: T004S | AX12: - | AY12: 996425 | AZ12: 27-08-202/ | BA12: Mr. Prathamesh JADHAV | BB12: T16692 | BC12: 390 | BD12: 0 | BE12: 0 | BF12: 0.1643026 | BJ12: MS. NIDHI RAJESH BAGLA | BK12: Approved | BR12: TeamLease Edtech Limited | BS12: 29AAPCS2871R1Z7 | BV12: '11804239708271640 | BY12: MAA | BZ12: BOM | CA12: 1034
A13: DZ26/144146 | B13: 22-08-2026 12:00:00 AM | C13: 22-08-2026 03:19:21 PM | D13: DW26/818413 | E13: Operations | F13: Bengaluru | G13: MR. PRATHAMESH JADHAV | H13: T16692 | J13: 62-MUM-PBO | L13: 23-08-2026 17:25:00 | M13: Mumbai-Chennai | N13: Indigo | O13: 6E-5048 | P13: Economy | Q13: V5S74Y | R13: 8260 | S13: 0 | T13: 436 | U13: 413 | V13: 9109 | W13: 199 | X13: 8910 | Y13: 0 | Z13: Teamlease Services Ltd | AA13: TLEdtech | AB13: 200118042396 | AC13: 5246483 | AD13: Manager | AE13: Round Trip | AF13: Domestic | AG13: L6 | AH13: prathamesh.jadhav@teamlease.com | AI13: J | AJ13: CANCEL:Plan cancelled for the trip. | AK13: 44855536 | AL13: 21-AUG-2026 | AM13: 16:04 | AN13: 600 | AO13: 0 | AQ13: CORPORATE | AR13: Official | AS13: 29AAPCS2871R1Z7 | AT13: Karnataka | AU13: V5S74Y | AV13: V5S74Y | AW13: T004S | AX13: - | AY13: 996425 | AZ13: 23-08-202/ | BA13: Mr. Prathamesh JADHAV | BB13: T16692 | BC13: 413 | BD13: 0 | BE13: 0 | BF13: 0.1643026 | BJ13: MS. NIDHI RAJESH BAGLA | BK13: Approved | BR13: TeamLease Edtech Limited | BS13: 29AAPCS2871R1Z7 | BV13: '11804239608231725 | BY13: BOM | BZ13: MAA | CA13: 1034
A14: DZ26/147806 | B14: 26-08-2026 12:00:00 AM | C14: 26-08-2026 10:50:24 AM | D14: DW26/817320 | E14: Operations | F14: Bengaluru | G14: MRS. SRIMATHI R | H14: SG0444 | I14: 3701618 | J14: 61-MUM-ASO | L14: 02-09-2026 16:15:00 | M14: Gwalior-Mumbai | N14: Indigo | O14: 6E-5265 | P14: Economy | Q14: IE8PPA | R14: 6780 | S14: 0 | T14: 1136 | U14: 339 | V14: 8255 | W14: 199 | X14: 8056 | Y14: 0 | Z14: Teamlease Services Ltd | AA14: TLEdtech | AB14: 200118040753 | AC14: 1388479 | AD14: Head - University Operations | AE14: Round Trip | AF14: Domestic | AG14: L10 | AH14: srimathi.krishnan@teamlease.com | AI14: V | AJ14: CANCEL:Official plans change | AK14: 44856343 | AL14: 21-AUG-2026 | AM14: 16:31 | AN14: 400 | AO14: 0 | AQ14: CORPORATE | AR14: Official | AS14: 29AAPCS2871R1Z7 | AT14: Karnataka | AU14: IE8PPA | AV14: IE8PPA | AW14: T004S | AX14: - | AY14: 996425 | AZ14: 02-09-202/ | BA14: Mrs. SRIMATHI R | BB14: SG0444 | BC14: 339 | BD14: 0 | BE14: 0 | BF14: 0.1544508 | BJ14: Mr. JAIDEEP KEWALRAMANI | BK14: Approved | BR14: TeamLease Edtech Limited | BS14: 29AAPCS2871R1Z7 | BV14: '11804075309021615 | BY14: GWL | BZ14: BOM | CA14: 972
A15: Total | R15: =SUM(R4:R14) -> 105760 | S15: =SUM(S4:S14) -> 0 | T15: =SUM(T4:T14) -> 7872 | U15: =SUM(U4:U14) -> 5288 | V15: =SUM(V4:V14) -> 118920 | W15: =SUM(W4:W14) -> 2538 | X15: =SUM(X4:X14) -> 116382 | Y15: =SUM(Y4:Y14) -> 0

Sheet RAIL CREDIT
A1: Rail Travel Cancellation Statement for the period 16-08-2026 to 31-08-2026
A3: Refund Reference No. | B3: Refund Reference Date | C3: Cancel Date | D3: Reference No. | E3: Department | F3: Location | G3: Passenger Name | H3: Employee Code | I3: Cost Center | J3: Cost Code | K3: Travel Date | L3: Sector | M3: Train | N3: Class | O3: PNR No. | P3: Total Fare | Q3: Xxln Charges | R3: Refund Amount | S3: Travel Mgmt Fee | T3: Corporate | U3: Business Unit | V3: Booking Reference No. | W3: Self Arranged | X3: Request No. | Y3: Request Created Date | Z3: Purpose of Visit | AA3: Train Quota | AB3: Sector Short | AC3: Trip Title | AD3: State Name | AE3: XL Code | AF3: Job Band | AG3: KM | AH3: Function | AI3: TR ID | AJ3: Debit Cost Code | AK3: Referred By | AL3: GL Code | AM3: Job Type | AN3: SAP / HR Company Code | AO3: Adani Legal Entity GST Number | AP3: Unique ID | AQ3: GST_NO | AR3: Job Reason
A4: LZ26/17613 | B4: 18-AUG-2026 | C4: 18-AUG-2026 | D4: LW26/154375 | E4: University Bd | F4: Bengaluru | G4: MR. NAKUL JOSHI | H4: T15226 | J4: 61-MUM-USE | K4: 18-AUG-2026 | L4: MUMBAI CENTRAL - MMCT-VADODARA JN - BRC | M4: VANDE BHARAT EXP | N4: CC | O4: 8252233853 | P4: 1144 | Q4: 149 | R4: 995 | S4: 0 | T4: TLSL | U4: TLEdtech | V4: 600117932495 | W4: N | X4: 44666082 | Y4: 13-08-2026 04:42:02 PM | Z4: Official | AA4: GENERAL | AB4: MMCT-BRC | AC4: Rail Service | AD4: Karnataka | AE4: T004S | AF4: L7 | AG4: 392 | AN4: TeamLease Edtech Limited | AO4: 29AAPCS2871R1Z7 | AP4: '11793249502413020 | AQ4: 29AAPCS2871R1Z7
A5: Total | P5: =SUM(P4:P4) -> 1144 | Q5: =SUM(Q4:Q4) -> 149 | R5: =SUM(R4:R4) -> 995 | S5: =SUM(S4:S4) -> 0

Sheet HOTEL CREDIT
A1: Hotel Cancellation Statement for the period 16-08-2026 to 31-08-2026
A3: Refund Reference No. | B3: Refund Reference Date | C3: Request No. | D3: Reference No. | E3: Reference Date | F3: Booking Reference No. | G3: Employee Id | H3: Employee Name | I3: Designation | J3: Cost Center | K3: Cost Code | L3: Check In Date | M3: Check Out Date | N3: No. of Rooms | O3: No. of Nights | P3: Hotel City | Q3: Hotel State | R3: Hotel Name | S3: Refund Amount | T3: Approver Name | U3: Approval Status | V3: Corporate | W3: Business Unit | X3: Purpose | Y3: Request Created Date | Z3: Purpose | AA3: Estimated Cost | AB3: Booking Status | AC3: Cancellation Reason | AD3: Cancel Date & Time | AE3: XL Code | AF3: Client GST No. | AG3: Project | AH3: Emp Grade | AI3: First Approver Name | AJ3: Second Approver Name | AK3: API Used | AL3: Department | AM3: Net Amount(Col AN - Col S) | AN3: Reference Amount | AO3: Cancel Status | AP3: Refund Applicability Date | AQ3: Cancellation Penalty | AR3: Base Fare | AS3: HCP_DISCOUNT_AMOUNT | AT3: BASE_LESS_HCP | AU3: GST | AV3: HCP_TAX_AMOUNT | AW3: GST_SUB_LESS_TAX | AX3: Extra Guest Charge | AY3: Hotel Service Charge | AZ3: Discount | BA3: Xxln Charges | BB3: TR ID | BC3: Debit Cost Code | BD3: Function | BE3: Referred By | BF3: GL Code | BG3: Job Type | BH3: Loction | BI3: Booking Id | BJ3: Division Name | BK3: SAP / HR Company Code | BL3: Adani Legal Entity GST Number | BM3: Agent Number | BN3: GST Assured | BO3: Hotel Type | BP3: Job Reason
A4: HR26/19078 | B4: 27-08-2026 12:00:00 AM | C4: 44856343 | D4: HW26/366258 | E4: 22-08-2026 12:00:00 AM | F4: 500118040754 | G4: SG0444 | H4: Mrs. Srimathi R | I4: Head - University Operations | J4: 3701618 | K4: 61-MUM-ASO | L4: 31-08-2026 02:00:00 PM | M4: 02-09-2026 12:00:00 PM | N4: 1 | O4: 2 | P4: Jhansi | Q4: Uttar Pradesh | R4: Nataraj Sarovar Portico | S4: 8081 | T4: Mr. JAIDEEP KEWALRAMANI | U4: Approved | V4: TLSL | W4: TLEdtech | X4: Official | Y4: 21-08-2026 12:00:00 AM | Z4: Official | AA4: 7901 | AB4: Cancelled | AC4: Quest Portal is not executing partial cancellation request . Hence as advised by Quest, cancelling it fully and doing a fresh booking for one night stay at Jhansi | AD4: 26-08-2026 02:50:55 PM | AE4: T004S | AF4: 27AAPCS2871R1ZB | AG4: - | AH4: L10 | AI4: Mr. JAIDEEP KEWALRAMANI | AK4: MMT | AL4: Operations | AM4: 0 | AN4: 8081 | AO4: Full | AP4: 29-AUG-2026 | AQ4: 0.05 | AR4: 8001 | AS4: 0 | AT4: 8001 | AU4: 400.05 | AV4: 0 | AW4: 400.05 | AX4: 0 | AY4: 0 | AZ4: 320 | BA4: 0.05 | BH4: Bengaluru | BI4: NH15247510997794 | BK4: TeamLease Edtech Limited | BL4: 27AAPCS2871R1ZB | BN4: Y | BO4: D
A5: HR26/19678 | B5: 31-08-2026 12:00:00 AM | C5: 45057696 | D5: HW26/385513 | E5: 31-08-2026 12:00:00 AM | F5: 500118176989 | G5: T17404 | H5: Ms. Deepti Deepti | I5: Assistant General Manager | K5: 61-MUM-USE | L5: 02-09-2026 12:00:00 PM | M5: 04-09-2026 10:00:00 AM | N5: 1 | O5: 2 | P5: Bhopal | Q5: Madhya Pradesh | R5: Hotel Insignia | S5: 7879 | T5: Mr. Shantanu Rooj | U5: Approved | V5: TLSL | W5: TLEdtech | X5: Official | Y5: 31-08-2026 12:00:00 AM | Z5: Official | AA5: 7487 | AB5: Cancelled | AC5: Due to change in plan | AD5: 31-08-2026 05:35:03 PM | AE5: T004S | AF5: 27AAPCS2871R1ZB | AG5: - | AH5: L8 | AI5: Mr. Shantanu Rooj | AK5: MMT | AL5: University Bd | AM5: 0 | AN5: 7879 | AO5: Full | AP5: 01-SEP-2026 | AQ5: 0.18 | AR5: 7839.22 | AS5: 0 | AT5: 7839.22 | AU5: 391.96 | AV5: 0 | AW5: 391.96 | AX5: 0 | AY5: 0 | AZ5: 352 | BA5: 0.18 | BH5: Bengaluru | BI5: NH19083513188468 | BK5: TeamLease Edtech Limited | BL5: 27AAPCS2871R1ZB | BN5: Y | BO5: D
A6: Total | S6: =SUM(S4:S5) -> 15960
